Workbook

Sheet Control Panel
A1: Health Plan Chat - Pricing Control Panel
A2: Every blue cell is editable. Everything else recalculates from them, on every tab. Change a price and watch section G and the Scenario and Sensitivity tabs move.
A4: LEGEND | B4: Edit me | C4: Formula | D4: Key output | E4: Assumption | F4: Red = gross margin under the floor in B52. Green = at or above it.
A6: A. COST TO SERVE
A7: Average minutes per conversation | B7: 3.5 | F7: Assumption. Voice calls and chat sessions blended.
A8: Blended cost per minute | B8: 0.14 | F8: Assumption. LLM + STT/TTS + telephony all-in. Synthflow retails $0.11-0.24/min.
A9: Marginal recording, storage and data per conversation | B9: 0.05 | F9: Assumption. Includes the CMS 10-year call retention obligation.
A10: COST PER CONVERSATION | B10: =B7*B8+B9 | F10: The most load-bearing number in this model.
A11: Fixed cost per account per month | B11: 43 | F11: Support, third-party and allocated overhead. Does not scale with usage.
A12: Target gross margin | B12: 0.7 | F12: Voice AI carries real variable COGS (inference and telephony), so it does not reach the generic 80% software benchmark at meaningful volume. 70% is the defensible target here. Raise it to 80% and the model will tell you the allowance has to fall to about 105 conversations.
A13: Reference conversations per month (for the floor) | B13: 180 | F13: Expected usage for a typical agency, NOT the 220 allowance. The allowance is a ceiling, not a forecast, so pricing the floor at the cap would over-price the product. Worst case at full allowance is shown on the Bottom-Up Model tab.
A14: Cost to serve at reference volume | B14: =B11+B13*B10
A15: FLOOR PRICE at target margin | B15: =B14/(1-B12) | F15: The Hero price must clear this.
A17: B. MARKET BAND (normalised to per agency per month)
A18: Synthflow (usage, estimated) | B18: 66 | F18: Estimated: published $0.11-0.24/min x ~375 min. Not a flat published price.
A19: Goodcall Scale tier | B19: 249 | F19: Source: Goodcall published pricing.
A20: Smith.ai Basic (90 calls) | B20: 600 | F20: Source: Smith.ai published pricing.
A21: careCycle (Medicare-native) | B21: 10000 | F21: Source: OPEN-FINDINGS OF-1, ~$10,000/mo for a 5-10 agent operation.
A22: Market low | B22: =MIN(B18:B21)
A23: Market median | B23: =MEDIAN(B18:B21)
A24: Market high | B24: =MAX(B18:B21) | F24: careCycle is an enterprise anomaly, not a target. It is the ceiling this segment is priced out of.
A26: C. VALUE CEILING
A27: Incremental enrollments per month - conservative | B27: 1
A28: Incremental enrollments per month - base | B28: 2
A29: Incremental enrollments per month - optimistic | B29: 4 | F29: Unconfirmed. Fair Square reported 4x after-hours conversion with AI voice.
A30: CMS initial commission per enrollment (2026, national) | B30: 694 | F30: Source: 2026 CMS Medicare Advantage commission release.
A31: Capture fraction | B31: 0.15 | F31: Methodology range 10-30%. 15% leaves most of the surplus with the customer.
A32: Annual value created (base case) | B32: =B28*B30*12
A33: VALUE CEILING per month (base case) | B33: =B32*B31/12 | F33: Year-one commissions only. Ignores renewals, so this is deliberately conservative.
A35: D. TIER PRICING (platform fee plus included usage)
A36: Tier | B36: Platform fee / mo | C36: Included conversations | D36: Effective $/conv | E36: Cost at full allowance | F36: Margin at full allowance
A37: Front Desk | B37: 199 | C37: 65 | D37: =B37/C37 | E37: =$B$11+C37*$B$10 | F37: =(B37-E37)/B37
A38: Plan Fluent | B38: 499 | C38: 220 | D38: =B38/C38 | E38: =$B$11+C38*$B$10 | F38: =(B38-E38)/B38
A39: Downline | B39: 1499 | C39: 750 | D39: =B39/C39 | E39: =$B$11+C39*$B$10 | F39: =(B39-E39)/B39
A41: E. USAGE OVERAGE BANDS (rate declines as volume grows)
A42: Band | B42: Applies up to (cumulative over allowance) | C42: Rate per conversation | D42: Margin at this rate
A43: Band 1 first 250 over | B43: 250 | C43: 1.45 | D43: =(C43-$B$10)/C43
A44: Band 2 next 750 | B44: 1000 | C44: 1.15 | D44: =(C44-$B$10)/C44
A45: Band 3 next 2,000 | B45: 3000 | C45: 0.95 | D45: =(C45-$B$10)/C45
A46: Band 4 beyond | B46: no limit | C46: 0.8 | D46: =(C46-$B$10)/C46
A47: Rates must fall down the bands, and Band 4 must stay above cost per conversation or heavy use loses money.
A48: F. GUARDRAILS AND BILLING
A49: Surge cap: maximum overage per month, as a multiple of platform fee | B49: 1.5 | F49: The answer to Smith.ai's billing-surprise complaints. Raise it to let revenue run; lower it to make bills safer.
A50: Annual billing discount on platform fee | B50: 0.15
A51: Prepaid commit discount on overage rates | B51: 0.1
A52: Gross margin floor (cells turn red below this) | B52: 0.55
A54: G. LIVE READOUT - gross margin at four utilisation levels
A55: Tier | B55: at 50% of allowance | C55: at 100% | D55: at 200% | E55: at 300% | F55: What to watch
A56: Front Desk | B56: =(($B$37+MIN((MIN(MAX(0,($C$37*0.5)-$C$37),$B$43)*$C$43+MIN(MAX(MAX(0,($C$37*0.5)-$C$37)-$B$43,0),$B$44-$B$43)*$C$44+MIN(MAX(MAX(0,($C$37*0.5)-$C$37)-$B$44,0),$B$45-$B$44)*$C$45+MAX(MAX(0,($C$37*0.5)-$C$37)-$B$45,0)*$C$46),$B$37*$B$49))-($B$11+($C$37*0.5)*$B$10))/($B$37+MIN((MIN(MAX(0,($C$37*0.5)-$C$37),$B$43)*$C$43+MIN(MAX(MAX(0,($C$37*0.5)-$C$37)-$B$43,0),$B$44-$B$43)*$C$44+MIN(MAX(MAX(0,($C$37*0.5)-$C$37)-$B$44,0),$B$45-$B$44)*$C$45+MAX(MAX(0,($C$37*0.5)-$C$37)-$B$45,0)*$C$46),$B$37*$B$49)) | C56: =(($B$37+MIN((MIN(MAX(0,($C$37*1.0)-$C$37),$B$43)*$C$43+MIN(MAX(MAX(0,($C$37*1.0)-$C$37)-$B$43,0),$B$44-$B$43)*$C$44+MIN(MAX(MAX(0,($C$37*1.0)-$C$37)-$B$44,0),$B$45-$B$44)*$C$45+MAX(MAX(0,($C$37*1.0)-$C$37)-$B$45,0)*$C$46),$B$37*$B$49))-($B$11+($C$37*1.0)*$B$10))/($B$37+MIN((MIN(MAX(0,($C$37*1.0)-$C$37),$B$43)*$C$43+MIN(MAX(MAX(0,($C$37*1.0)-$C$37)-$B$43,0),$B$44-$B$43)*$C$44+MIN(MAX(MAX(0,($C$37*1.0)-$C$37)-$B$44,0),$B$45-$B$44)*$C$45+MAX(MAX(0,($C$37*1.0)-$C$37)-$B$45,0)*$C$46),$B$37*$B$49)) | D56: =(($B$37+MIN((MIN(MAX(0,($C$37*2.0)-$C$37),$B$43)*$C$43+MIN(MAX(MAX(0,($C$37*2.0)-$C$37)-$B$43,0),$B$44-$B$43)*$C$44+MIN(MAX(MAX(0,($C$37*2.0)-$C$37)-$B$44,0),$B$45-$B$44)*$C$45+MAX(MAX(0,($C$37*2.0)-$C$37)-$B$45,0)*$C$46),$B$37*$B$49))-($B$11+($C$37*2.0)*$B$10))/($B$37+MIN((MIN(MAX(0,($C$37*2.0)-$C$37),$B$43)*$C$43+MIN(MAX(MAX(0,($C$37*2.0)-$C$37)-$B$43,0),$B$44-$B$43)*$C$44+MIN(MAX(MAX(0,($C$37*2.0)-$C$37)-$B$44,0),$B$45-$B$44)*$C$45+MAX(MAX(0,($C$37*2.0)-$C$37)-$B$45,0)*$C$46),$B$37*$B$49)) | E56: =(($B$37+MIN((MIN(MAX(0,($C$37*3.0)-$C$37),$B$43)*$C$43+MIN(MAX(MAX(0,($C$37*3.0)-$C$37)-$B$43,0),$B$44-$B$43)*$C$44+MIN(MAX(MAX(0,($C$37*3.0)-$C$37)-$B$44,0),$B$45-$B$44)*$C$45+MAX(MAX(0,($C$37*3.0)-$C$37)-$B$45,0)*$C$46),$B$37*$B$49))-($B$11+($C$37*3.0)*$B$10))/($B$37+MIN((MIN(MAX(0,($C$37*3.0)-$C$37),$B$43)*$C$43+MIN(MAX(MAX(0,($C$37*3.0)-$C$37)-$B$43,0),$B$44-$B$43)*$C$44+MIN(MAX(MAX(0,($C$37*3.0)-$C$37)-$B$44,0),$B$45-$B$44)*$C$45+MAX(MAX(0,($C$37*3.0)-$C$37)-$B$45,0)*$C$46),$B$37*$B$49)) | F56: Entry tier. Thin by design; its job is to make Plan Fluent obvious.
A57: Plan Fluent | B57: =(($B$38+MIN((MIN(MAX(0,($C$38*0.5)-$C$38),$B$43)*$C$43+MIN(MAX(MAX(0,($C$38*0.5)-$C$38)-$B$43,0),$B$44-$B$43)*$C$44+MIN(MAX(MAX(0,($C$38*0.5)-$C$38)-$B$44,0),$B$45-$B$44)*$C$45+MAX(MAX(0,($C$38*0.5)-$C$38)-$B$45,0)*$C$46),$B$38*$B$49))-($B$11+($C$38*0.5)*$B$10))/($B$38+MIN((MIN(MAX(0,($C$38*0.5)-$C$38),$B$43)*$C$43+MIN(MAX(MAX(0,($C$38*0.5)-$C$38)-$B$43,0),$B$44-$B$43)*$C$44+MIN(MAX(MAX(0,($C$38*0.5)-$C$38)-$B$44,0),$B$45-$B$44)*$C$45+MAX(MAX(0,($C$38*0.5)-$C$38)-$B$45,0)*$C$46),$B$38*$B$49)) | C57: =(($B$38+MIN((MIN(MAX(0,($C$38*1.0)-$C$38),$B$43)*$C$43+MIN(MAX(MAX(0,($C$38*1.0)-$C$38)-$B$43,0),$B$44-$B$43)*$C$44+MIN(MAX(MAX(0,($C$38*1.0)-$C$38)-$B$44,0),$B$45-$B$44)*$C$45+MAX(MAX(0,($C$38*1.0)-$C$38)-$B$45,0)*$C$46),$B$38*$B$49))-($B$11+($C$38*1.0)*$B$10))/($B$38+MIN((MIN(MAX(0,($C$38*1.0)-$C$38),$B$43)*$C$43+MIN(MAX(MAX(0,($C$38*1.0)-$C$38)-$B$43,0),$B$44-$B$43)*$C$44+MIN(MAX(MAX(0,($C$38*1.0)-$C$38)-$B$44,0),$B$45-$B$44)*$C$45+MAX(MAX(0,($C$38*1.0)-$C$38)-$B$45,0)*$C$46),$B$38*$B$49)) | D57: =(($B$38+MIN((MIN(MAX(0,($C$38*2.0)-$C$38),$B$43)*$C$43+MIN(MAX(MAX(0,($C$38*2.0)-$C$38)-$B$43,0),$B$44-$B$43)*$C$44+MIN(MAX(MAX(0,($C$38*2.0)-$C$38)-$B$44,0),$B$45-$B$44)*$C$45+MAX(MAX(0,($C$38*2.0)-$C$38)-$B$45,0)*$C$46),$B$38*$B$49))-($B$11+($C$38*2.0)*$B$10))/($B$38+MIN((MIN(MAX(0,($C$38*2.0)-$C$38),$B$43)*$C$43+MIN(MAX(MAX(0,($C$38*2.0)-$C$38)-$B$43,0),$B$44-$B$43)*$C$44+MIN(MAX(MAX(0,($C$38*2.0)-$C$38)-$B$44,0),$B$45-$B$44)*$C$45+MAX(MAX(0,($C$38*2.0)-$C$38)-$B$45,0)*$C$46),$B$38*$B$49)) | E57: =(($B$38+MIN((MIN(MAX(0,($C$38*3.0)-$C$38),$B$43)*$C$43+MIN(MAX(MAX(0,($C$38*3.0)-$C$38)-$B$43,0),$B$44-$B$43)*$C$44+MIN(MAX(MAX(0,($C$38*3.0)-$C$38)-$B$44,0),$B$45-$B$44)*$C$45+MAX(MAX(0,($C$38*3.0)-$C$38)-$B$45,0)*$C$46),$B$38*$B$49))-($B$11+($C$38*3.0)*$B$10))/($B$38+MIN((MIN(MAX(0,($C$38*3.0)-$C$38),$B$43)*$C$43+MIN(MAX(MAX(0,($C$38*3.0)-$C$38)-$B$43,0),$B$44-$B$43)*$C$44+MIN(MAX(MAX(0,($C$38*3.0)-$C$38)-$B$44,0),$B$45-$B$44)*$C$45+MAX(MAX(0,($C$38*3.0)-$C$38)-$B$45,0)*$C$46),$B$38*$B$49)) | F57: The Hero. Most customers should land here and it should hold margin across the range.
A58: Downline | B58: =(($B$39+MIN((MIN(MAX(0,($C$39*0.5)-$C$39),$B$43)*$C$43+MIN(MAX(MAX(0,($C$39*0.5)-$C$39)-$B$43,0),$B$44-$B$43)*$C$44+MIN(MAX(MAX(0,($C$39*0.5)-$C$39)-$B$44,0),$B$45-$B$44)*$C$45+MAX(MAX(0,($C$39*0.5)-$C$39)-$B$45,0)*$C$46),$B$39*$B$49))-($B$11+($C$39*0.5)*$B$10))/($B$39+MIN((MIN(MAX(0,($C$39*0.5)-$C$39),$B$43)*$C$43+MIN(MAX(MAX(0,($C$39*0.5)-$C$39)-$B$43,0),$B$44-$B$43)*$C$44+MIN(MAX(MAX(0,($C$39*0.5)-$C$39)-$B$44,0),$B$45-$B$44)*$C$45+MAX(MAX(0,($C$39*0.5)-$C$39)-$B$45,0)*$C$46),$B$39*$B$49)) | C58: =(($B$39+MIN((MIN(MAX(0,($C$39*1.0)-$C$39),$B$43)*$C$43+MIN(MAX(MAX(0,($C$39*1.0)-$C$39)-$B$43,0),$B$44-$B$43)*$C$44+MIN(MAX(MAX(0,($C$39*1.0)-$C$39)-$B$44,0),$B$45-$B$44)*$C$45+MAX(MAX(0,($C$39*1.0)-$C$39)-$B$45,0)*$C$46),$B$39*$B$49))-($B$11+($C$39*1.0)*$B$10))/($B$39+MIN((MIN(MAX(0,($C$39*1.0)-$C$39),$B$43)*$C$43+MIN(MAX(MAX(0,($C$39*1.0)-$C$39)-$B$43,0),$B$44-$B$43)*$C$44+MIN(MAX(MAX(0,($C$39*1.0)-$C$39)-$B$44,0),$B$45-$B$44)*$C$45+MAX(MAX(0,($C$39*1.0)-$C$39)-$B$45,0)*$C$46),$B$39*$B$49)) | D58: =(($B$39+MIN((MIN(MAX(0,($C$39*2.0)-$C$39),$B$43)*$C$43+MIN(MAX(MAX(0,($C$39*2.0)-$C$39)-$B$43,0),$B$44-$B$43)*$C$44+MIN(MAX(MAX(0,($C$39*2.0)-$C$39)-$B$44,0),$B$45-$B$44)*$C$45+MAX(MAX(0,($C$39*2.0)-$C$39)-$B$45,0)*$C$46),$B$39*$B$49))-($B$11+($C$39*2.0)*$B$10))/($B$39+MIN((MIN(MAX(0,($C$39*2.0)-$C$39),$B$43)*$C$43+MIN(MAX(MAX(0,($C$39*2.0)-$C$39)-$B$43,0),$B$44-$B$43)*$C$44+MIN(MAX(MAX(0,($C$39*2.0)-$C$39)-$B$44,0),$B$45-$B$44)*$C$45+MAX(MAX(0,($C$39*2.0)-$C$39)-$B$45,0)*$C$46),$B$39*$B$49)) | E58: =(($B$39+MIN((MIN(MAX(0,($C$39*3.0)-$C$39),$B$43)*$C$43+MIN(MAX(MAX(0,($C$39*3.0)-$C$39)-$B$43,0),$B$44-$B$43)*$C$44+MIN(MAX(MAX(0,($C$39*3.0)-$C$39)-$B$44,0),$B$45-$B$44)*$C$45+MAX(MAX(0,($C$39*3.0)-$C$39)-$B$45,0)*$C$46),$B$39*$B$49))-($B$11+($C$39*3.0)*$B$10))/($B$39+MIN((MIN(MAX(0,($C$39*3.0)-$C$39),$B$43)*$C$43+MIN(MAX(MAX(0,($C$39*3.0)-$C$39)-$B$43,0),$B$44-$B$43)*$C$44+MIN(MAX(MAX(0,($C$39*3.0)-$C$39)-$B$44,0),$B$45-$B$44)*$C$45+MAX(MAX(0,($C$39*3.0)-$C$39)-$B$45,0)*$C$46),$B$39*$B$49)) | F58: Top tier. If this dips, the included allowance is too generous.

Sheet Strategy
A1: Pricing Strategy (Phases 1-2)
A2: Beachhead is ICP-1. ICP-2 (GA / FMO downline) is served through the Downline tier as a sales-led, custom motion.
A4: Decision | B4: Rationale
A5: Goal balance | B5: Balanced, leaning to penetration over near-term yield. careCycle, the only competitor with comparable Medicare depth, prices a 5-10 agent operation at roughly $10,000 a month and so does not compete for this segment at all. Winning the beachhead matters more right now than maximising revenue per account.
A6: Stage (the When) | B6: MVP to early PMF. No paying cohort exists, so this price is a learning instrument, not a yield instrument. Expect to revise once design partner conversion and real usage data arrive.
A7: Beachhead (the Who) | B7: ICP-1: independent Medicare agencies, 3 to 10 licensed agents, $400K to $2.5M in annual commission revenue. Easy to service because the buyer is a single owner-operator with no committee and no procurement, and current share is zero.
A8: Sales motion | B8: Marketing and service led (farming) for Front Desk and Plan Fluent: buyers self-qualify through the Readiness Scorecard and the Benefit Answer Gap Report, then convert on a 72-hour sandbox. Plan document ingestion and CMS obligations need hand-holding, so this is not pure self-serve. Downline is sales led (hunting) and priced Contact sales.
A9: Strategic intent | B9: Differentiate, as a market shaker. The AI voice category is crowded and mature. Health Plan Chat niches into Medicare plan intelligence and follows the category's monthly subscription convention rather than resetting it.
A10: Denominator | B10: Per agency location per month, as a platform fee plus metered conversations. Not per seat: the value, always-on plan-grounded coverage, is shared across the whole office and does not scale with headcount. Not pure per-minute: unpredictable bills are the single loudest complaint against Smith.ai in the competitive research.
A11: Pricing basis | B11: Value based, floored on cost and referenced against the market band. Value based is the only basis that lets price track the plan-intelligence differentiator rather than commodity call-handling cost.
A12: Denominator x basis fit | B12: Pass. A location behaves like a device in the compatibility table and fits cost, market and value bases cleanly. Unlike a user, a location has a genuine, boundable cost to serve, so the floor is real.
A13: Usage vehicle | B13: Hybrid: a flat platform fee with an included conversation allowance, then declining-rate overage bands above it, capped each month by a surge multiple. The flat portion preserves the predictability the positioning promises; the metered portion makes revenue scale with the value delivered; the cap stops an AEP spike producing a frightening invoice.

Sheet Feature Matrix
A1: Feature Matrix (Phase 3)
A2: Demand and density carried from gtm/feature-scores.csv. OF-2 correction applied: row 25 density downgraded from 'only we' to 'a few do this'.
A4: # | B4: Capability | C4: Market demand | D4: Competitive density | E4: Zone | F4: Packaging role | G4: Marketing label | H4: Assigned tier
A5: 1 | B5: 24/7 AI voice answering for inbound calls | C5: All | D5: Commodity | E5: Table stakes | F5: Freemium-Lite | G5: Commoditized | H5: Decoy
A6: 2 | B6: Natural conversational voice interaction | C6: All | D6: Commodity | E6: Table stakes | F6: Freemium-Lite | G6: Commoditized | H6: Decoy
A7: 3 | B7: AI chatbot for website/portal | C7: Some | D7: Commodity | E7: Noise | F7: Drop-bury | G7: Outdated | H7: Excluded
A8: 4 | B8: Handles multiple calls simultaneously | C8: Most | D8: Commodity | E8: Table stakes | F8: Freemium-Lite | G8: Commoditized | H8: Decoy
A9: 5 | B9: Warm transfer/escalation to human agent | C9: All | D9: Most do this | E9: Table stakes | F9: Freemium-Lite | G9: Commoditized | H9: Decoy
A10: 6 | B10: After-hours lead capture | C10: All | D10: Commodity | E10: Table stakes | F10: Freemium-Lite | G10: Commoditized | H10: Decoy
A11: 7 | B11: Lead qualification before agent handoff | C11: Most | D11: Most do this | E11: Table stakes | F11: Freemium-Lite | G11: Commoditized | H11: Decoy
A12: 8 | B12: Call transcription & conversation summaries | C12: Most | D12: Most do this | E12: Table stakes | F12: Freemium-Lite | G12: Commoditized | H12: Decoy
A13: 9 | B13: Structured caller information captured for agent | C13: Most | D13: Most do this | E13: Table stakes | F13: Freemium-Lite | G13: Commoditized | H13: Decoy
A14: 10 | B14: Answers Medicare plan-specific questions | C14: All | D14: Only we do this | E14: Differentiator | F14: Premium-Hero | G14: Leading | H14: Hero
A15: 11 | B15: Understands plan benefits from plan documents | C15: All | D15: Only we do this | E15: Differentiator | F15: Premium-Hero | G15: Leading | H15: Hero
A16: 12 | B16: Answers benefits: dental, vision, hearing, transportation, OTC/flex | C16: All | D16: Only we do this | E16: Differentiator | F16: Premium-Hero | G16: Leading | H16: Hero
... A29: 25 | B29: Centralized deployment across agencies/downlines (Coming Soon) | C29: Some | D29: A few do this | E29: Niche | F29: Enterprise-Add-on | G29: Innovation | H29: Anchor
A31: Zone counts
A32: Table stakes | B32: 16
A33: Differentiator | B33: 6
A34: Niche | B34: 2
A35: Noise | B35: 1
A37: All six differentiators are the L3 Medicare plan-IP layer. No commodity feature reaches the differentiator zone, which is why the Hero tier is built on plan intelligence and nothing else.

Sheet Bottom-Up Model
A1: Bottom-Up Price Build (Phase 5)
A2: Floor, then market band, then value ceiling, then the Hero price inside them. Every input lives on the Control Panel; this tab only assembles them.
A4: LAYER 1 - COST FLOOR
A5: Cost per conversation | B5: ='Control Panel'!B10
A6: Fixed cost per account per month | B6: ='Control Panel'!B11
A7: Cost to serve at reference volume | B7: ='Control Panel'!B14
A8: Target gross margin | B8: ='Control Panel'!B12
A9: Floor price | B9: ='Control Panel'!B15 | F9: The Hero must clear this.
A11: LAYER 2 - MARKET BAND
A12: Market low | B12: ='Control Panel'!B22
A13: Market median | B13: ='Control Panel'!B23
A14: Market high | B14: ='Control Panel'!B24 | F14: careCycle. The anomaly this whole segment is priced out of.
A16: LAYER 3 - VALUE CEILING
A17: Value ceiling per month (base case) | B17: ='Control Panel'!B33 | F17: Year-one commissions only, so deliberately conservative. At MVP this sits below the floor, which is expected: price leans on floor and market until outcome data exists.
A19: HERO PRICE
A20: Lower bound | B20: =MAX(B9,B12)
A21: Upper bound | B21: =MAX(B17,B14)
A22: Chosen Hero price (Plan Fluent) | B22: ='Control Panel'!B38 | F22: A decision, not a formula. Edit it on the Control Panel.
A23: Gross margin at full allowance | B23: ='Control Panel'!F38
A24: Clears the floor? | B24: =IF(B22>=B9,"Yes","No - revise")
A25: Multiple below careCycle | B25: =B14/B22 | F25: The OF-1 wedge, quantified.
A27: DERIVED TIERS
A28: Front Desk (Decoy) | B28: ='Control Panel'!B37 | C28: ='Control Panel'!B37/'Control Panel'!B38 | D28: x Hero
A29: Downline (Anchor), reference | B29: ='Control Panel'!B39 | C29: ='Control Panel'!B39/'Control Panel'!B38 | D29: x Hero
A30: Methodology guide: Decoy 0.30-0.50x, Anchor 2.0-4.0x
A32: BILLING VIEW
B33: Monthly | C33: Annual (per mo.) | D33: Annual total
A34: Front Desk | B34: ='Control Panel'!B37 | C34: ='Control Panel'!B37*(1-'Control Panel'!$B$50) | D34: =C34*12
A35: Plan Fluent | B35: ='Control Panel'!B38 | C35: ='Control Panel'!B38*(1-'Control Panel'!$B$50) | D35: =C35*12
A36: Downline (from) | B36: ='Control Panel'!B39 | C36: ='Control Panel'!B39*(1-'Control Panel'!$B$50) | D36: =C36*12
A38: FLOOR SENSITIVITY - the floor moves with volume
A39: Scenario | B39: Conversations | C39: Cost to serve | D39: Floor at target margin | E39: Hero clears it? | F39: Note
A40: Expected usage (the pricing basis) | B40: ='Control Panel'!$B$13 | C40: ='Control Panel'!$B$11+B40*'Control Panel'!$B$10 | D40: =C40/(1-'Control Panel'!$B$12) | E40: =IF('Control Panel'!$B$38>=D40,"Yes","No") | F40: Priced here. This is what a typical agency actually uses.
A41: Full allowance (worst case) | B41: ='Control Panel'!$C$38 | C41: ='Control Panel'!$B$11+B41*'Control Panel'!$B$10 | D41: =C41/(1-'Control Panel'!$B$12) | E41: =IF('Control Panel'!$B$38>=D41,"Yes","No") | F41: Every account maxing its allowance. Margin at this point is shown on the Control Panel, section D.
A42: Double allowance | B42: ='Control Panel'!$C$38*2 | C42: ='Control Panel'!$B$11+B42*'Control Panel'!$B$10 | D42: =C42/(1-'Control Panel'!$B$12) | E42: =IF('Control Panel'!$B$38>=D42,"Yes","No") | F42: Overage revenue kicks in above the allowance, so margin recovers rather than collapsing.
A44: Read this honestly: the Hero clears the floor at expected usage, which is the right basis, because the included allowance is a cap rather than a forecast. At full allowance the gross margin is about 68%, a little under the 70% target. That is an accepted trade: predictability is the positioning, and an allowance tight enough to hold 80% would put a typical agency into overage every single month and break the promise the pricing is built on.

Sheet Usage Rate Card
A1: Usage Rate Card - the scalable vehicle
A2: Flat platform fee for predictability, metered conversations above the allowance so revenue scales with value, and a monthly cap so a busy AEP never produces a frightening invoice.
A4: PLATFORM FEE AND INCLUDED USAGE
B5: Front Desk | C5: Plan Fluent | D5: Downline | E5: Notes
A6: Platform fee, monthly | B6: ='Control Panel'!B37 | C6: ='Control Panel'!B38 | D6: ='Control Panel'!B39 | E6: Charged whether or not the allowance is used.
A7: Platform fee, annual (per mo.) | B7: ='Control Panel'!B37*(1-'Control Panel'!$B$50) | C7: ='Control Panel'!B38*(1-'Control Panel'!$B$50) | D7: ='Control Panel'!B39*(1-'Control Panel'!$B$50) | E7: Annual discount set on the Control Panel.
A8: Conversations included / month | B8: ='Control Panel'!C37 | C8: ='Control Panel'!C38 | D8: ='Control Panel'!C39 | E8: A conversation is one answered voice call or chat session.
A9: Effective rate inside allowance | B9: ='Control Panel'!B37/'Control Panel'!C37 | C9: ='Control Panel'!B38/'Control Panel'!C38 | D9: ='Control Panel'!B39/'Control Panel'!C39 | E9: What a buyer pays per conversation at full allowance.
A10: Monthly overage ceiling | B10: ='Control Panel'!B37*'Control Panel'!$B$49 | C10: ='Control Panel'!B38*'Control Panel'!$B$49 | D10: ='Control Panel'!B39*'Control Panel'!$B$49 | E10: Surge protection. Overage can never exceed this in any month.
A11: Worst-case monthly bill | B11: ='Control Panel'!B37*(1+'Control Panel'!$B$49) | C11: ='Control Panel'!B38*(1+'Control Panel'!$B$49) | D11: ='Control Panel'!B39*(1+'Control Panel'!$B$49) | E11: Platform fee plus the capped overage. The number to put in front of a nervous buyer.
A13: OVERAGE BANDS (rate falls as volume rises)
A14: Band | B14: Conversations over allowance | C14: Rate each | D14: With prepaid commit | E14: Margin at this rate
A15: Band 1 | B15: first 250 over | C15: ='Control Panel'!C43 | D15: ='Control Panel'!C43*(1-'Control Panel'!$B$51) | E15: =('Control Panel'!C43-'Control Panel'!$B$10)/'Control Panel'!C43
A16: Band 2 | B16: next 750 | C16: ='Control Panel'!C44 | D16: ='Control Panel'!C44*(1-'Control Panel'!$B$51) | E16: =('Control Panel'!C44-'Control Panel'!$B$10)/'Control Panel'!C44
A17: Band 3 | B17: next 2,000 | C17: ='Control Panel'!C45 | D17: ='Control Panel'!C45*(1-'Control Panel'!$B$51) | E17: =('Control Panel'!C45-'Control Panel'!$B$10)/'Control Panel'!C45
A18: Band 4 | B18: beyond that | C18: ='Control Panel'!C46 | D18: ='Control Panel'!C46*(1-'Control Panel'!$B$51) | E18: =('Control Panel'!C46-'Control Panel'!$B$10)/'Control Panel'!C46
A20: How a bill works: platform fee, plus each band of over-allowance conversations at its own rate, with total overage capped at the ceiling above.

Sheet Unit Economics
A1: Unit Economics by Volume
A2: How one account behaves as its monthly conversations rise. Margin columns are colour scaled: green healthy, red thin. Where a tier goes red, that account belongs on the next tier up.
A4: REVENUE, COST AND MARGIN PER ACCOUNT PER MONTH
A5: Conversations | B5: Front Desk | E5: Plan Fluent | H5: Downline
B6: Revenue | C6: Cost | D6: Margin | E6: Revenue | F6: Cost | G6: Margin | H6: Revenue | I6: Cost | J6: Margin
A7: 0 | B7: ='Control Panel'!$B$37+MIN((MIN(MAX(0,$A7-'Control Panel'!$C$37),'Control Panel'!$B$43)*'Control Panel'!$C$43+MIN(MAX(MAX(0,$A7-'Control Panel'!$C$37)-'Control Panel'!$B$43,0),'Control Panel'!$B$44-'Control Panel'!$B$43)*'Control Panel'!$C$44+MIN(MAX(MAX(0,$A7-'Control Panel'!$C$37)-'Control Panel'!$B$44,0),'Control Panel'!$B$45-'Control Panel'!$B$44)*'Control Panel'!$C$45+MAX(MAX(0,$A7-'Control Panel'!$C$37)-'Control Panel'!$B$45,0)*'Control Panel'!$C$46),'Control Panel'!$B$37*'Control Panel'!$B$49) | C7: ='Control Panel'!$B$11+$A7*'Control Panel'!$B$10 | D7: =IF(B7=0,0,(B7-C7)/B7) | E7: ='Control Panel'!$B$38+MIN((MIN(MAX(0,$A7-'Control Panel'!$C$38),'Control Panel'!$B$43)*'Control Panel'!$C$43+MIN(MAX(MAX(0,$A7-'Control Panel'!$C$38)-'Control Panel'!$B$43,0),'Control Panel'!$B$44-'Control Panel'!$B$43)*'Control Panel'!$C$44+MIN(MAX(MAX(0,$A7-'Control Panel'!$C$38)-'Control Panel'!$B$44,0),'Control Panel'!$B$45-'Control Panel'!$B$44)*'Control Panel'!$C$45+MAX(MAX(0,$A7-'Control Panel'!$C$38)-'Control Panel'!$B$45,0)*'Control Panel'!$C$46),'Control Panel'!$B$38*'Control Panel'!$B$49) | F7: ='Control Panel'!$B$11+$A7*'Control Panel'!$B$10 | G7: =IF(E7=0,0,(E7-F7)/E7) | H7: ='Control Panel'!$B$39+MIN((MIN(MAX(0,$A7-'Control Panel'!$C$39),'Control Panel'!$B$43)*'Control Panel'!$C$43+MIN(MAX(MAX(0,$A7-'Control Panel'!$C$39)-'Control Panel'!$B$43,0),'Control Panel'!$B$44-'Control Panel'!$B$43)*'Control Panel'!$C$44+MIN(MAX(MAX(0,$A7-'Control Panel'!$C$39)-'Control Panel'!$B$44,0),'Control Panel'!$B$45-'Control Panel'!$B$44)*'Control Panel'!$C$45+MAX(MAX(0,$A7-'Control Panel'!$C$39)-'Control Panel'!$B$45,0)*'Control Panel'!$C$46),'Control Panel'!$B$39*'Control Panel'!$B$49) | I7: ='Control Panel'!$B$11+$A7*'Control Panel'!$B$10 | J7: =IF(H7=0,0,(H7-I7)/H7)
A8: 80 | B8: ='Control Panel'!$B$37+MIN((MIN(MAX(0,$A8-'Control Panel'!$C$37),'Control Panel'!$B$43)*'Control Panel'!$C$43+MIN(MAX(MAX(0,$A8-'Control Panel'!$C$37)-'Control Panel'!$B$43,0),'Control Panel'!$B$44-'Control Panel'!$B$43)*'Control Panel'!$C$44+MIN(MAX(MAX(0,$A8-'Control Panel'!$C$37)-'Control Panel'!$B$44,0),'Control Panel'!$B$45-'Control Panel'!$B$44)*'Control Panel'!$C$45+MAX(MAX(0,$A8-'Control Panel'!$C$37)-'Control Panel'!$B$45,0)*'Control Panel'!$C$46),'Control Panel'!$B$37*'Control Panel'!$B$49) | C8: ='Control Panel'!$B$11+$A8*'Control Panel'!$B$10 | D8: =IF(B8=0,0,(B8-C8)/B8) | E8: ='Control Panel'!$B$38+MIN((MIN(MAX(0,$A8-'Control Panel'!$C$38),'Control Panel'!$B$43)*'Control Panel'!$C$43+MIN(MAX(MAX(0,$A8-'Control Panel'!$C$38)-'Control Panel'!$B$43,0),'Control Panel'!$B$44-'Control Panel'!$B$43)*'Control Panel'!$C$44+MIN(MAX(MAX(0,$A8-'Control Panel'!$C$38)-'Control Panel'!$B$44,0),'Control Panel'!$B$45-'Control Panel'!$B$44)*'Control Panel'!$C$45+MAX(MAX(0,$A8-'Control Panel'!$C$38)-'Control Panel'!$B$45,0)*'Control Panel'!$C$46),'Control Panel'!$B$38*'Control Panel'!$B$49) | F8: ='Control Panel'!$B$11+$A8*'Control Panel'!$B$10 | G8: =IF(E8=0,0,(E8-F8)/E8) | H8: ='Control Panel'!$B$39+MIN((MIN(MAX(0,$A8-'Control Panel'!$C$39),'Control Panel'!$B$43)*'Control Panel'!$C$43+MIN(MAX(MAX(0,$A8-'Control Panel'!$C$39)-'Control Panel'!$B$43,0),'Control Panel'!$B$44-'Control Panel'!$B$43)*'Control Panel'!$C$44+MIN(MAX(MAX(0,$A8-'Control Panel'!$C$39)-'Control Panel'!$B$44,0),'Control Panel'!$B$45-'Control Panel'!$B$44)*'Control Panel'!$C$45+MAX(MAX(0,$A8-'Control Panel'!$C$39)-'Control Panel'!$B$45,0)*'Control Panel'!$C$46),'Control Panel'!$B$39*'Control Panel'!$B$49) | I8: ='Control Panel'!$B$11+$A8*'Control Panel'!$B$10 | J8: =IF(H8=0,0,(H8-I8)/H8)
A9: 160 | B9: ='Control Panel'!$B$37+MIN((MIN(MAX(0,$A9-'Control Panel'!$C$37),'Control Panel'!$B$43)*'Control Panel'!$C$43+MIN(MAX(MAX(0,$A9-'Control Panel'!$C$37)-'Control Panel'!$B$43,0),'Control Panel'!$B$44-'Control Panel'!$B$43)*'Control Panel'!$C$44+MIN(MAX(MAX(0,$A9-'Control Panel'!$C$37)-'Control Panel'!$B$44,0),'Control Panel'!$B$45-'Control Panel'!$B$44)*'Control Panel'!$C$45+MAX(MAX(0,$A9-'Control Panel'!$C$37)-'Control Panel'!$B$45,0)*'Control Panel'!$C$46),'Control Panel'!$B$37*'Control Panel'!$B$49) | C9: ='Control Panel'!$B$11+$A9*'Control Panel'!$B$10 | D9: =IF(B9=0,0,(B9-C9)/B9) | E9: ='Control Panel'!$B$38+MIN((MIN(MAX(0,$A9-'Control Panel'!$C$38),'Control Panel'!$B$43)*'Control Panel'!$C$43+MIN(MAX(MAX(0,$A9-'Control Panel'!$C$38)-'Control Panel'!$B$43,0),'Control Panel'!$B$44-'Control Panel'!$B$43)*'Control Panel'!$C$44+MIN(MAX(MAX(0,$A9-'Control Panel'!$C$38)-'Control Panel'!$B$44,0),'Control Panel'!$B$45-'Control Panel'!$B$44)*'Control Panel'!$C$45+MAX(MAX(0,$A9-'Control Panel'!$C$38)-'Control Panel'!$B$45,0)*'Control Panel'!$C$46),'Control Panel'!$B$38*'Control Panel'!$B$49) | F9: ='Control Panel'!$B$11+$A9*'Control Panel'!$B$10 | G9: =IF(E9=0,0,(E9-F9)/E9) | H9: ='Control Panel'!$B$39+MIN((MIN(MAX(0,$A9-'Control Panel'!$C$39),'Control Panel'!$B$43)*'Control Panel'!$C$43+MIN(MAX(MAX(0,$A9-'Control Panel'!$C$39)-'Control Panel'!$B$43,0),'Control Panel'!$B$44-'Control Panel'!$B$43)*'Control Panel'!$C$44+MIN(MAX(MAX(0,$A9-'Control Panel'!$C$39)-'Control Panel'!$B$44,0),'Control Panel'!$B$45-'Control Panel'!$B$44)*'Control Panel'!$C$45+MAX(MAX(0,$A9-'Control Panel'!$C$39)-'Control Panel'!$B$45,0)*'Control Panel'!$C$46),'Control Panel'!$B$39*'Control Panel'!$B$49) | I9: ='Control Panel'!$B$11+$A9*'Control Panel'!$B$10 | J9: =IF(H9=0,0,(H9-I9)/H9)
A10: 240 | B10: ='Control Panel'!$B$37+MIN((MIN(MAX(0,$A10-'Control Panel'!$C$37),'Control Panel'!$B$43)*'Control Panel'!$C$43+MIN(MAX(MAX(0,$A10-'Control Panel'!$C$37)-'Control Panel'!$B$43,0),'Control Panel'!$B$44-'Control Panel'!$B$43)*'Control Panel'!$C$44+MIN(MAX(MAX(0,$A10-'Control Panel'!$C$37)-'Control Panel'!$B$44,0),'Control Panel'!$B$45-'Control Panel'!$B$44)*'Control Panel'!$C$45+MAX(MAX(0,$A10-'Control Panel'!$C$37)-'Control Panel'!$B$45,0)*'Control Panel'!$C$46),'Control Panel'!$B$37*'Control Panel'!$B$49) | C10: ='Control Panel'!$B$11+$A10*'Control Panel'!$B$10 | D10: =IF(B10=0,0,(B10-C10)/B10) | E10: ='Control Panel'!$B$38+MIN((MIN(MAX(0,$A10-'Control Panel'!$C$38),'Control Panel'!$B$43)*'Control Panel'!$C$43+MIN(MAX(MAX(0,$A10-'Control Panel'!$C$38)-'Control Panel'!$B$43,0),'Control Panel'!$B$44-'Control Panel'!$B$43)*'Control Panel'!$C$44+MIN(MAX(MAX(0,$A10-'Control Panel'!$C$38)-'Control Panel'!$B$44,0),'Control Panel'!$B$45-'Control Panel'!$B$44)*'Control Panel'!$C$45+MAX(MAX(0,$A10-'Control Panel'!$C$38)-'Control Panel'!$B$45,0)*'Control Panel'!$C$46),'Control Panel'!$B$38*'Control Panel'!$B$49) | F10: ='Control Panel'!$B$11+$A10*'Control Panel'!$B$10 | G10: =IF(E10=0,0,(E10-F10)/E10) | H10: ='Control Panel'!$B$39+MIN((MIN(MAX(0,$A10-'Control Panel'!$C$39),'Control Panel'!$B$43)*'Control Panel'!$C$43+MIN(MAX(MAX(0,$A10-'Control Panel'!$C$39)-'Control Panel'!$B$43,0),'Control Panel'!$B$44-'Control Panel'!$B$43)*'Control Panel'!$C$44+MIN(MAX(MAX(0,$A10-'Control Panel'!$C$39)-'Control Panel'!$B$44,0),'Control Panel'!$B$45-'Control Panel'!$B$44)*'Control Panel'!$C$45+MAX(MAX(0,$A10-'Control Panel'!$C$39)-'Control Panel'!$B$45,0)*'Control Panel'!$C$46),'Control Panel'!$B$39*'Control Panel'!$B$49) | I10: ='Control Panel'!$B$11+$A10*'Control Panel'!$B$10 | J10: =IF(H10=0,0,(H10-I10)/H10)
A11: 320 | B11: ='Control Panel'!$B$37+MIN((MIN(MAX(0,$A11-'Control Panel'!$C$37),'Control Panel'!$B$43)*'Control Panel'!$C$43+MIN(MAX(MAX(0,$A11-'Control Panel'!$C$37)-'Control Panel'!$B$43,0),'Control Panel'!$B$44-'Control Panel'!$B$43)*'Control Panel'!$C$44+MIN(MAX(MAX(0,$A11-'Control Panel'!$C$37)-'Control Panel'!$B$44,0),'Control Panel'!$B$45-'Control Panel'!$B$44)*'Control Panel'!$C$45+MAX(MAX(0,$A11-'Control Panel'!$C$37)-'Control Panel'!$B$45,0)*'Control Panel'!$C$46),'Control Panel'!$B$37*'Control Panel'!$B$49) | C11: ='Control Panel'!$B$11+$A11*'Control Panel'!$B$10 | D11: =IF(B11=0,0,(B11-C11)/B11) | E11: ='Control Panel'!$B$38+MIN((MIN(MAX(0,$A11-'Control Panel'!$C$38),'Control Panel'!$B$43)*'Control Panel'!$C$43+MIN(MAX(MAX(0,$A11-'Control Panel'!$C$38)-'Control Panel'!$B$43,0),'Control Panel'!$B$44-'Control Panel'!$B$43)*'Control Panel'!$C$44+MIN(MAX(MAX(0,$A11-'Control Panel'!$C$38)-'Control Panel'!$B$44,0),'Control Panel'!$B$45-'Control Panel'!$B$44)*'Control Panel'!$C$45+MAX(MAX(0,$A11-'Control Panel'!$C$38)-'Control Panel'!$B$45,0)*'Control Panel'!$C$46),'Control Panel'!$B$38*'Control Panel'!$B$49) | F11: ='Control Panel'!$B$11+$A11*'Control Panel'!$B$10 | G11: =IF(E11=0,0,(E11-F11)/E11) | H11: ='Control Panel'!$B$39+MIN((MIN(MAX(0,$A11-'Control Panel'!$C$39),'Control Panel'!$B$43)*'Control Panel'!$C$43+MIN(MAX(MAX(0,$A11-'Control Panel'!$C$39)-'Control Panel'!$B$43,0),'Control Panel'!$B$44-'Control Panel'!$B$43)*'Control Panel'!$C$44+MIN(MAX(MAX(0,$A11-'Control Panel'!$C$39)-'Control Panel'!$B$44,0),'Control Panel'!$B$45-'Control Panel'!$B$44)*'Control Panel'!$C$45+MAX(MAX(0,$A11-'Control Panel'!$C$39)-'Control Panel'!$B$45,0)*'Control Panel'!$C$46),'Control Panel'!$B$39*'Control Panel'!$B$49) | I11: ='Control Panel'!$B$11+$A11*'Control Panel'!$B$10 | J11: =IF(H11=0,0,(H11-I11)/H11)
A12: 400 | B12: ='Control Panel'!$B$37+MIN((MIN(MAX(0,$A12-'Control Panel'!$C$37),'Control Panel'!$B$43)*'Control Panel'!$C$43+MIN(MAX(MAX(0,$A12-'Control Panel'!$C$37)-'Control Panel'!$B$43,0),'Control Panel'!$B$44-'Control Panel'!$B$43)*'Control Panel'!$C$44+MIN(MAX(MAX(0,$A12-'Control Panel'!$C$37)-'Control Panel'!$B$44,0),'Control Panel'!$B$45-'Control Panel'!$B$44)*'Control Panel'!$C$45+MAX(MAX(0,$A12-'Control Panel'!$C$37)-'Control Panel'!$B$45,0)*'Control Panel'!$C$46),'Control Panel'!$B$37*'Control Panel'!$B$49) | C12: ='Control Panel'!$B$11+$A12*'Control Panel'!$B$10 | D12: =IF(B12=0,0,(B12-C12)/B12) | E12: ='Control Panel'!$B$38+MIN((MIN(MAX(0,$A12-'Control Panel'!$C$38),'Control Panel'!$B$43)*'Control Panel'!$C$43+MIN(MAX(MAX(0,$A12-'Control Panel'!$C$38)-'Control Panel'!$B$43,0),'Control Panel'!$B$44-'Control Panel'!$B$43)*'Control Panel'!$C$44+MIN(MAX(MAX(0,$A12-'Control Panel'!$C$38)-'Control Panel'!$B$44,0),'Control Panel'!$B$45-'Control Panel'!$B$44)*'Control Panel'!$C$45+MAX(MAX(0,$A12-'Control Panel'!$C$38)-'Control Panel'!$B$45,0)*'Control Panel'!$C$46),'Control Panel'!$B$38*'Control Panel'!$B$49) | F12: ='Control Panel'!$B$11+$A12*'Control Panel'!$B$10 | G12: =IF(E12=0,0,(E12-F12)/E12) | H12: ='Control Panel'!$B$39+MIN((MIN(MAX(0,$A12-'Control Panel'!$C$39),'Control Panel'!$B$43)*'Control Panel'!$C$43+MIN(MAX(MAX(0,$A12-'Control Panel'!$C$39)-'Control Panel'!$B$43,0),'Control Panel'!$B$44-'Control Panel'!$B$43)*'Control Panel'!$C$44+MIN(MAX(MAX(0,$A12-'Control Panel'!$C$39)-'Control Panel'!$B$44,0),'Control Panel'!$B$45-'Control Panel'!$B$44)*'Control Panel'!$C$45+MAX(MAX(0,$A12-'Control Panel'!$C$39)-'Control Panel'!$B$45,0)*'Control Panel'!$C$46),'Control Panel'!$B$39*'Control Panel'!$B$49) | I12: ='Control Panel'!$B$11+$A12*'Control Panel'!$B$10 | J12: =IF(H12=0,0,(H12-I12)/H12)
A13: 480 | B13: ='Control Panel'!$B$37+MIN((MIN(MAX(0,$A13-'Control Panel'!$C$37),'Control Panel'!$B$43)*'Control Panel'!$C$43+MIN(MAX(MAX(0,$A13-'Control Panel'!$C$37)-'Control Panel'!$B$43,0),'Control Panel'!$B$44-'Control Panel'!$B$43)*'Control Panel'!$C$44+MIN(MAX(MAX(0,$A13-'Control Panel'!$C$37)-'Control Panel'!$B$44,0),'Control Panel'!$B$45-'Control Panel'!$B$44)*'Control Panel'!$C$45+MAX(MAX(0,$A13-'Control Panel'!$C$37)-'Control Panel'!$B$45,0)*'Control Panel'!$C$46),'Control Panel'!$B$37*'Control Panel'!$B$49) | C13: ='Control Panel'!$B$11+$A13*'Control Panel'!$B$10 | D13: =IF(B13=0,0,(B13-C13)/B13) | E13: ='Control Panel'!$B$38+MIN((MIN(MAX(0,$A13-'Control Panel'!$C$38),'Control Panel'!$B$43)*'Control Panel'!$C$43+MIN(MAX(MAX(0,$A13-'Control Panel'!$C$38)-'Control Panel'!$B$43,0),'Control Panel'!$B$44-'Control Panel'!$B$43)*'Control Panel'!$C$44+MIN(MAX(MAX(0,$A13-'Control Panel'!$C$38)-'Control Panel'!$B$44,0),'Control Panel'!$B$45-'Control Panel'!$B$44)*'Control Panel'!$C$45+MAX(MAX(0,$A13-'Control Panel'!$C$38)-'Control Panel'!$B$45,0)*'Control Panel'!$C$46),'Control Panel'!$B$38*'Control Panel'!$B$49) | F13: ='Control Panel'!$B$11+$A13*'Control Panel'!$B$10 | G13: =IF(E13=0,0,(E13-F13)/E13) | H13: ='Control Panel'!$B$39+MIN((MIN(MAX(0,$A13-'Control Panel'!$C$39),'Control Panel'!$B$43)*'Control Panel'!$C$43+MIN(MAX(MAX(0,$A13-'Control Panel'!$C$39)-'Control Panel'!$B$43,0),'Control Panel'!$B$44-'Control Panel'!$B$43)*'Control Panel'!$C$44+MIN(MAX(MAX(0,$A13-'Control Panel'!$C$39)-'Control Panel'!$B$44,0),'Control Panel'!$B$45-'Control Panel'!$B$44)*'Control Panel'!$C$45+MAX(MAX(0,$A13-'Control Panel'!$C$39)-'Control Panel'!$B$45,0)*'Control Panel'!$C$46),'Control Panel'!$B$39*'Control Panel'!$B$49) | I13: ='Control Panel'!$B$11+$A13*'Control Panel'!$B$10 | J13: =IF(H13=0,0,(H13-I13)/H13)
A14: 560 | B14: ='Control Panel'!$B$37+MIN((MIN(MAX(0,$A14-'Control Panel'!$C$37),'Control Panel'!$B$43)*'Control Panel'!$C$43+MIN(MAX(MAX(0,$A14-'Control Panel'!$C$37)-'Control Panel'!$B$43,0),'Control Panel'!$B$44-'Control Panel'!$B$43)*'Control Panel'!$C$44+MIN(MAX(MAX(0,$A14-'Control Panel'!$C$37)-'Control Panel'!$B$44,0),'Control Panel'!$B$45-'Control Panel'!$B$44)*'Control Panel'!$C$45+MAX(MAX(0,$A14-'Control Panel'!$C$37)-'Control Panel'!$B$45,0)*'Control Panel'!$C$46),'Control Panel'!$B$37*'Control Panel'!$B$49) | C14: ='Control Panel'!$B$11+$A14*'Control Panel'!$B$10 | D14: =IF(B14=0,0,(B14-C14)/B14) | E14: ='Control Panel'!$B$38+MIN((MIN(MAX(0,$A14-'Control Panel'!$C$38),'Control Panel'!$B$43)*'Control Panel'!$C$43+MIN(MAX(MAX(0,$A14-'Control Panel'!$C$38)-'Control Panel'!$B$43,0),'Control Panel'!$B$44-'Control Panel'!$B$43)*'Control Panel'!$C$44+MIN(MAX(MAX(0,$A14-'Control Panel'!$C$38)-'Control Panel'!$B$44,0),'Control Panel'!$B$45-'Control Panel'!$B$44)*'Control Panel'!$C$45+MAX(MAX(0,$A14-'Control Panel'!$C$38)-'Control Panel'!$B$45,0)*'Control Panel'!$C$46),'Control Panel'!$B$38*'Control Panel'!$B$49) | F14: ='Control Panel'!$B$11+$A14*'Control Panel'!$B$10 | G14: =IF(E14=0,0,(E14-F14)/E14) | H14: ='Control Panel'!$B$39+MIN((MIN(MAX(0,$A14-'Control Panel'!$C$39),'Control Panel'!$B$43)*'Control Panel'!$C$43+MIN(MAX(MAX(0,$A14-'Control Panel'!$C$39)-'Control Panel'!$B$43,0),'Control Panel'!$B$44-'Control Panel'!$B$43)*'Control Panel'!$C$44+MIN(MAX(MAX(0,$A14-'Control Panel'!$C$39)-'Control Panel'!$B$44,0),'Control Panel'!$B$45-'Control Panel'!$B$44)*'Control Panel'!$C$45+MAX(MAX(0,$A14-'Control Panel'!$C$39)-'Control Panel'!$B$45,0)*'Control Panel'!$C$46),'Control Panel'!$B$39*'Control Panel'!$B$49) | I14: ='Control Panel'!$B$11+$A14*'Control Panel'!$B$10 | J14: =IF(H14=0,0,(H14-I14)/H14)
A15: 640 | B15: ='Control Panel'!$B$37+MIN((MIN(MAX(0,$A15-'Control Panel'!$C$37),'Control Panel'!$B$43)*'Control Panel'!$C$43+MIN(MAX(MAX(0,$A15-'Control Panel'!$C$37)-'Control Panel'!$B$43,0),'Control Panel'!$B$44-'Control Panel'!$B$43)*'Control Panel'!$C$44+MIN(MAX(MAX(0,$A15-'Control Panel'!$C$37)-'Control Panel'!$B$44,0),'Control Panel'!$B$45-'Control Panel'!$B$44)*'Control Panel'!$C$45+MAX(MAX(0,$A15-'Control Panel'!$C$37)-'Control Panel'!$B$45,0)*'Control Panel'!$C$46),'Control Panel'!$B$37*'Control Panel'!$B$49) | C15: ='Control Panel'!$B$11+$A15*'Control Panel'!$B$10 | D15: =IF(B15=0,0,(B15-C15)/B15) | E15: ='Control Panel'!$B$38+MIN((MIN(MAX(0,$A15-'Control Panel'!$C$38),'Control Panel'!$B$43)*'Control Panel'!$C$43+MIN(MAX(MAX(0,$A15-'Control Panel'!$C$38)-'Control Panel'!$B$43,0),'Control Panel'!$B$44-'Control Panel'!$B$43)*'Control Panel'!$C$44+MIN(MAX(MAX(0,$A15-'Control Panel'!$C$38)-'Control Panel'!$B$44,0),'Control Panel'!$B$45-'Control Panel'!$B$44)*'Control Panel'!$C$45+MAX(MAX(0,$A15-'Control Panel'!$C$38)-'Control Panel'!$B$45,0)*'Control Panel'!$C$46),'Control Panel'!$B$38*'Control Panel'!$B$49) | F15: ='Control Panel'!$B$11+$A15*'Control Panel'!$B$10 | G15: =IF(E15=0,0,(E15-F15)/E15) | H15: ='Control Panel'!$B$39+MIN((MIN(MAX(0,$A15-'Control Panel'!$C$39),'Control Panel'!$B$43)*'Control Panel'!$C$43+MIN(MAX(MAX(0,$A15-'Control Panel'!$C$39)-'Control Panel'!$B$43,0),'Control Panel'!$B$44-'Control Panel'!$B$43)*'Control Panel'!$C$44+MIN(MAX(MAX(0,$A15-'Control Panel'!$C$39)-'Control Panel'!$B$44,0),'Control Panel'!$B$45-'Control Panel'!$B$44)*'Control Panel'!$C$45+MAX(MAX(0,$A15-'Control Panel'!$C$39)-'Control Panel'!$B$45,0)*'Control Panel'!$C$46),'Control Panel'!$B$39*'Control Panel'!$B$49) | I15: ='Control Panel'!$B$11+$A15*'Control Panel'!$B$10 | J15: =IF(H15=0,0,(H15-I15)/H15)
A16: 720 | B16: ='Control Panel'!$B$37+MIN((MIN(MAX(0,$A16-'Control Panel'!$C$37),'Control Panel'!$B$43)*'Control Panel'!$C$43+MIN(MAX(MAX(0,$A16-'Control Panel'!$C$37)-'Control Panel'!$B$43,0),'Control Panel'!$B$44-'Control Panel'!$B$43)*'Control Panel'!$C$44+MIN(MAX(MAX(0,$A16-'Control Panel'!$C$37)-'Control Panel'!$B$44,0),'Control Panel'!$B$45-'Control Panel'!$B$44)*'Control Panel'!$C$45+MAX(MAX(0,$A16-'Control Panel'!$C$37)-'Control Panel'!$B$45,0)*'Control Panel'!$C$46),'Control Panel'!$B$37*'Control Panel'!$B$49) | C16: ='Control Panel'!$B$11+$A16*'Control Panel'!$B$10 | D16: =IF(B16=0,0,(B16-C16)/B16) | E16: ='Control Panel'!$B$38+MIN((MIN(MAX(0,$A16-'Control Panel'!$C$38),'Control Panel'!$B$43)*'Control Panel'!$C$43+MIN(MAX(MAX(0,$A16-'Control Panel'!$C$38)-'Control Panel'!$B$43,0),'Control Panel'!$B$44-'Control Panel'!$B$43)*'Control Panel'!$C$44+MIN(MAX(MAX(0,$A16-'Control Panel'!$C$38)-'Control Panel'!$B$44,0),'Control Panel'!$B$45-'Control Panel'!$B$44)*'Control Panel'!$C$45+MAX(MAX(0,$A16-'Control Panel'!$C$38)-'Control Panel'!$B$45,0)*'Control Panel'!$C$46),'Control Panel'!$B$38*'Control Panel'!$B$49) | F16: ='Control Panel'!$B$11+$A16*'Control Panel'!$B$10 | G16: =IF(E16=0,0,(E16-F16)/E16) | H16: ='Control Panel'!$B$39+MIN((MIN(MAX(0,$A16-'Control Panel'!$C$39),'Control Panel'!$B$43)*'Control Panel'!$C$43+MIN(MAX(MAX(0,$A16-'Control Panel'!$C$39)-'Control Panel'!$B$43,0),'Control Panel'!$B$44-'Control Panel'!$B$43)*'Control Panel'!$C$44+MIN(MAX(MAX(0,$A16-'Control Panel'!$C$39)-'Control Panel'!$B$44,0),'Control Panel'!$B$45-'Control Panel'!$B$44)*'Control Panel'!$C$45+MAX(MAX(0,$A16-'Control Panel'!$C$39)-'Control Panel'!$B$45,0)*'Control Panel'!$C$46),'Control Panel'!$B$39*'Control Panel'!$B$49) | I16: ='Control Panel'!$B$11+$A16*'Control Panel'!$B$10 | J16: =IF(H16=0,0,(H16-I16)/H16)
A17: 800 | B17: ='Control Panel'!$B$37+MIN((MIN(MAX(0,$A17-'Control Panel'!$C$37),'Control Panel'!$B$43)*'Control Panel'!$C$43+MIN(MAX(MAX(0,$A17-'Control Panel'!$C$37)-'Control Panel'!$B$43,0),'Control Panel'!$B$44-'Control Panel'!$B$43)*'Control Panel'!$C$44+MIN(MAX(MAX(0,$A17-'Control Panel'!$C$37)-'Control Panel'!$B$44,0),'Control Panel'!$B$45-'Control Panel'!$B$44)*'Control Panel'!$C$45+MAX(MAX(0,$A17-'Control Panel'!$C$37)-'Control Panel'!$B$45,0)*'Control Panel'!$C$46),'Control Panel'!$B$37*'Control Panel'!$B$49) | C17: ='Control Panel'!$B$11+$A17*'Control Panel'!$B$10 | D17: =IF(B17=0,0,(B17-C17)/B17) | E17: ='Control Panel'!$B$38+MIN((MIN(MAX(0,$A17-'Control Panel'!$C$38),'Control Panel'!$B$43)*'Control Panel'!$C$43+MIN(MAX(MAX(0,$A17-'Control Panel'!$C$38)-'Control Panel'!$B$43,0),'Control Panel'!$B$44-'Control Panel'!$B$43)*'Control Panel'!$C$44+MIN(MAX(MAX(0,$A17-'Control Panel'!$C$38)-'Control Panel'!$B$44,0),'Control Panel'!$B$45-'Control Panel'!$B$44)*'Control Panel'!$C$45+MAX(MAX(0,$A17-'Control Panel'!$C$38)-'Control Panel'!$B$45,0)*'Control Panel'!$C$46),'Control Panel'!$B$38*'Control Panel'!$B$49) | F17: ='Control Panel'!$B$11+$A17*'Control Panel'!$B$10 | G17: =IF(E17=0,0,(E17-F17)/E17) | H17: ='Control Panel'!$B$39+MIN((MIN(MAX(0,$A17-'Control Panel'!$C$39),'Control Panel'!$B$43)*'Control Panel'!$C$43+MIN(MAX(MAX(0,$A17-'Control Panel'!$C$39)-'Control Panel'!$B$43,0),'Control Panel'!$B$44-'Control Panel'!$B$43)*'Control Panel'!$C$44+MIN(MAX(MAX(0,$A17-'Control Panel'!$C$39)-'Control Panel'!$B$44,0),'Control Panel'!$B$45-'Control Panel'!$B$44)*'Control Panel'!$C$45+MAX(MAX(0,$A17-'Control Panel'!$C$39)-'Control Panel'!$B$45,0)*'Control Panel'!$C$46),'Control Panel'!$B$39*'Control Panel'!$B$49) | I17: ='Control Panel'!$B$11+$A17*'Control Panel'!$B$10 | J17: =IF(H17=0,0,(H17-I17)/H17)
A18: 880 | B18: ='Control Panel'!$B$37+MIN((MIN(MAX(0,$A18-'Control Panel'!$C$37),'Control Panel'!$B$43)*'Control Panel'!$C$43+MIN(MAX(MAX(0,$A18-'Control Panel'!$C$37)-'Control Panel'!$B$43,0),'Control Panel'!$B$44-'Control Panel'!$B$43)*'Control Panel'!$C$44+MIN(MAX(MAX(0,$A18-'Control Panel'!$C$37)-'Control Panel'!$B$44,0),'Control Panel'!$B$45-'Control Panel'!$B$44)*'Control Panel'!$C$45+MAX(MAX(0,$A18-'Control Panel'!$C$37)-'Control Panel'!$B$45,0)*'Control Panel'!$C$46),'Control Panel'!$B$37*'Control Panel'!$B$49) | C18: ='Control Panel'!$B$11+$A18*'Control Panel'!$B$10 | D18: =IF(B18=0,0,(B18-C18)/B18) | E18: ='Control Panel'!$B$38+MIN((MIN(MAX(0,$A18-'Control Panel'!$C$38),'Control Panel'!$B$43)*'Control Panel'!$C$43+MIN(MAX(MAX(0,$A18-'Control Panel'!$C$38)-'Control Panel'!$B$43,0),'Control Panel'!$B$44-'Control Panel'!$B$43)*'Control Panel'!$C$44+MIN(MAX(MAX(0,$A18-'Control Panel'!$C$38)-'Control Panel'!$B$44,0),'Control Panel'!$B$45-'Control Panel'!$B$44)*'Control Panel'!$C$45+MAX(MAX(0,$A18-'Control Panel'!$C$38)-'Control Panel'!$B$45,0)*'Control Panel'!$C$46),'Control Panel'!$B$38*'Control Panel'!$B$49) | F18: ='Control Panel'!$B$11+$A18*'Control Panel'!$B$10 | G18: =IF(E18=0,0,(E18-F18)/E18) | H18: ='Control Panel'!$B$39+MIN((MIN(MAX(0,$A18-'Control Panel'!$C$39),'Control Panel'!$B$43)*'Control Panel'!$C$43+MIN(MAX(MAX(0,$A18-'Control Panel'!$C$39)-'Control Panel'!$B$43,0),'Control Panel'!$B$44-'Control Panel'!$B$43)*'Control Panel'!$C$44+MIN(MAX(MAX(0,$A18-'Control Panel'!$C$39)-'Control Panel'!$B$44,0),'Control Panel'!$B$45-'Control Panel'!$B$44)*'Control Panel'!$C$45+MAX(MAX(0,$A18-'Control Panel'!$C$39)-'Control Panel'!$B$45,0)*'Control Panel'!$C$46),'Control Panel'!$B$39*'Control Panel'!$B$49) | I18: ='Control Panel'!$B$11+$A18*'Control Panel'!$B$10 | J18: =IF(H18=0,0,(H18-I18)/H18)
... A27: 1600 | B27: ='Control Panel'!$B$37+MIN((MIN(MAX(0,$A27-'Control Panel'!$C$37),'Control Panel'!$B$43)*'Control Panel'!$C$43+MIN(MAX(MAX(0,$A27-'Control Panel'!$C$37)-'Control Panel'!$B$43,0),'Control Panel'!$B$44-'Control Panel'!$B$43)*'Control Panel'!$C$44+MIN(MAX(MAX(0,$A27-'Control Panel'!$C$37)-'Control Panel'!$B$44,0),'Control Panel'!$B$45-'Control Panel'!$B$44)*'Control Panel'!$C$45+MAX(MAX(0,$A27-'Control Panel'!$C$37)-'Control Panel'!$B$45,0)*'Control Panel'!$C$46),'Control Panel'!$B$37*'Control Panel'!$B$49) | C27: ='Control Panel'!$B$11+$A27*'Control Panel'!$B$10 | D27: =IF(B27=0,0,(B27-C27)/B27) | E27: ='Control Panel'!$B$38+MIN((MIN(MAX(0,$A27-'Control Panel'!$C$38),'Control Panel'!$B$43)*'Control Panel'!$C$43+MIN(MAX(MAX(0,$A27-'Control Panel'!$C$38)-'Control Panel'!$B$43,0),'Control Panel'!$B$44-'Control Panel'!$B$43)*'Control Panel'!$C$44+MIN(MAX(MAX(0,$A27-'Control Panel'!$C$38)-'Control Panel'!$B$44,0),'Control Panel'!$B$45-'Control Panel'!$B$44)*'Control Panel'!$C$45+MAX(MAX(0,$A27-'Control Panel'!$C$38)-'Control Panel'!$B$45,0)*'Control Panel'!$C$46),'Control Panel'!$B$38*'Control Panel'!$B$49) | F27: ='Control Panel'!$B$11+$A27*'Control Panel'!$B$10 | G27: =IF(E27=0,0,(E27-F27)/E27) | H27: ='Control Panel'!$B$39+MIN((MIN(MAX(0,$A27-'Control Panel'!$C$39),'Control Panel'!$B$43)*'Control Panel'!$C$43+MIN(MAX(MAX(0,$A27-'Control Panel'!$C$39)-'Control Panel'!$B$43,0),'Control Panel'!$B$44-'Control Panel'!$B$43)*'Control Panel'!$C$44+MIN(MAX(MAX(0,$A27-'Control Panel'!$C$39)-'Control Panel'!$B$44,0),'Control Panel'!$B$45-'Control Panel'!$B$44)*'Control Panel'!$C$45+MAX(MAX(0,$A27-'Control Panel'!$C$39)-'Control Panel'!$B$45,0)*'Control Panel'!$C$46),'Control Panel'!$B$39*'Control Panel'!$B$49) | I27: ='Control Panel'!$B$11+$A27*'Control Panel'!$B$10 | J27: =IF(H27=0,0,(H27-I27)/H27)
A29: The crossover point where a tier's margin drops below the floor is the upgrade trigger for sales.

Sheet Scenario Model
A1: 12-Month Scenario Model with AEP Seasonality
A2: Four agency profiles across a full year. AEP runs 15 Oct to 7 Dec and OEP Jan to Mar, so volume is far from flat. Edit the blue baseline in each block.
A4: SEASONALITY MULTIPLIERS
A5: Month | B5: Jan | C5: Feb | D5: Mar | E5: Apr | F5: May | G5: Jun | H5: Jul | I5: Aug | J5: Sep | K5: Oct | L5: Nov | M5: Dec
A6: Multiplier | B6: 1.15 | C6: 0.95 | D6: 0.9 | E6: 0.8 | F6: 0.75 | G6: 0.75 | H6: 0.8 | I6: 0.85 | J6: 1.05 | K6: 1.8 | L6: 2.4 | M6: 1.6
A8: SMALL AGENCY - on Front Desk
A9: Baseline conv./mo | B9: 60 | D9: Platform fee | E9: ='Control Panel'!B37 | F9: Included | G9: ='Control Panel'!C37
A10: Month | B10: Mult. | C10: Conversations | D10: Over allowance | E10: Platform rev | F10: Overage rev | G10: Total revenue | H10: Cost | I10: Gross profit | J10: Margin
A11: Jan | B11: =B$6 | C11: =ROUND($B$9*B11,0) | D11: =MAX(0,C11-'Control Panel'!$C$37) | E11: ='Control Panel'!$B$37 | F11: =MIN((MIN(MAX(0,C11-'Control Panel'!$C$37),'Control Panel'!$B$43)*'Control Panel'!$C$43+MIN(MAX(MAX(0,C11-'Control Panel'!$C$37)-'Control Panel'!$B$43,0),'Control Panel'!$B$44-'Control Panel'!$B$43)*'Control Panel'!$C$44+MIN(MAX(MAX(0,C11-'Control Panel'!$C$37)-'Control Panel'!$B$44,0),'Control Panel'!$B$45-'Control Panel'!$B$44)*'Control Panel'!$C$45+MAX(MAX(0,C11-'Control Panel'!$C$37)-'Control Panel'!$B$45,0)*'Control Panel'!$C$46),'Control Panel'!$B$37*'Control Panel'!$B$49) | G11: =E11+F11 | H11: ='Control Panel'!$B$11+C11*'Control Panel'!$B$10 | I11: =G11-H11 | J11: =IF(G11=0,0,I11/G11)
A12: Feb | B12: =C$6 | C12: =ROUND($B$9*B12,0) | D12: =MAX(0,C12-'Control Panel'!$C$37) | E12: ='Control Panel'!$B$37 | F12: =MIN((MIN(MAX(0,C12-'Control Panel'!$C$37),'Control Panel'!$B$43)*'Control Panel'!$C$43+MIN(MAX(MAX(0,C12-'Control Panel'!$C$37)-'Control Panel'!$B$43,0),'Control Panel'!$B$44-'Control Panel'!$B$43)*'Control Panel'!$C$44+MIN(MAX(MAX(0,C12-'Control Panel'!$C$37)-'Control Panel'!$B$44,0),'Control Panel'!$B$45-'Control Panel'!$B$44)*'Control Panel'!$C$45+MAX(MAX(0,C12-'Control Panel'!$C$37)-'Control Panel'!$B$45,0)*'Control Panel'!$C$46),'Control Panel'!$B$37*'Control Panel'!$B$49) | G12: =E12+F12 | H12: ='Control Panel'!$B$11+C12*'Control Panel'!$B$10 | I12: =G12-H12 | J12: =IF(G12=0,0,I12/G12)
A13: Mar | B13: =D$6 | C13: =ROUND($B$9*B13,0) | D13: =MAX(0,C13-'Control Panel'!$C$37) | E13: ='Control Panel'!$B$37 | F13: =MIN((MIN(MAX(0,C13-'Control Panel'!$C$37),'Control Panel'!$B$43)*'Control Panel'!$C$43+MIN(MAX(MAX(0,C13-'Control Panel'!$C$37)-'Control Panel'!$B$43,0),'Control Panel'!$B$44-'Control Panel'!$B$43)*'Control Panel'!$C$44+MIN(MAX(MAX(0,C13-'Control Panel'!$C$37)-'Control Panel'!$B$44,0),'Control Panel'!$B$45-'Control Panel'!$B$44)*'Control Panel'!$C$45+MAX(MAX(0,C13-'Control Panel'!$C$37)-'Control Panel'!$B$45,0)*'Control Panel'!$C$46),'Control Panel'!$B$37*'Control Panel'!$B$49) | G13: =E13+F13 | H13: ='Control Panel'!$B$11+C13*'Control Panel'!$B$10 | I13: =G13-H13 | J13: =IF(G13=0,0,I13/G13)
A14: Apr | B14: =E$6 | C14: =ROUND($B$9*B14,0) | D14: =MAX(0,C14-'Control Panel'!$C$37) | E14: ='Control Panel'!$B$37 | F14: =MIN((MIN(MAX(0,C14-'Control Panel'!$C$37),'Control Panel'!$B$43)*'Control Panel'!$C$43+MIN(MAX(MAX(0,C14-'Control Panel'!$C$37)-'Control Panel'!$B$43,0),'Control Panel'!$B$44-'Control Panel'!$B$43)*'Control Panel'!$C$44+MIN(MAX(MAX(0,C14-'Control Panel'!$C$37)-'Control Panel'!$B$44,0),'Control Panel'!$B$45-'Control Panel'!$B$44)*'Control Panel'!$C$45+MAX(MAX(0,C14-'Control Panel'!$C$37)-'Control Panel'!$B$45,0)*'Control Panel'!$C$46),'Control Panel'!$B$37*'Control Panel'!$B$49) | G14: =E14+F14 | H14: ='Control Panel'!$B$11+C14*'Control Panel'!$B$10 | I14: =G14-H14 | J14: =IF(G14=0,0,I14/G14)
A15: May | B15: =F$6 | C15: =ROUND($B$9*B15,0) | D15: =MAX(0,C15-'Control Panel'!$C$37) | E15: ='Control Panel'!$B$37 | F15: =MIN((MIN(MAX(0,C15-'Control Panel'!$C$37),'Control Panel'!$B$43)*'Control Panel'!$C$43+MIN(MAX(MAX(0,C15-'Control Panel'!$C$37)-'Control Panel'!$B$43,0),'Control Panel'!$B$44-'Control Panel'!$B$43)*'Control Panel'!$C$44+MIN(MAX(MAX(0,C15-'Control Panel'!$C$37)-'Control Panel'!$B$44,0),'Control Panel'!$B$45-'Control Panel'!$B$44)*'Control Panel'!$C$45+MAX(MAX(0,C15-'Control Panel'!$C$37)-'Control Panel'!$B$45,0)*'Control Panel'!$C$46),'Control Panel'!$B$37*'Control Panel'!$B$49) | G15: =E15+F15 | H15: ='Control Panel'!$B$11+C15*'Control Panel'!$B$10 | I15: =G15-H15 | J15: =IF(G15=0,0,I15/G15)
A16: Jun | B16: =G$6 | C16: =ROUND($B$9*B16,0) | D16: =MAX(0,C16-'Control Panel'!$C$37) | E16: ='Control Panel'!$B$37 | F16: =MIN((MIN(MAX(0,C16-'Control Panel'!$C$37),'Control Panel'!$B$43)*'Control Panel'!$C$43+MIN(MAX(MAX(0,C16-'Control Panel'!$C$37)-'Control Panel'!$B$43,0),'Control Panel'!$B$44-'Control Panel'!$B$43)*'Control Panel'!$C$44+MIN(MAX(MAX(0,C16-'Control Panel'!$C$37)-'Control Panel'!$B$44,0),'Control Panel'!$B$45-'Control Panel'!$B$44)*'Control Panel'!$C$45+MAX(MAX(0,C16-'Control Panel'!$C$37)-'Control Panel'!$B$45,0)*'Control Panel'!$C$46),'Control Panel'!$B$37*'Control Panel'!$B$49) | G16: =E16+F16 | H16: ='Control Panel'!$B$11+C16*'Control Panel'!$B$10 | I16: =G16-H16 | J16: =IF(G16=0,0,I16/G16)
A17: Jul | B17: =H$6 | C17: =ROUND($B$9*B17,0) | D17: =MAX(0,C17-'Control Panel'!$C$37) | E17: ='Control Panel'!$B$37 | F17: =MIN((MIN(MAX(0,C17-'Control Panel'!$C$37),'Control Panel'!$B$43)*'Control Panel'!$C$43+MIN(MAX(MAX(0,C17-'Control Panel'!$C$37)-'Control Panel'!$B$43,0),'Control Panel'!$B$44-'Control Panel'!$B$43)*'Control Panel'!$C$44+MIN(MAX(MAX(0,C17-'Control Panel'!$C$37)-'Control Panel'!$B$44,0),'Control Panel'!$B$45-'Control Panel'!$B$44)*'Control Panel'!$C$45+MAX(MAX(0,C17-'Control Panel'!$C$37)-'Control Panel'!$B$45,0)*'Control Panel'!$C$46),'Control Panel'!$B$37*'Control Panel'!$B$49) | G17: =E17+F17 | H17: ='Control Panel'!$B$11+C17*'Control Panel'!$B$10 | I17: =G17-H17 | J17: =IF(G17=0,0,I17/G17)
A18: Aug | B18: =I$6 | C18: =ROUND($B$9*B18,0) | D18: =MAX(0,C18-'Control Panel'!$C$37) | E18: ='Control Panel'!$B$37 | F18: =MIN((MIN(MAX(0,C18-'Control Panel'!$C$37),'Control Panel'!$B$43)*'Control Panel'!$C$43+MIN(MAX(MAX(0,C18-'Control Panel'!$C$37)-'Control Panel'!$B$43,0),'Control Panel'!$B$44-'Control Panel'!$B$43)*'Control Panel'!$C$44+MIN(MAX(MAX(0,C18-'Control Panel'!$C$37)-'Control Panel'!$B$44,0),'Control Panel'!$B$45-'Control Panel'!$B$44)*'Control Panel'!$C$45+MAX(MAX(0,C18-'Control Panel'!$C$37)-'Control Panel'!$B$45,0)*'Control Panel'!$C$46),'Control Panel'!$B$37*'Control Panel'!$B$49) | G18: =E18+F18 | H18: ='Control Panel'!$B$11+C18*'Control Panel'!$B$10 | I18: =G18-H18 | J18: =IF(G18=0,0,I18/G18)
A19: Sep | B19: =J$6 | C19: =ROUND($B$9*B19,0) | D19: =MAX(0,C19-'Control Panel'!$C$37) | E19: ='Control Panel'!$B$37 | F19: =MIN((MIN(MAX(0,C19-'Control Panel'!$C$37),'Control Panel'!$B$43)*'Control Panel'!$C$43+MIN(MAX(MAX(0,C19-'Control Panel'!$C$37)-'Control Panel'!$B$43,0),'Control Panel'!$B$44-'Control Panel'!$B$43)*'Control Panel'!$C$44+MIN(MAX(MAX(0,C19-'Control Panel'!$C$37)-'Control Panel'!$B$44,0),'Control Panel'!$B$45-'Control Panel'!$B$44)*'Control Panel'!$C$45+MAX(MAX(0,C19-'Control Panel'!$C$37)-'Control Panel'!$B$45,0)*'Control Panel'!$C$46),'Control Panel'!$B$37*'Control Panel'!$B$49) | G19: =E19+F19 | H19: ='Control Panel'!$B$11+C19*'Control Panel'!$B$10 | I19: =G19-H19 | J19: =IF(G19=0,0,I19/G19)
A20: Oct | B20: =K$6 | C20: =ROUND($B$9*B20,0) | D20: =MAX(0,C20-'Control Panel'!$C$37) | E20: ='Control Panel'!$B$37 | F20: =MIN((MIN(MAX(0,C20-'Control Panel'!$C$37),'Control Panel'!$B$43)*'Control Panel'!$C$43+MIN(MAX(MAX(0,C20-'Control Panel'!$C$37)-'Control Panel'!$B$43,0),'Control Panel'!$B$44-'Control Panel'!$B$43)*'Control Panel'!$C$44+MIN(MAX(MAX(0,C20-'Control Panel'!$C$37)-'Control Panel'!$B$44,0),'Control Panel'!$B$45-'Control Panel'!$B$44)*'Control Panel'!$C$45+MAX(MAX(0,C20-'Control Panel'!$C$37)-'Control Panel'!$B$45,0)*'Control Panel'!$C$46),'Control Panel'!$B$37*'Control Panel'!$B$49) | G20: =E20+F20 | H20: ='Control Panel'!$B$11+C20*'Control Panel'!$B$10 | I20: =G20-H20 | J20: =IF(G20=0,0,I20/G20)
A21: Nov | B21: =L$6 | C21: =ROUND($B$9*B21,0) | D21: =MAX(0,C21-'Control Panel'!$C$37) | E21: ='Control Panel'!$B$37 | F21: =MIN((MIN(MAX(0,C21-'Control Panel'!$C$37),'Control Panel'!$B$43)*'Control Panel'!$C$43+MIN(MAX(MAX(0,C21-'Control Panel'!$C$37)-'Control Panel'!$B$43,0),'Control Panel'!$B$44-'Control Panel'!$B$43)*'Control Panel'!$C$44+MIN(MAX(MAX(0,C21-'Control Panel'!$C$37)-'Control Panel'!$B$44,0),'Control Panel'!$B$45-'Control Panel'!$B$44)*'Control Panel'!$C$45+MAX(MAX(0,C21-'Control Panel'!$C$37)-'Control Panel'!$B$45,0)*'Control Panel'!$C$46),'Control Panel'!$B$37*'Control Panel'!$B$49) | G21: =E21+F21 | H21: ='Control Panel'!$B$11+C21*'Control Panel'!$B$10 | I21: =G21-H21 | J21: =IF(G21=0,0,I21/G21)
A22: Dec | B22: =M$6 | C22: =ROUND($B$9*B22,0) | D22: =MAX(0,C22-'Control Panel'!$C$37) | E22: ='Control Panel'!$B$37 | F22: =MIN((MIN(MAX(0,C22-'Control Panel'!$C$37),'Control Panel'!$B$43)*'Control Panel'!$C$43+MIN(MAX(MAX(0,C22-'Control Panel'!$C$37)-'Control Panel'!$B$43,0),'Control Panel'!$B$44-'Control Panel'!$B$43)*'Control Panel'!$C$44+MIN(MAX(MAX(0,C22-'Control Panel'!$C$37)-'Control Panel'!$B$44,0),'Control Panel'!$B$45-'Control Panel'!$B$44)*'Control Panel'!$C$45+MAX(MAX(0,C22-'Control Panel'!$C$37)-'Control Panel'!$B$45,0)*'Control Panel'!$C$46),'Control Panel'!$B$37*'Control Panel'!$B$49) | G22: =E22+F22 | H22: ='Control Panel'!$B$11+C22*'Control Panel'!$B$10 | I22: =G22-H22 | J22: =IF(G22=0,0,I22/G22)
A23: YEAR TOTAL | C23: =SUM(C11:C22) | D23: =SUM(D11:D22) | E23: =SUM(E11:E22) | F23: =SUM(F11:F22) | G23: =SUM(G11:G22) | H23: =SUM(H11:H22) | I23: =SUM(I11:I22) | J23: =IF(G23=0,0,I23/G23)
A25: TYPICAL AGENCY - on Plan Fluent
A26: Baseline conv./mo | B26: 180 | D26: Platform fee | E26: ='Control Panel'!B38 | F26: Included | G26: ='Control Panel'!C38
A27: Month | B27: Mult. | C27: Conversations | D27: Over allowance | E27: Platform rev | F27: Overage rev | G27: Total revenue | H27: Cost | I27: Gross profit | J27: Margin
A28: Jan | B28: =B$6 | C28: =ROUND($B$26*B28,0) | D28: =MAX(0,C28-'Control Panel'!$C$38) | E28: ='Control Panel'!$B$38 | F28: =MIN((MIN(MAX(0,C28-'Control Panel'!$C$38),'Control Panel'!$B$43)*'Control Panel'!$C$43+MIN(MAX(MAX(0,C28-'Control Panel'!$C$38)-'Control Panel'!$B$43,0),'Control Panel'!$B$44-'Control Panel'!$B$43)*'Control Panel'!$C$44+MIN(MAX(MAX(0,C28-'Control Panel'!$C$38)-'Control Panel'!$B$44,0),'Control Panel'!$B$45-'Control Panel'!$B$44)*'Control Panel'!$C$45+MAX(MAX(0,C28-'Control Panel'!$C$38)-'Control Panel'!$B$45,0)*'Control Panel'!$C$46),'Control Panel'!$B$38*'Control Panel'!$B$49) | G28: =E28+F28 | H28: ='Control Panel'!$B$11+C28*'Control Panel'!$B$10 | I28: =G28-H28 | J28: =IF(G28=0,0,I28/G28)
A29: Feb | B29: =C$6 | C29: =ROUND($B$26*B29,0) | D29: =MAX(0,C29-'Control Panel'!$C$38) | E29: ='Control Panel'!$B$38 | F29: =MIN((MIN(MAX(0,C29-'Control Panel'!$C$38),'Control Panel'!$B$43)*'Control Panel'!$C$43+MIN(MAX(MAX(0,C29-'Control Panel'!$C$38)-'Control Panel'!$B$43,0),'Control Panel'!$B$44-'Control Panel'!$B$43)*'Control Panel'!$C$44+MIN(MAX(MAX(0,C29-'Control Panel'!$C$38)-'Control Panel'!$B$44,0),'Control Panel'!$B$45-'Control Panel'!$B$44)*'Control Panel'!$C$45+MAX(MAX(0,C29-'Control Panel'!$C$38)-'Control Panel'!$B$45,0)*'Control Panel'!$C$46),'Control Panel'!$B$38*'Control Panel'!$B$49) | G29: =E29+F29 | H29: ='Control Panel'!$B$11+C29*'Control Panel'!$B$10 | I29: =G29-H29 | J29: =IF(G29=0,0,I29/G29)
A30: Mar | B30: =D$6 | C30: =ROUND($B$26*B30,0) | D30: =MAX(0,C30-'Control Panel'!$C$38) | E30: ='Control Panel'!$B$38 | F30: =MIN((MIN(MAX(0,C30-'Control Panel'!$C$38),'Control Panel'!$B$43)*'Control Panel'!$C$43+MIN(MAX(MAX(0,C30-'Control Panel'!$C$38)-'Control Panel'!$B$43,0),'Control Panel'!$B$44-'Control Panel'!$B$43)*'Control Panel'!$C$44+MIN(MAX(MAX(0,C30-'Control Panel'!$C$38)-'Control Panel'!$B$44,0),'Control Panel'!$B$45-'Control Panel'!$B$44)*'Control Panel'!$C$45+MAX(MAX(0,C30-'Control Panel'!$C$38)-'Control Panel'!$B$45,0)*'Control Panel'!$C$46),'Control Panel'!$B$38*'Control Panel'!$B$49) | G30: =E30+F30 | H30: ='Control Panel'!$B$11+C30*'Control Panel'!$B$10 | I30: =G30-H30 | J30: =IF(G30=0,0,I30/G30)
A31: Apr | B31: =E$6 | C31: =ROUND($B$26*B31,0) | D31: =MAX(0,C31-'Control Panel'!$C$38) | E31: ='Control Panel'!$B$38 | F31: =MIN((MIN(MAX(0,C31-'Control Panel'!$C$38),'Control Panel'!$B$43)*'Control Panel'!$C$43+MIN(MAX(MAX(0,C31-'Control Panel'!$C$38)-'Control Panel'!$B$43,0),'Control Panel'!$B$44-'Control Panel'!$B$43)*'Control Panel'!$C$44+MIN(MAX(MAX(0,C31-'Control Panel'!$C$38)-'Control Panel'!$B$44,0),'Control Panel'!$B$45-'Control Panel'!$B$44)*'Control Panel'!$C$45+MAX(MAX(0,C31-'Control Panel'!$C$38)-'Control Panel'!$B$45,0)*'Control Panel'!$C$46),'Control Panel'!$B$38*'Control Panel'!$B$49) | G31: =E31+F31 | H31: ='Control Panel'!$B$11+C31*'Control Panel'!$B$10 | I31: =G31-H31 | J31: =IF(G31=0,0,I31/G31)
A32: May | B32: =F$6 | C32: =ROUND($B$26*B32,0) | D32: =MAX(0,C32-'Control Panel'!$C$38) | E32: ='Control Panel'!$B$38 | F32: =MIN((MIN(MAX(0,C32-'Control Panel'!$C$38),'Control Panel'!$B$43)*'Control Panel'!$C$43+MIN(MAX(MAX(0,C32-'Control Panel'!$C$38)-'Control Panel'!$B$43,0),'Control Panel'!$B$44-'Control Panel'!$B$43)*'Control Panel'!$C$44+MIN(MAX(MAX(0,C32-'Control Panel'!$C$38)-'Control Panel'!$B$44,0),'Control Panel'!$B$45-'Control Panel'!$B$44)*'Control Panel'!$C$45+MAX(MAX(0,C32-'Control Panel'!$C$38)-'Control Panel'!$B$45,0)*'Control Panel'!$C$46),'Control Panel'!$B$38*'Control Panel'!$B$49) | G32: =E32+F32 | H32: ='Control Panel'!$B$11+C32*'Control Panel'!$B$10 | I32: =G32-H32 | J32: =IF(G32=0,0,I32/G32)
A33: Jun | B33: =G$6 | C33: =ROUND($B$26*B33,0) | D33: =MAX(0,C33-'Control Panel'!$C$38) | E33: ='Control Panel'!$B$38 | F33: =MIN((MIN(MAX(0,C33-'Control Panel'!$C$38),'Control Panel'!$B$43)*'Control Panel'!$C$43+MIN(MAX(MAX(0,C33-'Control Panel'!$C$38)-'Control Panel'!$B$43,0),'Control Panel'!$B$44-'Control Panel'!$B$43)*'Control Panel'!$C$44+MIN(MAX(MAX(0,C33-'Control Panel'!$C$38)-'Control Panel'!$B$44,0),'Control Panel'!$B$45-'Control Panel'!$B$44)*'Control Panel'!$C$45+MAX(MAX(0,C33-'Control Panel'!$C$38)-'Control Panel'!$B$45,0)*'Control Panel'!$C$46),'Control Panel'!$B$38*'Control Panel'!$B$49) | G33: =E33+F33 | H33: ='Control Panel'!$B$11+C33*'Control Panel'!$B$10 | I33: =G33-H33 | J33: =IF(G33=0,0,I33/G33)
A34: Jul | B34: =H$6 | C34: =ROUND($B$26*B34,0) | D34: =MAX(0,C34-'Control Panel'!$C$38) | E34: ='Control Panel'!$B$38 | F34: =MIN((MIN(MAX(0,C34-'Control Panel'!$C$38),'Control Panel'!$B$43)*'Control Panel'!$C$43+MIN(MAX(MAX(0,C34-'Control Panel'!$C$38)-'Control Panel'!$B$43,0),'Control Panel'!$B$44-'Control Panel'!$B$43)*'Control Panel'!$C$44+MIN(MAX(MAX(0,C34-'Control Panel'!$C$38)-'Control Panel'!$B$44,0),'Control Panel'!$B$45-'Control Panel'!$B$44)*'Control Panel'!$C$45+MAX(MAX(0,C34-'Control Panel'!$C$38)-'Control Panel'!$B$45,0)*'Control Panel'!$C$46),'Control Panel'!$B$38*'Control Panel'!$B$49) | G34: =E34+F34 | H34: ='Control Panel'!$B$11+C34*'Control Panel'!$B$10 | I34: =G34-H34 | J34: =IF(G34=0,0,I34/G34)
A35: Aug | B35: =I$6 | C35: =ROUND($B$26*B35,0) | D35: =MAX(0,C35-'Control Panel'!$C$38) | E35: ='Control Panel'!$B$38 | F35: =MIN((MIN(MAX(0,C35-'Control Panel'!$C$38),'Control Panel'!$B$43)*'Control Panel'!$C$43+MIN(MAX(MAX(0,C35-'Control Panel'!$C$38)-'Control Panel'!$B$43,0),'Control Panel'!$B$44-'Control Panel'!$B$43)*'Control Panel'!$C$44+MIN(MAX(MAX(0,C35-'Control Panel'!$C$38)-'Control Panel'!$B$44,0),'Control Panel'!$B$45-'Control Panel'!$B$44)*'Control Panel'!$C$45+MAX(MAX(0,C35-'Control Panel'!$C$38)-'Control Panel'!$B$45,0)*'Control Panel'!$C$46),'Control Panel'!$B$38*'Control Panel'!$B$49) | G35: =E35+F35 | H35: ='Control Panel'!$B$11+C35*'Control Panel'!$B$10 | I35: =G35-H35 | J35: =IF(G35=0,0,I35/G35)
A36: Sep | B36: =J$6 | C36: =ROUND($B$26*B36,0) | D36: =MAX(0,C36-'Control Panel'!$C$38) | E36: ='Control Panel'!$B$38 | F36: =MIN((MIN(MAX(0,C36-'Control Panel'!$C$38),'Control Panel'!$B$43)*'Control Panel'!$C$43+MIN(MAX(MAX(0,C36-'Control Panel'!$C$38)-'Control Panel'!$B$43,0),'Control Panel'!$B$44-'Control Panel'!$B$43)*'Control Panel'!$C$44+MIN(MAX(MAX(0,C36-'Control Panel'!$C$38)-'Control Panel'!$B$44,0),'Control Panel'!$B$45-'Control Panel'!$B$44)*'Control Panel'!$C$45+MAX(MAX(0,C36-'Control Panel'!$C$38)-'Control Panel'!$B$45,0)*'Control Panel'!$C$46),'Control Panel'!$B$38*'Control Panel'!$B$49) | G36: =E36+F36 | H36: ='Control Panel'!$B$11+C36*'Control Panel'!$B$10 | I36: =G36-H36 | J36: =IF(G36=0,0,I36/G36)
A37: Oct | B37: =K$6 | C37: =ROUND($B$26*B37,0) | D37: =MAX(0,C37-'Control Panel'!$C$38) | E37: ='Control Panel'!$B$38 | F37: =MIN((MIN(MAX(0,C37-'Control Panel'!$C$38),'Control Panel'!$B$43)*'Control Panel'!$C$43+MIN(MAX(MAX(0,C37-'Control Panel'!$C$38)-'Control Panel'!$B$43,0),'Control Panel'!$B$44-'Control Panel'!$B$43)*'Control Panel'!$C$44+MIN(MAX(MAX(0,C37-'Control Panel'!$C$38)-'Control Panel'!$B$44,0),'Control Panel'!$B$45-'Control Panel'!$B$44)*'Control Panel'!$C$45+MAX(MAX(0,C37-'Control Panel'!$C$38)-'Control Panel'!$B$45,0)*'Control Panel'!$C$46),'Control Panel'!$B$38*'Control Panel'!$B$49) | G37: =E37+F37 | H37: ='Control Panel'!$B$11+C37*'Control Panel'!$B$10 | I37: =G37-H37 | J37: =IF(G37=0,0,I37/G37)
A38: Nov | B38: =L$6 | C38: =ROUND($B$26*B38,0) | D38: =MAX(0,C38-'Control Panel'!$C$38) | E38: ='Control Panel'!$B$38 | F38: =MIN((MIN(MAX(0,C38-'Control Panel'!$C$38),'Control Panel'!$B$43)*'Control Panel'!$C$43+MIN(MAX(MAX(0,C38-'Control Panel'!$C$38)-'Control Panel'!$B$43,0),'Control Panel'!$B$44-'Control Panel'!$B$43)*'Control Panel'!$C$44+MIN(MAX(MAX(0,C38-'Control Panel'!$C$38)-'Control Panel'!$B$44,0),'Control Panel'!$B$45-'Control Panel'!$B$44)*'Control Panel'!$C$45+MAX(MAX(0,C38-'Control Panel'!$C$38)-'Control Panel'!$B$45,0)*'Control Panel'!$C$46),'Control Panel'!$B$38*'Control Panel'!$B$49) | G38: =E38+F38 | H38: ='Control Panel'!$B$11+C38*'Control Panel'!$B$10 | I38: =G38-H38 | J38: =IF(G38=0,0,I38/G38)
A39: Dec | B39: =M$6 | C39: =ROUND($B$26*B39,0) | D39: =MAX(0,C39-'Control Panel'!$C$38) | E39: ='Control Panel'!$B$38 | F39: =MIN((MIN(MAX(0,C39-'Control Panel'!$C$38),'Control Panel'!$B$43)*'Control Panel'!$C$43+MIN(MAX(MAX(0,C39-'Control Panel'!$C$38)-'Control Panel'!$B$43,0),'Control Panel'!$B$44-'Control Panel'!$B$43)*'Control Panel'!$C$44+MIN(MAX(MAX(0,C39-'Control Panel'!$C$38)-'Control Panel'!$B$44,0),'Control Panel'!$B$45-'Control Panel'!$B$44)*'Control Panel'!$C$45+MAX(MAX(0,C39-'Control Panel'!$C$38)-'Control Panel'!$B$45,0)*'Control Panel'!$C$46),'Control Panel'!$B$38*'Control Panel'!$B$49) | G39: =E39+F39 | H39: ='Control Panel'!$B$11+C39*'Control Panel'!$B$10 | I39: =G39-H39 | J39: =IF(G39=0,0,I39/G39)
A40: YEAR TOTAL | C40: =SUM(C28:C39) | D40: =SUM(D28:D39) | E40: =SUM(E28:E39) | F40: =SUM(F28:F39) | G40: =SUM(G28:G39) | H40: =SUM(H28:H39) | I40: =SUM(I28:I39) | J40: =IF(G40=0,0,I40/G40)
A42: HEAVY AGENCY ON PLAN FLUENT - on Plan Fluent
A43: Baseline conv./mo | B43: 420 | D43: Platform fee | E43: ='Control Panel'!B38 | F43: Included | G43: ='Control Panel'!C38
A44: Month | B44: Mult. | C44: Conversations | D44: Over allowance | E44: Platform rev | F44: Overage rev | G44: Total revenue | H44: Cost | I44: Gross profit | J44: Margin
A45: Jan | B45: =B$6 | C45: =ROUND($B$43*B45,0) | D45: =MAX(0,C45-'Control Panel'!$C$38) | E45: ='Control Panel'!$B$38 | F45: =MIN((MIN(MAX(0,C45-'Control Panel'!$C$38),'Control Panel'!$B$43)*'Control Panel'!$C$43+MIN(MAX(MAX(0,C45-'Control Panel'!$C$38)-'Control Panel'!$B$43,0),'Control Panel'!$B$44-'Control Panel'!$B$43)*'Control Panel'!$C$44+MIN(MAX(MAX(0,C45-'Control Panel'!$C$38)-'Control Panel'!$B$44,0),'Control Panel'!$B$45-'Control Panel'!$B$44)*'Control Panel'!$C$45+MAX(MAX(0,C45-'Control Panel'!$C$38)-'Control Panel'!$B$45,0)*'Control Panel'!$C$46),'Control Panel'!$B$38*'Control Panel'!$B$49) | G45: =E45+F45 | H45: ='Control Panel'!$B$11+C45*'Control Panel'!$B$10 | I45: =G45-H45 | J45: =IF(G45=0,0,I45/G45)
A46: Feb | B46: =C$6 | C46: =ROUND($B$43*B46,0) | D46: =MAX(0,C46-'Control Panel'!$C$38) | E46: ='Control Panel'!$B$38 | F46: =MIN((MIN(MAX(0,C46-'Control Panel'!$C$38),'Control Panel'!$B$43)*'Control Panel'!$C$43+MIN(MAX(MAX(0,C46-'Control Panel'!$C$38)-'Control Panel'!$B$43,0),'Control Panel'!$B$44-'Control Panel'!$B$43)*'Control Panel'!$C$44+MIN(MAX(MAX(0,C46-'Control Panel'!$C$38)-'Control Panel'!$B$44,0),'Control Panel'!$B$45-'Control Panel'!$B$44)*'Control Panel'!$C$45+MAX(MAX(0,C46-'Control Panel'!$C$38)-'Control Panel'!$B$45,0)*'Control Panel'!$C$46),'Control Panel'!$B$38*'Control Panel'!$B$49) | G46: =E46+F46 | H46: ='Control Panel'!$B$11+C46*'Control Panel'!$B$10 | I46: =G46-H46 | J46: =IF(G46=0,0,I46/G46)
A47: Mar | B47: =D$6 | C47: =ROUND($B$43*B47,0) | D47: =MAX(0,C47-'Control Panel'!$C$38) | E47: ='Control Panel'!$B$38 | F47: =MIN((MIN(MAX(0,C47-'Control Panel'!$C$38),'Control Panel'!$B$43)*'Control Panel'!$C$43+MIN(MAX(MAX(0,C47-'Control Panel'!$C$38)-'Control Panel'!$B$43,0),'Control Panel'!$B$44-'Control Panel'!$B$43)*'Control Panel'!$C$44+MIN(MAX(MAX(0,C47-'Control Panel'!$C$38)-'Control Panel'!$B$44,0),'Control Panel'!$B$45-'Control Panel'!$B$44)*'Control Panel'!$C$45+MAX(MAX(0,C47-'Control Panel'!$C$38)-'Control Panel'!$B$45,0)*'Control Panel'!$C$46),'Control Panel'!$B$38*'Control Panel'!$B$49) | G47: =E47+F47 | H47: ='Control Panel'!$B$11+C47*'Control Panel'!$B$10 | I47: =G47-H47 | J47: =IF(G47=0,0,I47/G47)
A48: Apr | B48: =E$6 | C48: =ROUND($B$43*B48,0) | D48: =MAX(0,C48-'Control Panel'!$C$38) | E48: ='Control Panel'!$B$38 | F48: =MIN((MIN(MAX(0,C48-'Control Panel'!$C$38),'Control Panel'!$B$43)*'Control Panel'!$C$43+MIN(MAX(MAX(0,C48-'Control Panel'!$C$38)-'Control Panel'!$B$43,0),'Control Panel'!$B$44-'Control Panel'!$B$43)*'Control Panel'!$C$44+MIN(MAX(MAX(0,C48-'Control Panel'!$C$38)-'Control Panel'!$B$44,0),'Control Panel'!$B$45-'Control Panel'!$B$44)*'Control Panel'!$C$45+MAX(MAX(0,C48-'Control Panel'!$C$38)-'Control Panel'!$B$45,0)*'Control Panel'!$C$46),'Control Panel'!$B$38*'Control Panel'!$B$49) | G48: =E48+F48 | H48: ='Control Panel'!$B$11+C48*'Control Panel'!$B$10 | I48: =G48-H48 | J48: =IF(G48=0,0,I48/G48)
A49: May | B49: =F$6 | C49: =ROUND($B$43*B49,0) | D49: =MAX(0,C49-'Control Panel'!$C$38) | E49: ='Control Panel'!$B$38 | F49: =MIN((MIN(MAX(0,C49-'Control Panel'!$C$38),'Control Panel'!$B$43)*'Control Panel'!$C$43+MIN(MAX(MAX(0,C49-'Control Panel'!$C$38)-'Control Panel'!$B$43,0),'Control Panel'!$B$44-'Control Panel'!$B$43)*'Control Panel'!$C$44+MIN(MAX(MAX(0,C49-'Control Panel'!$C$38)-'Control Panel'!$B$44,0),'Control Panel'!$B$45-'Control Panel'!$B$44)*'Control Panel'!$C$45+MAX(MAX(0,C49-'Control Panel'!$C$38)-'Control Panel'!$B$45,0)*'Control Panel'!$C$46),'Control Panel'!$B$38*'Control Panel'!$B$49) | G49: =E49+F49 | H49: ='Control Panel'!$B$11+C49*'Control Panel'!$B$10 | I49: =G49-H49 | J49: =IF(G49=0,0,I49/G49)
A50: Jun | B50: =G$6 | C50: =ROUND($B$43*B50,0) | D50: =MAX(0,C50-'Control Panel'!$C$38) | E50: ='Control Panel'!$B$38 | F50: =MIN((MIN(MAX(0,C50-'Control Panel'!$C$38),'Control Panel'!$B$43)*'Control Panel'!$C$43+MIN(MAX(MAX(0,C50-'Control Panel'!$C$38)-'Control Panel'!$B$43,0),'Control Panel'!$B$44-'Control Panel'!$B$43)*'Control Panel'!$C$44+MIN(MAX(MAX(0,C50-'Control Panel'!$C$38)-'Control Panel'!$B$44,0),'Control Panel'!$B$45-'Control Panel'!$B$44)*'Control Panel'!$C$45+MAX(MAX(0,C50-'Control Panel'!$C$38)-'Control Panel'!$B$45,0)*'Control Panel'!$C$46),'Control Panel'!$B$38*'Control Panel'!$B$49) | G50: =E50+F50 | H50: ='Control Panel'!$B$11+C50*'Control Panel'!$B$10 | I50: =G50-H50 | J50: =IF(G50=0,0,I50/G50)
A51: Jul | B51: =H$6 | C51: =ROUND($B$43*B51,0) | D51: =MAX(0,C51-'Control Panel'!$C$38) | E51: ='Control Panel'!$B$38 | F51: =MIN((MIN(MAX(0,C51-'Control Panel'!$C$38),'Control Panel'!$B$43)*'Control Panel'!$C$43+MIN(MAX(MAX(0,C51-'Control Panel'!$C$38)-'Control Panel'!$B$43,0),'Control Panel'!$B$44-'Control Panel'!$B$43)*'Control Panel'!$C$44+MIN(MAX(MAX(0,C51-'Control Panel'!$C$38)-'Control Panel'!$B$44,0),'Control Panel'!$B$45-'Control Panel'!$B$44)*'Control Panel'!$C$45+MAX(MAX(0,C51-'Control Panel'!$C$38)-'Control Panel'!$B$45,0)*'Control Panel'!$C$46),'Control Panel'!$B$38*'Control Panel'!$B$49) | G51: =E51+F51 | H51: ='Control Panel'!$B$11+C51*'Control Panel'!$B$10 | I51: =G51-H51 | J51: =IF(G51=0,0,I51/G51)
A52: Aug | B52: =I$6 | C52: =ROUND($B$43*B52,0) | D52: =MAX(0,C52-'Control Panel'!$C$38) | E52: ='Control Panel'!$B$38 | F52: =MIN((MIN(MAX(0,C52-'Control Panel'!$C$38),'Control Panel'!$B$43)*'Control Panel'!$C$43+MIN(MAX(MAX(0,C52-'Control Panel'!$C$38)-'Control Panel'!$B$43,0),'Control Panel'!$B$44-'Control Panel'!$B$43)*'Control Panel'!$C$44+MIN(MAX(MAX(0,C52-'Control Panel'!$C$38)-'Control Panel'!$B$44,0),'Control Panel'!$B$45-'Control Panel'!$B$44)*'Control Panel'!$C$45+MAX(MAX(0,C52-'Control Panel'!$C$38)-'Control Panel'!$B$45,0)*'Control Panel'!$C$46),'Control Panel'!$B$38*'Control Panel'!$B$49) | G52: =E52+F52 | H52: ='Control Panel'!$B$11+C52*'Control Panel'!$B$10 | I52: =G52-H52 | J52: =IF(G52=0,0,I52/G52)
A53: Sep | B53: =J$6 | C53: =ROUND($B$43*B53,0) | D53: =MAX(0,C53-'Control Panel'!$C$38) | E53: ='Control Panel'!$B$38 | F53: =MIN((MIN(MAX(0,C53-'Control Panel'!$C$38),'Control Panel'!$B$43)*'Control Panel'!$C$43+MIN(MAX(MAX(0,C53-'Control Panel'!$C$38)-'Control Panel'!$B$43,0),'Control Panel'!$B$44-'Control Panel'!$B$43)*'Control Panel'!$C$44+MIN(MAX(MAX(0,C53-'Control Panel'!$C$38)-'Control Panel'!$B$44,0),'Control Panel'!$B$45-'Control Panel'!$B$44)*'Control Panel'!$C$45+MAX(MAX(0,C53-'Control Panel'!$C$38)-'Control Panel'!$B$45,0)*'Control Panel'!$C$46),'Control Panel'!$B$38*'Control Panel'!$B$49) | G53: =E53+F53 | H53: ='Control Panel'!$B$11+C53*'Control Panel'!$B$10 | I53: =G53-H53 | J53: =IF(G53=0,0,I53/G53)
A54: Oct | B54: =K$6 | C54: =ROUND($B$43*B54,0) | D54: =MAX(0,C54-'Control Panel'!$C$38) | E54: ='Control Panel'!$B$38 | F54: =MIN((MIN(MAX(0,C54-'Control Panel'!$C$38),'Control Panel'!$B$43)*'Control Panel'!$C$43+MIN(MAX(MAX(0,C54-'Control Panel'!$C$38)-'Control Panel'!$B$43,0),'Control Panel'!$B$44-'Control Panel'!$B$43)*'Control Panel'!$C$44+MIN(MAX(MAX(0,C54-'Control Panel'!$C$38)-'Control Panel'!$B$44,0),'Control Panel'!$B$45-'Control Panel'!$B$44)*'Control Panel'!$C$45+MAX(MAX(0,C54-'Control Panel'!$C$38)-'Control Panel'!$B$45,0)*'Control Panel'!$C$46),'Control Panel'!$B$38*'Control Panel'!$B$49) | G54: =E54+F54 | H54: ='Control Panel'!$B$11+C54*'Control Panel'!$B$10 | I54: =G54-H54 | J54: =IF(G54=0,0,I54/G54)
A55: Nov | B55: =L$6 | C55: =ROUND($B$43*B55,0) | D55: =MAX(0,C55-'Control Panel'!$C$38) | E55: ='Control Panel'!$B$38 | F55: =MIN((MIN(MAX(0,C55-'Control Panel'!$C$38),'Control Panel'!$B$43)*'Control Panel'!$C$43+MIN(MAX(MAX(0,C55-'Control Panel'!$C$38)-'Control Panel'!$B$43,0),'Control Panel'!$B$44-'Control Panel'!$B$43)*'Control Panel'!$C$44+MIN(MAX(MAX(0,C55-'Control Panel'!$C$38)-'Control Panel'!$B$44,0),'Control Panel'!$B$45-'Control Panel'!$B$44)*'Control Panel'!$C$45+MAX(MAX(0,C55-'Control Panel'!$C$38)-'Control Panel'!$B$45,0)*'Control Panel'!$C$46),'Control Panel'!$B$38*'Control Panel'!$B$49) | G55: =E55+F55 | H55: ='Control Panel'!$B$11+C55*'Control Panel'!$B$10 | I55: =G55-H55 | J55: =IF(G55=0,0,I55/G55)
A56: Dec | B56: =M$6 | C56: =ROUND($B$43*B56,0) | D56: =MAX(0,C56-'Control Panel'!$C$38) | E56: ='Control Panel'!$B$38 | F56: =MIN((MIN(MAX(0,C56-'Control Panel'!$C$38),'Control Panel'!$B$43)*'Control Panel'!$C$43+MIN(MAX(MAX(0,C56-'Control Panel'!$C$38)-'Control Panel'!$B$43,0),'Control Panel'!$B$44-'Control Panel'!$B$43)*'Control Panel'!$C$44+MIN(MAX(MAX(0,C56-'Control Panel'!$C$38)-'Control Panel'!$B$44,0),'Control Panel'!$B$45-'Control Panel'!$B$44)*'Control Panel'!$C$45+MAX(MAX(0,C56-'Control Panel'!$C$38)-'Control Panel'!$B$45,0)*'Control Panel'!$C$46),'Control Panel'!$B$38*'Control Panel'!$B$49) | G56: =E56+F56 | H56: ='Control Panel'!$B$11+C56*'Control Panel'!$B$10 | I56: =G56-H56 | J56: =IF(G56=0,0,I56/G56)
A57: YEAR TOTAL | C57: =SUM(C45:C56) | D57: =SUM(D45:D56) | E57: =SUM(E45:E56) | F57: =SUM(F45:F56) | G57: =SUM(G45:G56) | H57: =SUM(H45:H56) | I57: =SUM(I45:I56) | J57: =IF(G57=0,0,I57/G57)
A59: HEAVY AGENCY UPGRADED TO DOWNLINE - on Downline
A60: Baseline conv./mo | B60: 420 | D60: Platform fee | E60: ='Control Panel'!B39 | F60: Included | G60: ='Control Panel'!C39
A61: Month | B61: Mult. | C61: Conversations | D61: Over allowance | E61: Platform rev | F61: Overage rev | G61: Total revenue | H61: Cost | I61: Gross profit | J61: Margin
A62: Jan | B62: =B$6 | C62: =ROUND($B$60*B62,0) | D62: =MAX(0,C62-'Control Panel'!$C$39) | E62: ='Control Panel'!$B$39 | F62: =MIN((MIN(MAX(0,C62-'Control Panel'!$C$39),'Control Panel'!$B$43)*'Control Panel'!$C$43+MIN(MAX(MAX(0,C62-'Control Panel'!$C$39)-'Control Panel'!$B$43,0),'Control Panel'!$B$44-'Control Panel'!$B$43)*'Control Panel'!$C$44+MIN(MAX(MAX(0,C62-'Control Panel'!$C$39)-'Control Panel'!$B$44,0),'Control Panel'!$B$45-'Control Panel'!$B$44)*'Control Panel'!$C$45+MAX(MAX(0,C62-'Control Panel'!$C$39)-'Control Panel'!$B$45,0)*'Control Panel'!$C$46),'Control Panel'!$B$39*'Control Panel'!$B$49) | G62: =E62+F62 | H62: ='Control Panel'!$B$11+C62*'Control Panel'!$B$10 | I62: =G62-H62 | J62: =IF(G62=0,0,I62/G62)
A63: Feb | B63: =C$6 | C63: =ROUND($B$60*B63,0) | D63: =MAX(0,C63-'Control Panel'!$C$39) | E63: ='Control Panel'!$B$39 | F63: =MIN((MIN(MAX(0,C63-'Control Panel'!$C$39),'Control Panel'!$B$43)*'Control Panel'!$C$43+MIN(MAX(MAX(0,C63-'Control Panel'!$C$39)-'Control Panel'!$B$43,0),'Control Panel'!$B$44-'Control Panel'!$B$43)*'Control Panel'!$C$44+MIN(MAX(MAX(0,C63-'Control Panel'!$C$39)-'Control Panel'!$B$44,0),'Control Panel'!$B$45-'Control Panel'!$B$44)*'Control Panel'!$C$45+MAX(MAX(0,C63-'Control Panel'!$C$39)-'Control Panel'!$B$45,0)*'Control Panel'!$C$46),'Control Panel'!$B$39*'Control Panel'!$B$49) | G63: =E63+F63 | H63: ='Control Panel'!$B$11+C63*'Control Panel'!$B$10 | I63: =G63-H63 | J63: =IF(G63=0,0,I63/G63)
A64: Mar | B64: =D$6 | C64: =ROUND($B$60*B64,0) | D64: =MAX(0,C64-'Control Panel'!$C$39) | E64: ='Control Panel'!$B$39 | F64: =MIN((MIN(MAX(0,C64-'Control Panel'!$C$39),'Control Panel'!$B$43)*'Control Panel'!$C$43+MIN(MAX(MAX(0,C64-'Control Panel'!$C$39)-'Control Panel'!$B$43,0),'Control Panel'!$B$44-'Control Panel'!$B$43)*'Control Panel'!$C$44+MIN(MAX(MAX(0,C64-'Control Panel'!$C$39)-'Control Panel'!$B$44,0),'Control Panel'!$B$45-'Control Panel'!$B$44)*'Control Panel'!$C$45+MAX(MAX(0,C64-'Control Panel'!$C$39)-'Control Panel'!$B$45,0)*'Control Panel'!$C$46),'Control Panel'!$B$39*'Control Panel'!$B$49) | G64: =E64+F64 | H64: ='Control Panel'!$B$11+C64*'Control Panel'!$B$10 | I64: =G64-H64 | J64: =IF(G64=0,0,I64/G64)
A65: Apr | B65: =E$6 | C65: =ROUND($B$60*B65,0) | D65: =MAX(0,C65-'Control Panel'!$C$39) | E65: ='Control Panel'!$B$39 | F65: =MIN((MIN(MAX(0,C65-'Control Panel'!$C$39),'Control Panel'!$B$43)*'Control Panel'!$C$43+MIN(MAX(MAX(0,C65-'Control Panel'!$C$39)-'Control Panel'!$B$43,0),'Control Panel'!$B$44-'Control Panel'!$B$43)*'Control Panel'!$C$44+MIN(MAX(MAX(0,C65-'Control Panel'!$C$39)-'Control Panel'!$B$44,0),'Control Panel'!$B$45-'Control Panel'!$B$44)*'Control Panel'!$C$45+MAX(MAX(0,C65-'Control Panel'!$C$39)-'Control Panel'!$B$45,0)*'Control Panel'!$C$46),'Control Panel'!$B$39*'Control Panel'!$B$49) | G65: =E65+F65 | H65: ='Control Panel'!$B$11+C65*'Control Panel'!$B$10 | I65: =G65-H65 | J65: =IF(G65=0,0,I65/G65)
A66: May | B66: =F$6 | C66: =ROUND($B$60*B66,0) | D66: =MAX(0,C66-'Control Panel'!$C$39) | E66: ='Control Panel'!$B$39 | F66: =MIN((MIN(MAX(0,C66-'Control Panel'!$C$39),'Control Panel'!$B$43)*'Control Panel'!$C$43+MIN(MAX(MAX(0,C66-'Control Panel'!$C$39)-'Control Panel'!$B$43,0),'Control Panel'!$B$44-'Control Panel'!$B$43)*'Control Panel'!$C$44+MIN(MAX(MAX(0,C66-'Control Panel'!$C$39)-'Control Panel'!$B$44,0),'Control Panel'!$B$45-'Control Panel'!$B$44)*'Control Panel'!$C$45+MAX(MAX(0,C66-'Control Panel'!$C$39)-'Control Panel'!$B$45,0)*'Control Panel'!$C$46),'Control Panel'!$B$39*'Control Panel'!$B$49) | G66: =E66+F66 | H66: ='Control Panel'!$B$11+C66*'Control Panel'!$B$10 | I66: =G66-H66 | J66: =IF(G66=0,0,I66/G66)
A67: Jun | B67: =G$6 | C67: =ROUND($B$60*B67,0) | D67: =MAX(0,C67-'Control Panel'!$C$39) | E67: ='Control Panel'!$B$39 | F67: =MIN((MIN(MAX(0,C67-'Control Panel'!$C$39),'Control Panel'!$B$43)*'Control Panel'!$C$43+MIN(MAX(MAX(0,C67-'Control Panel'!$C$39)-'Control Panel'!$B$43,0),'Control Panel'!$B$44-'Control Panel'!$B$43)*'Control Panel'!$C$44+MIN(MAX(MAX(0,C67-'Control Panel'!$C$39)-'Control Panel'!$B$44,0),'Control Panel'!$B$45-'Control Panel'!$B$44)*'Control Panel'!$C$45+MAX(MAX(0,C67-'Control Panel'!$C$39)-'Control Panel'!$B$45,0)*'Control Panel'!$C$46),'Control Panel'!$B$39*'Control Panel'!$B$49) | G67: =E67+F67 | H67: ='Control Panel'!$B$11+C67*'Control Panel'!$B$10 | I67: =G67-H67 | J67: =IF(G67=0,0,I67/G67)
A68: Jul | B68: =H$6 | C68: =ROUND($B$60*B68,0) | D68: =MAX(0,C68-'Control Panel'!$C$39) | E68: ='Control Panel'!$B$39 | F68: =MIN((MIN(MAX(0,C68-'Control Panel'!$C$39),'Control Panel'!$B$43)*'Control Panel'!$C$43+MIN(MAX(MAX(0,C68-'Control Panel'!$C$39)-'Control Panel'!$B$43,0),'Control Panel'!$B$44-'Control Panel'!$B$43)*'Control Panel'!$C$44+MIN(MAX(MAX(0,C68-'Control Panel'!$C$39)-'Control Panel'!$B$44,0),'Control Panel'!$B$45-'Control Panel'!$B$44)*'Control Panel'!$C$45+MAX(MAX(0,C68-'Control Panel'!$C$39)-'Control Panel'!$B$45,0)*'Control Panel'!$C$46),'Control Panel'!$B$39*'Control Panel'!$B$49) | G68: =E68+F68 | H68: ='Control Panel'!$B$11+C68*'Control Panel'!$B$10 | I68: =G68-H68 | J68: =IF(G68=0,0,I68/G68)
A69: Aug | B69: =I$6 | C69: =ROUND($B$60*B69,0) | D69: =MAX(0,C69-'Control Panel'!$C$39) | E69: ='Control Panel'!$B$39 | F69: =MIN((MIN(MAX(0,C69-'Control Panel'!$C$39),'Control Panel'!$B$43)*'Control Panel'!$C$43+MIN(MAX(MAX(0,C69-'Control Panel'!$C$39)-'Control Panel'!$B$43,0),'Control Panel'!$B$44-'Control Panel'!$B$43)*'Control Panel'!$C$44+MIN(MAX(MAX(0,C69-'Control Panel'!$C$39)-'Control Panel'!$B$44,0),'Control Panel'!$B$45-'Control Panel'!$B$44)*'Control Panel'!$C$45+MAX(MAX(0,C69-'Control Panel'!$C$39)-'Control Panel'!$B$45,0)*'Control Panel'!$C$46),'Control Panel'!$B$39*'Control Panel'!$B$49) | G69: =E69+F69 | H69: ='Control Panel'!$B$11+C69*'Control Panel'!$B$10 | I69: =G69-H69 | J69: =IF(G69=0,0,I69/G69)
A70: Sep | B70: =J$6 | C70: =ROUND($B$60*B70,0) | D70: =MAX(0,C70-'Control Panel'!$C$39) | E70: ='Control Panel'!$B$39 | F70: =MIN((MIN(MAX(0,C70-'Control Panel'!$C$39),'Control Panel'!$B$43)*'Control Panel'!$C$43+MIN(MAX(MAX(0,C70-'Control Panel'!$C$39)-'Control Panel'!$B$43,0),'Control Panel'!$B$44-'Control Panel'!$B$43)*'Control Panel'!$C$44+MIN(MAX(MAX(0,C70-'Control Panel'!$C$39)-'Control Panel'!$B$44,0),'Control Panel'!$B$45-'Control Panel'!$B$44)*'Control Panel'!$C$45+MAX(MAX(0,C70-'Control Panel'!$C$39)-'Control Panel'!$B$45,0)*'Control Panel'!$C$46),'Control Panel'!$B$39*'Control Panel'!$B$49) | G70: =E70+F70 | H70: ='Control Panel'!$B$11+C70*'Control Panel'!$B$10 | I70: =G70-H70 | J70: =IF(G70=0,0,I70/G70)
A71: Oct | B71: =K$6 | C71: =ROUND($B$60*B71,0) | D71: =MAX(0,C71-'Control Panel'!$C$39) | E71: ='Control Panel'!$B$39 | F71: =MIN((MIN(MAX(0,C71-'Control Panel'!$C$39),'Control Panel'!$B$43)*'Control Panel'!$C$43+MIN(MAX(MAX(0,C71-'Control Panel'!$C$39)-'Control Panel'!$B$43,0),'Control Panel'!$B$44-'Control Panel'!$B$43)*'Control Panel'!$C$44+MIN(MAX(MAX(0,C71-'Control Panel'!$C$39)-'Control Panel'!$B$44,0),'Control Panel'!$B$45-'Control Panel'!$B$44)*'Control Panel'!$C$45+MAX(MAX(0,C71-'Control Panel'!$C$39)-'Control Panel'!$B$45,0)*'Control Panel'!$C$46),'Control Panel'!$B$39*'Control Panel'!$B$49) | G71: =E71+F71 | H71: ='Control Panel'!$B$11+C71*'Control Panel'!$B$10 | I71: =G71-H71 | J71: =IF(G71=0,0,I71/G71)
A72: Nov | B72: =L$6 | C72: =ROUND($B$60*B72,0) | D72: =MAX(0,C72-'Control Panel'!$C$39) | E72: ='Control Panel'!$B$39 | F72: =MIN((MIN(MAX(0,C72-'Control Panel'!$C$39),'Control Panel'!$B$43)*'Control Panel'!$C$43+MIN(MAX(MAX(0,C72-'Control Panel'!$C$39)-'Control Panel'!$B$43,0),'Control Panel'!$B$44-'Control Panel'!$B$43)*'Control Panel'!$C$44+MIN(MAX(MAX(0,C72-'Control Panel'!$C$39)-'Control Panel'!$B$44,0),'Control Panel'!$B$45-'Control Panel'!$B$44)*'Control Panel'!$C$45+MAX(MAX(0,C72-'Control Panel'!$C$39)-'Control Panel'!$B$45,0)*'Control Panel'!$C$46),'Control Panel'!$B$39*'Control Panel'!$B$49) | G72: =E72+F72 | H72: ='Control Panel'!$B$11+C72*'Control Panel'!$B$10 | I72: =G72-H72 | J72: =IF(G72=0,0,I72/G72)
A73: Dec | B73: =M$6 | C73: =ROUND($B$60*B73,0) | D73: =MAX(0,C73-'Control Panel'!$C$39) | E73: ='Control Panel'!$B$39 | F73: =MIN((MIN(MAX(0,C73-'Control Panel'!$C$39),'Control Panel'!$B$43)*'Control Panel'!$C$43+MIN(MAX(MAX(0,C73-'Control Panel'!$C$39)-'Control Panel'!$B$43,0),'Control Panel'!$B$44-'Control Panel'!$B$43)*'Control Panel'!$C$44+MIN(MAX(MAX(0,C73-'Control Panel'!$C$39)-'Control Panel'!$B$44,0),'Control Panel'!$B$45-'Control Panel'!$B$44)*'Control Panel'!$C$45+MAX(MAX(0,C73-'Control Panel'!$C$39)-'Control Panel'!$B$45,0)*'Control Panel'!$C$46),'Control Panel'!$B$39*'Control Panel'!$B$49) | G73: =E73+F73 | H73: ='Control Panel'!$B$11+C73*'Control Panel'!$B$10 | I73: =G73-H73 | J73: =IF(G73=0,0,I73/G73)
A74: YEAR TOTAL | C74: =SUM(C62:C73) | D74: =SUM(D62:D73) | E74: =SUM(E62:E73) | F74: =SUM(F62:F73) | G74: =SUM(G62:G73) | H74: =SUM(H62:H73) | I74: =SUM(I62:I73) | J74: =IF(G74=0,0,I74/G74)
A76: Blocks three and four are the same agency on two different tiers. That contrast is the upgrade conversation, in numbers.

Sheet Sensitivity
A1: Sensitivity - Plan Fluent price against real usage
A2: Gross margin at each combination. Rows are the platform fee you could charge, columns are what an account actually uses. Allowance and costs come from the Control Panel.
A4: GROSS MARGIN GRID
A5: Fee \ Conversations | B5: 100 | C5: 200 | D5: 300 | E5: 400 | F5: 500 | G5: 600 | H5: 700 | I5: 800 | J5: 900 | K5: 1000
A6: 249 | B6: =(($A6+MIN((MIN(MAX(0,B$5-'Control Panel'!$C$38),'Control Panel'!$B$43)*'Control Panel'!$C$43+MIN(MAX(MAX(0,B$5-'Control Panel'!$C$38)-'Control Panel'!$B$43,0),'Control Panel'!$B$44-'Control Panel'!$B$43)*'Control Panel'!$C$44+MIN(MAX(MAX(0,B$5-'Control Panel'!$C$38)-'Control Panel'!$B$44,0),'Control Panel'!$B$45-'Control Panel'!$B$44)*'Control Panel'!$C$45+MAX(MAX(0,B$5-'Control Panel'!$C$38)-'Control Panel'!$B$45,0)*'Control Panel'!$C$46),$A6*'Control Panel'!$B$49))-('Control Panel'!$B$11+B$5*'Control Panel'!$B$10))/($A6+MIN((MIN(MAX(0,B$5-'Control Panel'!$C$38),'Control Panel'!$B$43)*'Control Panel'!$C$43+MIN(MAX(MAX(0,B$5-'Control Panel'!$C$38)-'Control Panel'!$B$43,0),'Control Panel'!$B$44-'Control Panel'!$B$43)*'Control Panel'!$C$44+MIN(MAX(MAX(0,B$5-'Control Panel'!$C$38)-'Control Panel'!$B$44,0),'Control Panel'!$B$45-'Control Panel'!$B$44)*'Control Panel'!$C$45+MAX(MAX(0,B$5-'Control Panel'!$C$38)-'Control Panel'!$B$45,0)*'Control Panel'!$C$46),$A6*'Control Panel'!$B$49)) | C6: =(($A6+MIN((MIN(MAX(0,C$5-'Control Panel'!$C$38),'Control Panel'!$B$43)*'Control Panel'!$C$43+MIN(MAX(MAX(0,C$5-'Control Panel'!$C$38)-'Control Panel'!$B$43,0),'Control Panel'!$B$44-'Control Panel'!$B$43)*'Control Panel'!$C$44+MIN(MAX(MAX(0,C$5-'Control Panel'!$C$38)-'Control Panel'!$B$44,0),'Control Panel'!$B$45-'Control Panel'!$B$44)*'Control Panel'!$C$45+MAX(MAX(0,C$5-'Control Panel'!$C$38)-'Control Panel'!$B$45,0)*'Control Panel'!$C$46),$A6*'Control Panel'!$B$49))-('Control Panel'!$B$11+C$5*'Control Panel'!$B$10))/($A6+MIN((MIN(MAX(0,C$5-'Control Panel'!$C$38),'Control Panel'!$B$43)*'Control Panel'!$C$43+MIN(MAX(MAX(0,C$5-'Control Panel'!$C$38)-'Control Panel'!$B$43,0),'Control Panel'!$B$44-'Control Panel'!$B$43)*'Control Panel'!$C$44+MIN(MAX(MAX(0,C$5-'Control Panel'!$C$38)-'Control Panel'!$B$44,0),'Control Panel'!$B$45-'Control Panel'!$B$44)*'Control Panel'!$C$45+MAX(MAX(0,C$5-'Control Panel'!$C$38)-'Control Panel'!$B$45,0)*'Control Panel'!$C$46),$A6*'Control Panel'!$B$49)) | D6: =(($A6+MIN((MIN(MAX(0,D$5-'Control Panel'!$C$38),'Control Panel'!$B$43)*'Control Panel'!$C$43+MIN(MAX(MAX(0,D$5-'Control Panel'!$C$38)-'Control Panel'!$B$43,0),'Control Panel'!$B$44-'Control Panel'!$B$43)*'Control Panel'!$C$44+MIN(MAX(MAX(0,D$5-'Control Panel'!$C$38)-'Control Panel'!$B$44,0),'Control Panel'!$B$45-'Control Panel'!$B$44)*'Control Panel'!$C$45+MAX(MAX(0,D$5-'Control Panel'!$C$38)-'Control Panel'!$B$45,0)*'Control Panel'!$C$46),$A6*'Control Panel'!$B$49))-('Control Panel'!$B$11+D$5*'Control Panel'!$B$10))/($A6+MIN((MIN(MAX(0,D$5-'Control Panel'!$C$38),'Control Panel'!$B$43)*'Control Panel'!$C$43+MIN(MAX(MAX(0,D$5-'Control Panel'!$C$38)-'Control Panel'!$B$43,0),'Control Panel'!$B$44-'Control Panel'!$B$43)*'Control Panel'!$C$44+MIN(MAX(MAX(0,D$5-'Control Panel'!$C$38)-'Control Panel'!$B$44,0),'Control Panel'!$B$45-'Control Panel'!$B$44)*'Control Panel'!$C$45+MAX(MAX(0,D$5-'Control Panel'!$C$38)-'Control Panel'!$B$45,0)*'Control Panel'!$C$46),$A6*'Control Panel'!$B$49)) | E6: =(($A6+MIN((MIN(MAX(0,E$5-'Control Panel'!$C$38),'Control Panel'!$B$43)*'Control Panel'!$C$43+MIN(MAX(MAX(0,E$5-'Control Panel'!$C$38)-'Control Panel'!$B$43,0),'Control Panel'!$B$44-'Control Panel'!$B$43)*'Control Panel'!$C$44+MIN(MAX(MAX(0,E$5-'Control Panel'!$C$38)-'Control Panel'!$B$44,0),'Control Panel'!$B$45-'Control Panel'!$B$44)*'Control Panel'!$C$45+MAX(MAX(0,E$5-'Control Panel'!$C$38)-'Control Panel'!$B$45,0)*'Control Panel'!$C$46),$A6*'Control Panel'!$B$49))-('Control Panel'!$B$11+E$5*'Control Panel'!$B$10))/($A6+MIN((MIN(MAX(0,E$5-'Control Panel'!$C$38),'Control Panel'!$B$43)*'Control Panel'!$C$43+MIN(MAX(MAX(0,E$5-'Control Panel'!$C$38)-'Control Panel'!$B$43,0),'Control Panel'!$B$44-'Control Panel'!$B$43)*'Control Panel'!$C$44+MIN(MAX(MAX(0,E$5-'Control Panel'!$C$38)-'Control Panel'!$B$44,0),'Control Panel'!$B$45-'Control Panel'!$B$44)*'Control Panel'!$C$45+MAX(MAX(0,E$5-'Control Panel'!$C$38)-'Control Panel'!$B$45,0)*'Control Panel'!$C$46),$A6*'Control Panel'!$B$49)) | F6: =(($A6+MIN((MIN(MAX(0,F$5-'Control Panel'!$C$38),'Control Panel'!$B$43)*'Control Panel'!$C$43+MIN(MAX(MAX(0,F$5-'Control Panel'!$C$38)-'Control Panel'!$B$43,0),'Control Panel'!$B$44-'Control Panel'!$B$43)*'Control Panel'!$C$44+MIN(MAX(MAX(0,F$5-'Control Panel'!$C$38)-'Control Panel'!$B$44,0),'Control Panel'!$B$45-'Control Panel'!$B$44)*'Control Panel'!$C$45+MAX(MAX(0,F$5-'Control Panel'!$C$38)-'Control Panel'!$B$45,0)*'Control Panel'!$C$46),$A6*'Control Panel'!$B$49))-('Control Panel'!$B$11+F$5*'Control Panel'!$B$10))/($A6+MIN((MIN(MAX(0,F$5-'Control Panel'!$C$38),'Control Panel'!$B$43)*'Control Panel'!$C$43+MIN(MAX(MAX(0,F$5-'Control Panel'!$C$38)-'Control Panel'!$B$43,0),'Control Panel'!$B$44-'Control Panel'!$B$43)*'Control Panel'!$C$44+MIN(MAX(MAX(0,F$5-'Control Panel'!$C$38)-'Control Panel'!$B$44,0),'Control Panel'!$B$45-'Control Panel'!$B$44)*'Control Panel'!$C$45+MAX(MAX(0,F$5-'Control Panel'!$C$38)-'Control Panel'!$B$45,0)*'Control Panel'!$C$46),$A6*'Control Panel'!$B$49)) | G6: =(($A6+MIN((MIN(MAX(0,G$5-'Control Panel'!$C$38),'Control Panel'!$B$43)*'Control Panel'!$C$43+MIN(MAX(MAX(0,G$5-'Control Panel'!$C$38)-'Control Panel'!$B$43,0),'Control Panel'!$B$44-'Control Panel'!$B$43)*'Control Panel'!$C$44+MIN(MAX(MAX(0,G$5-'Control Panel'!$C$38)-'Control Panel'!$B$44,0),'Control Panel'!$B$45-'Control Panel'!$B$44)*'Control Panel'!$C$45+MAX(MAX(0,G$5-'Control Panel'!$C$38)-'Control Panel'!$B$45,0)*'Control Panel'!$C$46),$A6*'Control Panel'!$B$49))-('Control Panel'!$B$11+G$5*'Control Panel'!$B$10))/($A6+MIN((MIN(MAX(0,G$5-'Control Panel'!$C$38),'Control Panel'!$B$43)*'Control Panel'!$C$43+MIN(MAX(MAX(0,G$5-'Control Panel'!$C$38)-'Control Panel'!$B$43,0),'Control Panel'!$B$44-'Control Panel'!$B$43)*'Control Panel'!$C$44+MIN(MAX(MAX(0,G$5-'Control Panel'!$C$38)-'Control Panel'!$B$44,0),'Control Panel'!$B$45-'Control Panel'!$B$44)*'Control Panel'!$C$45+MAX(MAX(0,G$5-'Control Panel'!$C$38)-'Control Panel'!$B$45,0)*'Control Panel'!$C$46),$A6*'Control Panel'!$B$49)) | H6: =(($A6+MIN((MIN(MAX(0,H$5-'Control Panel'!$C$38),'Control Panel'!$B$43)*'Control Panel'!$C$43+MIN(MAX(MAX(0,H$5-'Control Panel'!$C$38)-'Control Panel'!$B$43,0),'Control Panel'!$B$44-'Control Panel'!$B$43)*'Control Panel'!$C$44+MIN(MAX(MAX(0,H$5-'Control Panel'!$C$38)-'Control Panel'!$B$44,0),'Control Panel'!$B$45-'Control Panel'!$B$44)*'Control Panel'!$C$45+MAX(MAX(0,H$5-'Control Panel'!$C$38)-'Control Panel'!$B$45,0)*'Control Panel'!$C$46),$A6*'Control Panel'!$B$49))-('Control Panel'!$B$11+H$5*'Control Panel'!$B$10))/($A6+MIN((MIN(MAX(0,H$5-'Control Panel'!$C$38),'Control Panel'!$B$43)*'Control Panel'!$C$43+MIN(MAX(MAX(0,H$5-'Control Panel'!$C$38)-'Control Panel'!$B$43,0),'Control Panel'!$B$44-'Control Panel'!$B$43)*'Control Panel'!$C$44+MIN(MAX(MAX(0,H$5-'Control Panel'!$C$38)-'Control Panel'!$B$44,0),'Control Panel'!$B$45-'Control Panel'!$B$44)*'Control Panel'!$C$45+MAX(MAX(0,H$5-'Control Panel'!$C$38)-'Control Panel'!$B$45,0)*'Control Panel'!$C$46),$A6*'Control Panel'!$B$49)) | I6: =(($A6+MIN((MIN(MAX(0,I$5-'Control Panel'!$C$38),'Control Panel'!$B$43)*'Control Panel'!$C$43+MIN(MAX(MAX(0,I$5-'Control Panel'!$C$38)-'Control Panel'!$B$43,0),'Control Panel'!$B$44-'Control Panel'!$B$43)*'Control Panel'!$C$44+MIN(MAX(MAX(0,I$5-'Control Panel'!$C$38)-'Control Panel'!$B$44,0),'Control Panel'!$B$45-'Control Panel'!$B$44)*'Control Panel'!$C$45+MAX(MAX(0,I$5-'Control Panel'!$C$38)-'Control Panel'!$B$45,0)*'Control Panel'!$C$46),$A6*'Control Panel'!$B$49))-('Control Panel'!$B$11+I$5*'Control Panel'!$B$10))/($A6+MIN((MIN(MAX(0,I$5-'Control Panel'!$C$38),'Control Panel'!$B$43)*'Control Panel'!$C$43+MIN(MAX(MAX(0,I$5-'Control Panel'!$C$38)-'Control Panel'!$B$43,0),'Control Panel'!$B$44-'Control Panel'!$B$43)*'Control Panel'!$C$44+MIN(MAX(MAX(0,I$5-'Control Panel'!$C$38)-'Control Panel'!$B$44,0),'Control Panel'!$B$45-'Control Panel'!$B$44)*'Control Panel'!$C$45+MAX(MAX(0,I$5-'Control Panel'!$C$38)-'Control Panel'!$B$45,0)*'Control Panel'!$C$46),$A6*'Control Panel'!$B$49)) | ... K6: =(($A6+MIN((MIN(MAX(0,K$5-'Control Panel'!$C$38),'Control Panel'!$B$43)*'Control Panel'!$C$43+MIN(MAX(MAX(0,K$5-'Control Panel'!$C$38)-'Control Panel'!$B$43,0),'Control Panel'!$B$44-'Control Panel'!$B$43)*'Control Panel'!$C$44+MIN(MAX(MAX(0,K$5-'Control Panel'!$C$38)-'Control Panel'!$B$44,0),'Control Panel'!$B$45-'Control Panel'!$B$44)*'Control Panel'!$C$45+MAX(MAX(0,K$5-'Control Panel'!$C$38)-'Control Panel'!$B$45,0)*'Control Panel'!$C$46),$A6*'Control Panel'!$B$49))-('Control Panel'!$B$11+K$5*'Control Panel'!$B$10))/($A6+MIN((MIN(MAX(0,K$5-'Control Panel'!$C$38),'Control Panel'!$B$43)*'Control Panel'!$C$43+MIN(MAX(MAX(0,K$5-'Control Panel'!$C$38)-'Control Panel'!$B$43,0),'Control Panel'!$B$44-'Control Panel'!$B$43)*'Control Panel'!$C$44+MIN(MAX(MAX(0,K$5-'Control Panel'!$C$38)-'Control Panel'!$B$44,0),'Control Panel'!$B$45-'Control Panel'!$B$44)*'Control Panel'!$C$45+MAX(MAX(0,K$5-'Control Panel'!$C$38)-'Control Panel'!$B$45,0)*'Control Panel'!$C$46),$A6*'Control Panel'!$B$49))
A7: 299 | B7: =(($A7+MIN((MIN(MAX(0,B$5-'Control Panel'!$C$38),'Control Panel'!$B$43)*'Control Panel'!$C$43+MIN(MAX(MAX(0,B$5-'Control Panel'!$C$38)-'Control Panel'!$B$43,0),'Control Panel'!$B$44-'Control Panel'!$B$43)*'Control Panel'!$C$44+MIN(MAX(MAX(0,B$5-'Control Panel'!$C$38)-'Control Panel'!$B$44,0),'Control Panel'!$B$45-'Control Panel'!$B$44)*'Control Panel'!$C$45+MAX(MAX(0,B$5-'Control Panel'!$C$38)-'Control Panel'!$B$45,0)*'Control Panel'!$C$46),$A7*'Control Panel'!$B$49))-('Control Panel'!$B$11+B$5*'Control Panel'!$B$10))/($A7+MIN((MIN(MAX(0,B$5-'Control Panel'!$C$38),'Control Panel'!$B$43)*'Control Panel'!$C$43+MIN(MAX(MAX(0,B$5-'Control Panel'!$C$38)-'Control Panel'!$B$43,0),'Control Panel'!$B$44-'Control Panel'!$B$43)*'Control Panel'!$C$44+MIN(MAX(MAX(0,B$5-'Control Panel'!$C$38)-'Control Panel'!$B$44,0),'Control Panel'!$B$45-'Control Panel'!$B$44)*'Control Panel'!$C$45+MAX(MAX(0,B$5-'Control Panel'!$C$38)-'Control Panel'!$B$45,0)*'Control Panel'!$C$46),$A7*'Control Panel'!$B$49)) | C7: =(($A7+MIN((MIN(MAX(0,C$5-'Control Panel'!$C$38),'Control Panel'!$B$43)*'Control Panel'!$C$43+MIN(MAX(MAX(0,C$5-'Control Panel'!$C$38)-'Control Panel'!$B$43,0),'Control Panel'!$B$44-'Control Panel'!$B$43)*'Control Panel'!$C$44+MIN(MAX(MAX(0,C$5-'Control Panel'!$C$38)-'Control Panel'!$B$44,0),'Control Panel'!$B$45-'Control Panel'!$B$44)*'Control Panel'!$C$45+MAX(MAX(0,C$5-'Control Panel'!$C$38)-'Control Panel'!$B$45,0)*'Control Panel'!$C$46),$A7*'Control Panel'!$B$49))-('Control Panel'!$B$11+C$5*'Control Panel'!$B$10))/($A7+MIN((MIN(MAX(0,C$5-'Control Panel'!$C$38),'Control Panel'!$B$43)*'Control Panel'!$C$43+MIN(MAX(MAX(0,C$5-'Control Panel'!$C$38)-'Control Panel'!$B$43,0),'Control Panel'!$B$44-'Control Panel'!$B$43)*'Control Panel'!$C$44+MIN(MAX(MAX(0,C$5-'Control Panel'!$C$38)-'Control Panel'!$B$44,0),'Control Panel'!$B$45-'Control Panel'!$B$44)*'Control Panel'!$C$45+MAX(MAX(0,C$5-'Control Panel'!$C$38)-'Control Panel'!$B$45,0)*'Control Panel'!$C$46),$A7*'Control Panel'!$B$49)) | D7: =(($A7+MIN((MIN(MAX(0,D$5-'Control Panel'!$C$38),'Control Panel'!$B$43)*'Control Panel'!$C$43+MIN(MAX(MAX(0,D$5-'Control Panel'!$C$38)-'Control Panel'!$B$43,0),'Control Panel'!$B$44-'Control Panel'!$B$43)*'Control Panel'!$C$44+MIN(MAX(MAX(0,D$5-'Control Panel'!$C$38)-'Control Panel'!$B$44,0),'Control Panel'!$B$45-'Control Panel'!$B$44)*'Control Panel'!$C$45+MAX(MAX(0,D$5-'Control Panel'!$C$38)-'Control Panel'!$B$45,0)*'Control Panel'!$C$46),$A7*'Control Panel'!$B$49))-('Control Panel'!$B$11+D$5*'Control Panel'!$B$10))/($A7+MIN((MIN(MAX(0,D$5-'Control Panel'!$C$38),'Control Panel'!$B$43)*'Control Panel'!$C$43+MIN(MAX(MAX(0,D$5-'Control Panel'!$C$38)-'Control Panel'!$B$43,0),'Control Panel'!$B$44-'Control Panel'!$B$43)*'Control Panel'!$C$44+MIN(MAX(MAX(0,D$5-'Control Panel'!$C$38)-'Control Panel'!$B$44,0),'Control Panel'!$B$45-'Control Panel'!$B$44)*'Control Panel'!$C$45+MAX(MAX(0,D$5-'Control Panel'!$C$38)-'Control Panel'!$B$45,0)*'Control Panel'!$C$46),$A7*'Control Panel'!$B$49)) | E7: =(($A7+MIN((MIN(MAX(0,E$5-'Control Panel'!$C$38),'Control Panel'!$B$43)*'Control Panel'!$C$43+MIN(MAX(MAX(0,E$5-'Control Panel'!$C$38)-'Control Panel'!$B$43,0),'Control Panel'!$B$44-'Control Panel'!$B$43)*'Control Panel'!$C$44+MIN(MAX(MAX(0,E$5-'Control Panel'!$C$38)-'Control Panel'!$B$44,0),'Control Panel'!$B$45-'Control Panel'!$B$44)*'Control Panel'!$C$45+MAX(MAX(0,E$5-'Control Panel'!$C$38)-'Control Panel'!$B$45,0)*'Control Panel'!$C$46),$A7*'Control Panel'!$B$49))-('Control Panel'!$B$11+E$5*'Control Panel'!$B$10))/($A7+MIN((MIN(MAX(0,E$5-'Control Panel'!$C$38),'Control Panel'!$B$43)*'Control Panel'!$C$43+MIN(MAX(MAX(0,E$5-'Control Panel'!$C$38)-'Control Panel'!$B$43,0),'Control Panel'!$B$44-'Control Panel'!$B$43)*'Control Panel'!$C$44+MIN(MAX(MAX(0,E$5-'Control Panel'!$C$38)-'Control Panel'!$B$44,0),'Control Panel'!$B$45-'Control Panel'!$B$44)*'Control Panel'!$C$45+MAX(MAX(0,E$5-'Control Panel'!$C$38)-'Control Panel'!$B$45,0)*'Control Panel'!$C$46),$A7*'Control Panel'!$B$49)) | F7: =(($A7+MIN((MIN(MAX(0,F$5-'Control Panel'!$C$38),'Control Panel'!$B$43)*'Control Panel'!$C$43+MIN(MAX(MAX(0,F$5-'Control Panel'!$C$38)-'Control Panel'!$B$43,0),'Control Panel'!$B$44-'Control Panel'!$B$43)*'Control Panel'!$C$44+MIN(MAX(MAX(0,F$5-'Control Panel'!$C$38)-'Control Panel'!$B$44,0),'Control Panel'!$B$45-'Control Panel'!$B$44)*'Control Panel'!$C$45+MAX(MAX(0,F$5-'Control Panel'!$C$38)-'Control Panel'!$B$45,0)*'Control Panel'!$C$46),$A7*'Control Panel'!$B$49))-('Control Panel'!$B$11+F$5*'Control Panel'!$B$10))/($A7+MIN((MIN(MAX(0,F$5-'Control Panel'!$C$38),'Control Panel'!$B$43)*'Control Panel'!$C$43+MIN(MAX(MAX(0,F$5-'Control Panel'!$C$38)-'Control Panel'!$B$43,0),'Control Panel'!$B$44-'Control Panel'!$B$43)*'Control Panel'!$C$44+MIN(MAX(MAX(0,F$5-'Control Panel'!$C$38)-'Control Panel'!$B$44,0),'Control Panel'!$B$45-'Control Panel'!$B$44)*'Control Panel'!$C$45+MAX(MAX(0,F$5-'Control Panel'!$C$38)-'Control Panel'!$B$45,0)*'Control Panel'!$C$46),$A7*'Control Panel'!$B$49)) | G7: =(($A7+MIN((MIN(MAX(0,G$5-'Control Panel'!$C$38),'Control Panel'!$B$43)*'Control Panel'!$C$43+MIN(MAX(MAX(0,G$5-'Control Panel'!$C$38)-'Control Panel'!$B$43,0),'Control Panel'!$B$44-'Control Panel'!$B$43)*'Control Panel'!$C$44+MIN(MAX(MAX(0,G$5-'Control Panel'!$C$38)-'Control Panel'!$B$44,0),'Control Panel'!$B$45-'Control Panel'!$B$44)*'Control Panel'!$C$45+MAX(MAX(0,G$5-'Control Panel'!$C$38)-'Control Panel'!$B$45,0)*'Control Panel'!$C$46),$A7*'Control Panel'!$B$49))-('Control Panel'!$B$11+G$5*'Control Panel'!$B$10))/($A7+MIN((MIN(MAX(0,G$5-'Control Panel'!$C$38),'Control Panel'!$B$43)*'Control Panel'!$C$43+MIN(MAX(MAX(0,G$5-'Control Panel'!$C$38)-'Control Panel'!$B$43,0),'Control Panel'!$B$44-'Control Panel'!$B$43)*'Control Panel'!$C$44+MIN(MAX(MAX(0,G$5-'Control Panel'!$C$38)-'Control Panel'!$B$44,0),'Control Panel'!$B$45-'Control Panel'!$B$44)*'Control Panel'!$C$45+MAX(MAX(0,G$5-'Control Panel'!$C$38)-'Control Panel'!$B$45,0)*'Control Panel'!$C$46),$A7*'Control Panel'!$B$49)) | H7: =(($A7+MIN((MIN(MAX(0,H$5-'Control Panel'!$C$38),'Control Panel'!$B$43)*'Control Panel'!$C$43+MIN(MAX(MAX(0,H$5-'Control Panel'!$C$38)-'Control Panel'!$B$43,0),'Control Panel'!$B$44-'Control Panel'!$B$43)*'Control Panel'!$C$44+MIN(MAX(MAX(0,H$5-'Control Panel'!$C$38)-'Control Panel'!$B$44,0),'Control Panel'!$B$45-'Control Panel'!$B$44)*'Control Panel'!$C$45+MAX(MAX(0,H$5-'Control Panel'!$C$38)-'Control Panel'!$B$45,0)*'Control Panel'!$C$46),$A7*'Control Panel'!$B$49))-('Control Panel'!$B$11+H$5*'Control Panel'!$B$10))/($A7+MIN((MIN(MAX(0,H$5-'Control Panel'!$C$38),'Control Panel'!$B$43)*'Control Panel'!$C$43+MIN(MAX(MAX(0,H$5-'Control Panel'!$C$38)-'Control Panel'!$B$43,0),'Control Panel'!$B$44-'Control Panel'!$B$43)*'Control Panel'!$C$44+MIN(MAX(MAX(0,H$5-'Control Panel'!$C$38)-'Control Panel'!$B$44,0),'Control Panel'!$B$45-'Control Panel'!$B$44)*'Control Panel'!$C$45+MAX(MAX(0,H$5-'Control Panel'!$C$38)-'Control Panel'!$B$45,0)*'Control Panel'!$C$46),$A7*'Control Panel'!$B$49)) | I7: =(($A7+MIN((MIN(MAX(0,I$5-'Control Panel'!$C$38),'Control Panel'!$B$43)*'Control Panel'!$C$43+MIN(MAX(MAX(0,I$5-'Control Panel'!$C$38)-'Control Panel'!$B$43,0),'Control Panel'!$B$44-'Control Panel'!$B$43)*'Control Panel'!$C$44+MIN(MAX(MAX(0,I$5-'Control Panel'!$C$38)-'Control Panel'!$B$44,0),'Control Panel'!$B$45-'Control Panel'!$B$44)*'Control Panel'!$C$45+MAX(MAX(0,I$5-'Control Panel'!$C$38)-'Control Panel'!$B$45,0)*'Control Panel'!$C$46),$A7*'Control Panel'!$B$49))-('Control Panel'!$B$11+I$5*'Control Panel'!$B$10))/($A7+MIN((MIN(MAX(0,I$5-'Control Panel'!$C$38),'Control Panel'!$B$43)*'Control Panel'!$C$43+MIN(MAX(MAX(0,I$5-'Control Panel'!$C$38)-'Control Panel'!$B$43,0),'Control Panel'!$B$44-'Control Panel'!$B$43)*'Control Panel'!$C$44+MIN(MAX(MAX(0,I$5-'Control Panel'!$C$38)-'Control Panel'!$B$44,0),'Control Panel'!$B$45-'Control Panel'!$B$44)*'Control Panel'!$C$45+MAX(MAX(0,I$5-'Control Panel'!$C$38)-'Control Panel'!$B$45,0)*'Control Panel'!$C$46),$A7*'Control Panel'!$B$49)) | ... K7: =(($A7+MIN((MIN(MAX(0,K$5-'Control Panel'!$C$38),'Control Panel'!$B$43)*'Control Panel'!$C$43+MIN(MAX(MAX(0,K$5-'Control Panel'!$C$38)-'Control Panel'!$B$43,0),'Control Panel'!$B$44-'Control Panel'!$B$43)*'Control Panel'!$C$44+MIN(MAX(MAX(0,K$5-'Control Panel'!$C$38)-'Control Panel'!$B$44,0),'Control Panel'!$B$45-'Control Panel'!$B$44)*'Control Panel'!$C$45+MAX(MAX(0,K$5-'Control Panel'!$C$38)-'Control Panel'!$B$45,0)*'Control Panel'!$C$46),$A7*'Control Panel'!$B$49))-('Control Panel'!$B$11+K$5*'Control Panel'!$B$10))/($A7+MIN((MIN(MAX(0,K$5-'Control Panel'!$C$38),'Control Panel'!$B$43)*'Control Panel'!$C$43+MIN(MAX(MAX(0,K$5-'Control Panel'!$C$38)-'Control Panel'!$B$43,0),'Control Panel'!$B$44-'Control Panel'!$B$43)*'Control Panel'!$C$44+MIN(MAX(MAX(0,K$5-'Control Panel'!$C$38)-'Control Panel'!$B$44,0),'Control Panel'!$B$45-'Control Panel'!$B$44)*'Control Panel'!$C$45+MAX(MAX(0,K$5-'Control Panel'!$C$38)-'Control Panel'!$B$45,0)*'Control Panel'!$C$46),$A7*'Control Panel'!$B$49))
A8: 349 | B8: =(($A8+MIN((MIN(MAX(0,B$5-'Control Panel'!$C$38),'Control Panel'!$B$43)*'Control Panel'!$C$43+MIN(MAX(MAX(0,B$5-'Control Panel'!$C$38)-'Control Panel'!$B$43,0),'Control Panel'!$B$44-'Control Panel'!$B$43)*'Control Panel'!$C$44+MIN(MAX(MAX(0,B$5-'Control Panel'!$C$38)-'Control Panel'!$B$44,0),'Control Panel'!$B$45-'Control Panel'!$B$44)*'Control Panel'!$C$45+MAX(MAX(0,B$5-'Control Panel'!$C$38)-'Control Panel'!$B$45,0)*'Control Panel'!$C$46),$A8*'Control Panel'!$B$49))-('Control Panel'!$B$11+B$5*'Control Panel'!$B$10))/($A8+MIN((MIN(MAX(0,B$5-'Control Panel'!$C$38),'Control Panel'!$B$43)*'Control Panel'!$C$43+MIN(MAX(MAX(0,B$5-'Control Panel'!$C$38)-'Control Panel'!$B$43,0),'Control Panel'!$B$44-'Control Panel'!$B$43)*'Control Panel'!$C$44+MIN(MAX(MAX(0,B$5-'Control Panel'!$C$38)-'Control Panel'!$B$44,0),'Control Panel'!$B$45-'Control Panel'!$B$44)*'Control Panel'!$C$45+MAX(MAX(0,B$5-'Control Panel'!$C$38)-'Control Panel'!$B$45,0)*'Control Panel'!$C$46),$A8*'Control Panel'!$B$49)) | C8: =(($A8+MIN((MIN(MAX(0,C$5-'Control Panel'!$C$38),'Control Panel'!$B$43)*'Control Panel'!$C$43+MIN(MAX(MAX(0,C$5-'Control Panel'!$C$38)-'Control Panel'!$B$43,0),'Control Panel'!$B$44-'Control Panel'!$B$43)*'Control Panel'!$C$44+MIN(MAX(MAX(0,C$5-'Control Panel'!$C$38)-'Control Panel'!$B$44,0),'Control Panel'!$B$45-'Control Panel'!$B$44)*'Control Panel'!$C$45+MAX(MAX(0,C$5-'Control Panel'!$C$38)-'Control Panel'!$B$45,0)*'Control Panel'!$C$46),$A8*'Control Panel'!$B$49))-('Control Panel'!$B$11+C$5*'Control Panel'!$B$10))/($A8+MIN((MIN(MAX(0,C$5-'Control Panel'!$C$38),'Control Panel'!$B$43)*'Control Panel'!$C$43+MIN(MAX(MAX(0,C$5-'Control Panel'!$C$38)-'Control Panel'!$B$43,0),'Control Panel'!$B$44-'Control Panel'!$B$43)*'Control Panel'!$C$44+MIN(MAX(MAX(0,C$5-'Control Panel'!$C$38)-'Control Panel'!$B$44,0),'Control Panel'!$B$45-'Control Panel'!$B$44)*'Control Panel'!$C$45+MAX(MAX(0,C$5-'Control Panel'!$C$38)-'Control Panel'!$B$45,0)*'Control Panel'!$C$46),$A8*'Control Panel'!$B$49)) | D8: =(($A8+MIN((MIN(MAX(0,D$5-'Control Panel'!$C$38),'Control Panel'!$B$43)*'Control Panel'!$C$43+MIN(MAX(MAX(0,D$5-'Control Panel'!$C$38)-'Control Panel'!$B$43,0),'Control Panel'!$B$44-'Control Panel'!$B$43)*'Control Panel'!$C$44+MIN(MAX(MAX(0,D$5-'Control Panel'!$C$38)-'Control Panel'!$B$44,0),'Control Panel'!$B$45-'Control Panel'!$B$44)*'Control Panel'!$C$45+MAX(MAX(0,D$5-'Control Panel'!$C$38)-'Control Panel'!$B$45,0)*'Control Panel'!$C$46),$A8*'Control Panel'!$B$49))-('Control Panel'!$B$11+D$5*'Control Panel'!$B$10))/($A8+MIN((MIN(MAX(0,D$5-'Control Panel'!$C$38),'Control Panel'!$B$43)*'Control Panel'!$C$43+MIN(MAX(MAX(0,D$5-'Control Panel'!$C$38)-'Control Panel'!$B$43,0),'Control Panel'!$B$44-'Control Panel'!$B$43)*'Control Panel'!$C$44+MIN(MAX(MAX(0,D$5-'Control Panel'!$C$38)-'Control Panel'!$B$44,0),'Control Panel'!$B$45-'Control Panel'!$B$44)*'Control Panel'!$C$45+MAX(MAX(0,D$5-'Control Panel'!$C$38)-'Control Panel'!$B$45,0)*'Control Panel'!$C$46),$A8*'Control Panel'!$B$49)) | E8: =(($A8+MIN((MIN(MAX(0,E$5-'Control Panel'!$C$38),'Control Panel'!$B$43)*'Control Panel'!$C$43+MIN(MAX(MAX(0,E$5-'Control Panel'!$C$38)-'Control Panel'!$B$43,0),'Control Panel'!$B$44-'Control Panel'!$B$43)*'Control Panel'!$C$44+MIN(MAX(MAX(0,E$5-'Control Panel'!$C$38)-'Control Panel'!$B$44,0),'Control Panel'!$B$45-'Control Panel'!$B$44)*'Control Panel'!$C$45+MAX(MAX(0,E$5-'Control Panel'!$C$38)-'Control Panel'!$B$45,0)*'Control Panel'!$C$46),$A8*'Control Panel'!$B$49))-('Control Panel'!$B$11+E$5*'Control Panel'!$B$10))/($A8+MIN((MIN(MAX(0,E$5-'Control Panel'!$C$38),'Control Panel'!$B$43)*'Control Panel'!$C$43+MIN(MAX(MAX(0,E$5-'Control Panel'!$C$38)-'Control Panel'!$B$43,0),'Control Panel'!$B$44-'Control Panel'!$B$43)*'Control Panel'!$C$44+MIN(MAX(MAX(0,E$5-'Control Panel'!$C$38)-'Control Panel'!$B$44,0),'Control Panel'!$B$45-'Control Panel'!$B$44)*'Control Panel'!$C$45+MAX(MAX(0,E$5-'Control Panel'!$C$38)-'Control Panel'!$B$45,0)*'Control Panel'!$C$46),$A8*'Control Panel'!$B$49)) | F8: =(($A8+MIN((MIN(MAX(0,F$5-'Control Panel'!$C$38),'Control Panel'!$B$43)*'Control Panel'!$C$43+MIN(MAX(MAX(0,F$5-'Control Panel'!$C$38)-'Control Panel'!$B$43,0),'Control Panel'!$B$44-'Control Panel'!$B$43)*'Control Panel'!$C$44+MIN(MAX(MAX(0,F$5-'Control Panel'!$C$38)-'Control Panel'!$B$44,0),'Control Panel'!$B$45-'Control Panel'!$B$44)*'Control Panel'!$C$45+MAX(MAX(0,F$5-'Control Panel'!$C$38)-'Control Panel'!$B$45,0)*'Control Panel'!$C$46),$A8*'Control Panel'!$B$49))-('Control Panel'!$B$11+F$5*'Control Panel'!$B$10))/($A8+MIN((MIN(MAX(0,F$5-'Control Panel'!$C$38),'Control Panel'!$B$43)*'Control Panel'!$C$43+MIN(MAX(MAX(0,F$5-'Control Panel'!$C$38)-'Control Panel'!$B$43,0),'Control Panel'!$B$44-'Control Panel'!$B$43)*'Control Panel'!$C$44+MIN(MAX(MAX(0,F$5-'Control Panel'!$C$38)-'Control Panel'!$B$44,0),'Control Panel'!$B$45-'Control Panel'!$B$44)*'Control Panel'!$C$45+MAX(MAX(0,F$5-'Control Panel'!$C$38)-'Control Panel'!$B$45,0)*'Control Panel'!$C$46),$A8*'Control Panel'!$B$49)) | G8: =(($A8+MIN((MIN(MAX(0,G$5-'Control Panel'!$C$38),'Control Panel'!$B$43)*'Control Panel'!$C$43+MIN(MAX(MAX(0,G$5-'Control Panel'!$C$38)-'Control Panel'!$B$43,0),'Control Panel'!$B$44-'Control Panel'!$B$43)*'Control Panel'!$C$44+MIN(MAX(MAX(0,G$5-'Control Panel'!$C$38)-'Control Panel'!$B$44,0),'Control Panel'!$B$45-'Control Panel'!$B$44)*'Control Panel'!$C$45+MAX(MAX(0,G$5-'Control Panel'!$C$38)-'Control Panel'!$B$45,0)*'Control Panel'!$C$46),$A8*'Control Panel'!$B$49))-('Control Panel'!$B$11+G$5*'Control Panel'!$B$10))/($A8+MIN((MIN(MAX(0,G$5-'Control Panel'!$C$38),'Control Panel'!$B$43)*'Control Panel'!$C$43+MIN(MAX(MAX(0,G$5-'Control Panel'!$C$38)-'Control Panel'!$B$43,0),'Control Panel'!$B$44-'Control Panel'!$B$43)*'Control Panel'!$C$44+MIN(MAX(MAX(0,G$5-'Control Panel'!$C$38)-'Control Panel'!$B$44,0),'Control Panel'!$B$45-'Control Panel'!$B$44)*'Control Panel'!$C$45+MAX(MAX(0,G$5-'Control Panel'!$C$38)-'Control Panel'!$B$45,0)*'Control Panel'!$C$46),$A8*'Control Panel'!$B$49)) | H8: =(($A8+MIN((MIN(MAX(0,H$5-'Control Panel'!$C$38),'Control Panel'!$B$43)*'Control Panel'!$C$43+MIN(MAX(MAX(0,H$5-'Control Panel'!$C$38)-'Control Panel'!$B$43,0),'Control Panel'!$B$44-'Control Panel'!$B$43)*'Control Panel'!$C$44+MIN(MAX(MAX(0,H$5-'Control Panel'!$C$38)-'Control Panel'!$B$44,0),'Control Panel'!$B$45-'Control Panel'!$B$44)*'Control Panel'!$C$45+MAX(MAX(0,H$5-'Control Panel'!$C$38)-'Control Panel'!$B$45,0)*'Control Panel'!$C$46),$A8*'Control Panel'!$B$49))-('Control Panel'!$B$11+H$5*'Control Panel'!$B$10))/($A8+MIN((MIN(MAX(0,H$5-'Control Panel'!$C$38),'Control Panel'!$B$43)*'Control Panel'!$C$43+MIN(MAX(MAX(0,H$5-'Control Panel'!$C$38)-'Control Panel'!$B$43,0),'Control Panel'!$B$44-'Control Panel'!$B$43)*'Control Panel'!$C$44+MIN(MAX(MAX(0,H$5-'Control Panel'!$C$38)-'Control Panel'!$B$44,0),'Control Panel'!$B$45-'Control Panel'!$B$44)*'Control Panel'!$C$45+MAX(MAX(0,H$5-'Control Panel'!$C$38)-'Control Panel'!$B$45,0)*'Control Panel'!$C$46),$A8*'Control Panel'!$B$49)) | I8: =(($A8+MIN((MIN(MAX(0,I$5-'Control Panel'!$C$38),'Control Panel'!$B$43)*'Control Panel'!$C$43+MIN(MAX(MAX(0,I$5-'Control Panel'!$C$38)-'Control Panel'!$B$43,0),'Control Panel'!$B$44-'Control Panel'!$B$43)*'Control Panel'!$C$44+MIN(MAX(MAX(0,I$5-'Control Panel'!$C$38)-'Control Panel'!$B$44,0),'Control Panel'!$B$45-'Control Panel'!$B$44)*'Control Panel'!$C$45+MAX(MAX(0,I$5-'Control Panel'!$C$38)-'Control Panel'!$B$45,0)*'Control Panel'!$C$46),$A8*'Control Panel'!$B$49))-('Control Panel'!$B$11+I$5*'Control Panel'!$B$10))/($A8+MIN((MIN(MAX(0,I$5-'Control Panel'!$C$38),'Control Panel'!$B$43)*'Control Panel'!$C$43+MIN(MAX(MAX(0,I$5-'Control Panel'!$C$38)-'Control Panel'!$B$43,0),'Control Panel'!$B$44-'Control Panel'!$B$43)*'Control Panel'!$C$44+MIN(MAX(MAX(0,I$5-'Control Panel'!$C$38)-'Control Panel'!$B$44,0),'Control Panel'!$B$45-'Control Panel'!$B$44)*'Control Panel'!$C$45+MAX(MAX(0,I$5-'Control Panel'!$C$38)-'Control Panel'!$B$45,0)*'Control Panel'!$C$46),$A8*'Control Panel'!$B$49)) | ... K8: =(($A8+MIN((MIN(MAX(0,K$5-'Control Panel'!$C$38),'Control Panel'!$B$43)*'Control Panel'!$C$43+MIN(MAX(MAX(0,K$5-'Control Panel'!$C$38)-'Control Panel'!$B$43,0),'Control Panel'!$B$44-'Control Panel'!$B$43)*'Control Panel'!$C$44+MIN(MAX(MAX(0,K$5-'Control Panel'!$C$38)-'Control Panel'!$B$44,0),'Control Panel'!$B$45-'Control Panel'!$B$44)*'Control Panel'!$C$45+MAX(MAX(0,K$5-'Control Panel'!$C$38)-'Control Panel'!$B$45,0)*'Control Panel'!$C$46),$A8*'Control Panel'!$B$49))-('Control Panel'!$B$11+K$5*'Control Panel'!$B$10))/($A8+MIN((MIN(MAX(0,K$5-'Control Panel'!$C$38),'Control Panel'!$B$43)*'Control Panel'!$C$43+MIN(MAX(MAX(0,K$5-'Control Panel'!$C$38)-'Control Panel'!$B$43,0),'Control Panel'!$B$44-'Control Panel'!$B$43)*'Control Panel'!$C$44+MIN(MAX(MAX(0,K$5-'Control Panel'!$C$38)-'Control Panel'!$B$44,0),'Control Panel'!$B$45-'Control Panel'!$B$44)*'Control Panel'!$C$45+MAX(MAX(0,K$5-'Control Panel'!$C$38)-'Control Panel'!$B$45,0)*'Control Panel'!$C$46),$A8*'Control Panel'!$B$49))
A9: 399 | B9: =(($A9+MIN((MIN(MAX(0,B$5-'Control Panel'!$C$38),'Control Panel'!$B$43)*'Control Panel'!$C$43+MIN(MAX(MAX(0,B$5-'Control Panel'!$C$38)-'Control Panel'!$B$43,0),'Control Panel'!$B$44-'Control Panel'!$B$43)*'Control Panel'!$C$44+MIN(MAX(MAX(0,B$5-'Control Panel'!$C$38)-'Control Panel'!$B$44,0),'Control Panel'!$B$45-'Control Panel'!$B$44)*'Control Panel'!$C$45+MAX(MAX(0,B$5-'Control Panel'!$C$38)-'Control Panel'!$B$45,0)*'Control Panel'!$C$46),$A9*'Control Panel'!$B$49))-('Control Panel'!$B$11+B$5*'Control Panel'!$B$10))/($A9+MIN((MIN(MAX(0,B$5-'Control Panel'!$C$38),'Control Panel'!$B$43)*'Control Panel'!$C$43+MIN(MAX(MAX(0,B$5-'Control Panel'!$C$38)-'Control Panel'!$B$43,0),'Control Panel'!$B$44-'Control Panel'!$B$43)*'Control Panel'!$C$44+MIN(MAX(MAX(0,B$5-'Control Panel'!$C$38)-'Control Panel'!$B$44,0),'Control Panel'!$B$45-'Control Panel'!$B$44)*'Control Panel'!$C$45+MAX(MAX(0,B$5-'Control Panel'!$C$38)-'Control Panel'!$B$45,0)*'Control Panel'!$C$46),$A9*'Control Panel'!$B$49)) | C9: =(($A9+MIN((MIN(MAX(0,C$5-'Control Panel'!$C$38),'Control Panel'!$B$43)*'Control Panel'!$C$43+MIN(MAX(MAX(0,C$5-'Control Panel'!$C$38)-'Control Panel'!$B$43,0),'Control Panel'!$B$44-'Control Panel'!$B$43)*'Control Panel'!$C$44+MIN(MAX(MAX(0,C$5-'Control Panel'!$C$38)-'Control Panel'!$B$44,0),'Control Panel'!$B$45-'Control Panel'!$B$44)*'Control Panel'!$C$45+MAX(MAX(0,C$5-'Control Panel'!$C$38)-'Control Panel'!$B$45,0)*'Control Panel'!$C$46),$A9*'Control Panel'!$B$49))-('Control Panel'!$B$11+C$5*'Control Panel'!$B$10))/($A9+MIN((MIN(MAX(0,C$5-'Control Panel'!$C$38),'Control Panel'!$B$43)*'Control Panel'!$C$43+MIN(MAX(MAX(0,C$5-'Control Panel'!$C$38)-'Control Panel'!$B$43,0),'Control Panel'!$B$44-'Control Panel'!$B$43)*'Control Panel'!$C$44+MIN(MAX(MAX(0,C$5-'Control Panel'!$C$38)-'Control Panel'!$B$44,0),'Control Panel'!$B$45-'Control Panel'!$B$44)*'Control Panel'!$C$45+MAX(MAX(0,C$5-'Control Panel'!$C$38)-'Control Panel'!$B$45,0)*'Control Panel'!$C$46),$A9*'Control Panel'!$B$49)) | D9: =(($A9+MIN((MIN(MAX(0,D$5-'Control Panel'!$C$38),'Control Panel'!$B$43)*'Control Panel'!$C$43+MIN(MAX(MAX(0,D$5-'Control Panel'!$C$38)-'Control Panel'!$B$43,0),'Control Panel'!$B$44-'Control Panel'!$B$43)*'Control Panel'!$C$44+MIN(MAX(MAX(0,D$5-'Control Panel'!$C$38)-'Control Panel'!$B$44,0),'Control Panel'!$B$45-'Control Panel'!$B$44)*'Control Panel'!$C$45+MAX(MAX(0,D$5-'Control Panel'!$C$38)-'Control Panel'!$B$45,0)*'Control Panel'!$C$46),$A9*'Control Panel'!$B$49))-('Control Panel'!$B$11+D$5*'Control Panel'!$B$10))/($A9+MIN((MIN(MAX(0,D$5-'Control Panel'!$C$38),'Control Panel'!$B$43)*'Control Panel'!$C$43+MIN(MAX(MAX(0,D$5-'Control Panel'!$C$38)-'Control Panel'!$B$43,0),'Control Panel'!$B$44-'Control Panel'!$B$43)*'Control Panel'!$C$44+MIN(MAX(MAX(0,D$5-'Control Panel'!$C$38)-'Control Panel'!$B$44,0),'Control Panel'!$B$45-'Control Panel'!$B$44)*'Control Panel'!$C$45+MAX(MAX(0,D$5-'Control Panel'!$C$38)-'Control Panel'!$B$45,0)*'Control Panel'!$C$46),$A9*'Control Panel'!$B$49)) | E9: =(($A9+MIN((MIN(MAX(0,E$5-'Control Panel'!$C$38),'Control Panel'!$B$43)*'Control Panel'!$C$43+MIN(MAX(MAX(0,E$5-'Control Panel'!$C$38)-'Control Panel'!$B$43,0),'Control Panel'!$B$44-'Control Panel'!$B$43)*'Control Panel'!$C$44+MIN(MAX(MAX(0,E$5-'Control Panel'!$C$38)-'Control Panel'!$B$44,0),'Control Panel'!$B$45-'Control Panel'!$B$44)*'Control Panel'!$C$45+MAX(MAX(0,E$5-'Control Panel'!$C$38)-'Control Panel'!$B$45,0)*'Control Panel'!$C$46),$A9*'Control Panel'!$B$49))-('Control Panel'!$B$11+E$5*'Control Panel'!$B$10))/($A9+MIN((MIN(MAX(0,E$5-'Control Panel'!$C$38),'Control Panel'!$B$43)*'Control Panel'!$C$43+MIN(MAX(MAX(0,E$5-'Control Panel'!$C$38)-'Control Panel'!$B$43,0),'Control Panel'!$B$44-'Control Panel'!$B$43)*'Control Panel'!$C$44+MIN(MAX(MAX(0,E$5-'Control Panel'!$C$38)-'Control Panel'!$B$44,0),'Control Panel'!$B$45-'Control Panel'!$B$44)*'Control Panel'!$C$45+MAX(MAX(0,E$5-'Control Panel'!$C$38)-'Control Panel'!$B$45,0)*'Control Panel'!$C$46),$A9*'Control Panel'!$B$49)) | F9: =(($A9+MIN((MIN(MAX(0,F$5-'Control Panel'!$C$38),'Control Panel'!$B$43)*'Control Panel'!$C$43+MIN(MAX(MAX(0,F$5-'Control Panel'!$C$38)-'Control Panel'!$B$43,0),'Control Panel'!$B$44-'Control Panel'!$B$43)*'Control Panel'!$C$44+MIN(MAX(MAX(0,F$5-'Control Panel'!$C$38)-'Control Panel'!$B$44,0),'Control Panel'!$B$45-'Control Panel'!$B$44)*'Control Panel'!$C$45+MAX(MAX(0,F$5-'Control Panel'!$C$38)-'Control Panel'!$B$45,0)*'Control Panel'!$C$46),$A9*'Control Panel'!$B$49))-('Control Panel'!$B$11+F$5*'Control Panel'!$B$10))/($A9+MIN((MIN(MAX(0,F$5-'Control Panel'!$C$38),'Control Panel'!$B$43)*'Control Panel'!$C$43+MIN(MAX(MAX(0,F$5-'Control Panel'!$C$38)-'Control Panel'!$B$43,0),'Control Panel'!$B$44-'Control Panel'!$B$43)*'Control Panel'!$C$44+MIN(MAX(MAX(0,F$5-'Control Panel'!$C$38)-'Control Panel'!$B$44,0),'Control Panel'!$B$45-'Control Panel'!$B$44)*'Control Panel'!$C$45+MAX(MAX(0,F$5-'Control Panel'!$C$38)-'Control Panel'!$B$45,0)*'Control Panel'!$C$46),$A9*'Control Panel'!$B$49)) | G9: =(($A9+MIN((MIN(MAX(0,G$5-'Control Panel'!$C$38),'Control Panel'!$B$43)*'Control Panel'!$C$43+MIN(MAX(MAX(0,G$5-'Control Panel'!$C$38)-'Control Panel'!$B$43,0),'Control Panel'!$B$44-'Control Panel'!$B$43)*'Control Panel'!$C$44+MIN(MAX(MAX(0,G$5-'Control Panel'!$C$38)-'Control Panel'!$B$44,0),'Control Panel'!$B$45-'Control Panel'!$B$44)*'Control Panel'!$C$45+MAX(MAX(0,G$5-'Control Panel'!$C$38)-'Control Panel'!$B$45,0)*'Control Panel'!$C$46),$A9*'Control Panel'!$B$49))-('Control Panel'!$B$11+G$5*'Control Panel'!$B$10))/($A9+MIN((MIN(MAX(0,G$5-'Control Panel'!$C$38),'Control Panel'!$B$43)*'Control Panel'!$C$43+MIN(MAX(MAX(0,G$5-'Control Panel'!$C$38)-'Control Panel'!$B$43,0),'Control Panel'!$B$44-'Control Panel'!$B$43)*'Control Panel'!$C$44+MIN(MAX(MAX(0,G$5-'Control Panel'!$C$38)-'Control Panel'!$B$44,0),'Control Panel'!$B$45-'Control Panel'!$B$44)*'Control Panel'!$C$45+MAX(MAX(0,G$5-'Control Panel'!$C$38)-'Control Panel'!$B$45,0)*'Control Panel'!$C$46),$A9*'Control Panel'!$B$49)) | H9: =(($A9+MIN((MIN(MAX(0,H$5-'Control Panel'!$C$38),'Control Panel'!$B$43)*'Control Panel'!$C$43+MIN(MAX(MAX(0,H$5-'Control Panel'!$C$38)-'Control Panel'!$B$43,0),'Control Panel'!$B$44-'Control Panel'!$B$43)*'Control Panel'!$C$44+MIN(MAX(MAX(0,H$5-'Control Panel'!$C$38)-'Control Panel'!$B$44,0),'Control Panel'!$B$45-'Control Panel'!$B$44)*'Control Panel'!$C$45+MAX(MAX(0,H$5-'Control Panel'!$C$38)-'Control Panel'!$B$45,0)*'Control Panel'!$C$46),$A9*'Control Panel'!$B$49))-('Control Panel'!$B$11+H$5*'Control Panel'!$B$10))/($A9+MIN((MIN(MAX(0,H$5-'Control Panel'!$C$38),'Control Panel'!$B$43)*'Control Panel'!$C$43+MIN(MAX(MAX(0,H$5-'Control Panel'!$C$38)-'Control Panel'!$B$43,0),'Control Panel'!$B$44-'Control Panel'!$B$43)*'Control Panel'!$C$44+MIN(MAX(MAX(0,H$5-'Control Panel'!$C$38)-'Control Panel'!$B$44,0),'Control Panel'!$B$45-'Control Panel'!$B$44)*'Control Panel'!$C$45+MAX(MAX(0,H$5-'Control Panel'!$C$38)-'Control Panel'!$B$45,0)*'Control Panel'!$C$46),$A9*'Control Panel'!$B$49)) | I9: =(($A9+MIN((MIN(MAX(0,I$5-'Control Panel'!$C$38),'Control Panel'!$B$43)*'Control Panel'!$C$43+MIN(MAX(MAX(0,I$5-'Control Panel'!$C$38)-'Control Panel'!$B$43,0),'Control Panel'!$B$44-'Control Panel'!$B$43)*'Control Panel'!$C$44+MIN(MAX(MAX(0,I$5-'Control Panel'!$C$38)-'Control Panel'!$B$44,0),'Control Panel'!$B$45-'Control Panel'!$B$44)*'Control Panel'!$C$45+MAX(MAX(0,I$5-'Control Panel'!$C$38)-'Control Panel'!$B$45,0)*'Control Panel'!$C$46),$A9*'Control Panel'!$B$49))-('Control Panel'!$B$11+I$5*'Control Panel'!$B$10))/($A9+MIN((MIN(MAX(0,I$5-'Control Panel'!$C$38),'Control Panel'!$B$43)*'Control Panel'!$C$43+MIN(MAX(MAX(0,I$5-'Control Panel'!$C$38)-'Control Panel'!$B$43,0),'Control Panel'!$B$44-'Control Panel'!$B$43)*'Control Panel'!$C$44+MIN(MAX(MAX(0,I$5-'Control Panel'!$C$38)-'Control Panel'!$B$44,0),'Control Panel'!$B$45-'Control Panel'!$B$44)*'Control Panel'!$C$45+MAX(MAX(0,I$5-'Control Panel'!$C$38)-'Control Panel'!$B$45,0)*'Control Panel'!$C$46),$A9*'Control Panel'!$B$49)) | ... K9: =(($A9+MIN((MIN(MAX(0,K$5-'Control Panel'!$C$38),'Control Panel'!$B$43)*'Control Panel'!$C$43+MIN(MAX(MAX(0,K$5-'Control Panel'!$C$38)-'Control Panel'!$B$43,0),'Control Panel'!$B$44-'Control Panel'!$B$43)*'Control Panel'!$C$44+MIN(MAX(MAX(0,K$5-'Control Panel'!$C$38)-'Control Panel'!$B$44,0),'Control Panel'!$B$45-'Control Panel'!$B$44)*'Control Panel'!$C$45+MAX(MAX(0,K$5-'Control Panel'!$C$38)-'Control Panel'!$B$45,0)*'Control Panel'!$C$46),$A9*'Control Panel'!$B$49))-('Control Panel'!$B$11+K$5*'Control Panel'!$B$10))/($A9+MIN((MIN(MAX(0,K$5-'Control Panel'!$C$38),'Control Panel'!$B$43)*'Control Panel'!$C$43+MIN(MAX(MAX(0,K$5-'Control Panel'!$C$38)-'Control Panel'!$B$43,0),'Control Panel'!$B$44-'Control Panel'!$B$43)*'Control Panel'!$C$44+MIN(MAX(MAX(0,K$5-'Control Panel'!$C$38)-'Control Panel'!$B$44,0),'Control Panel'!$B$45-'Control Panel'!$B$44)*'Control Panel'!$C$45+MAX(MAX(0,K$5-'Control Panel'!$C$38)-'Control Panel'!$B$45,0)*'Control Panel'!$C$46),$A9*'Control Panel'!$B$49))
A10: 449 | B10: =(($A10+MIN((MIN(MAX(0,B$5-'Control Panel'!$C$38),'Control Panel'!$B$43)*'Control Panel'!$C$43+MIN(MAX(MAX(0,B$5-'Control Panel'!$C$38)-'Control Panel'!$B$43,0),'Control Panel'!$B$44-'Control Panel'!$B$43)*'Control Panel'!$C$44+MIN(MAX(MAX(0,B$5-'Control Panel'!$C$38)-'Control Panel'!$B$44,0),'Control Panel'!$B$45-'Control Panel'!$B$44)*'Control Panel'!$C$45+MAX(MAX(0,B$5-'Control Panel'!$C$38)-'Control Panel'!$B$45,0)*'Control Panel'!$C$46),$A10*'Control Panel'!$B$49))-('Control Panel'!$B$11+B$5*'Control Panel'!$B$10))/($A10+MIN((MIN(MAX(0,B$5-'Control Panel'!$C$38),'Control Panel'!$B$43)*'Control Panel'!$C$43+MIN(MAX(MAX(0,B$5-'Control Panel'!$C$38)-'Control Panel'!$B$43,0),'Control Panel'!$B$44-'Control Panel'!$B$43)*'Control Panel'!$C$44+MIN(MAX(MAX(0,B$5-'Control Panel'!$C$38)-'Control Panel'!$B$44,0),'Control Panel'!$B$45-'Control Panel'!$B$44)*'Control Panel'!$C$45+MAX(MAX(0,B$5-'Control Panel'!$C$38)-'Control Panel'!$B$45,0)*'Control Panel'!$C$46),$A10*'Control Panel'!$B$49)) | C10: =(($A10+MIN((MIN(MAX(0,C$5-'Control Panel'!$C$38),'Control Panel'!$B$43)*'Control Panel'!$C$43+MIN(MAX(MAX(0,C$5-'Control Panel'!$C$38)-'Control Panel'!$B$43,0),'Control Panel'!$B$44-'Control Panel'!$B$43)*'Control Panel'!$C$44+MIN(MAX(MAX(0,C$5-'Control Panel'!$C$38)-'Control Panel'!$B$44,0),'Control Panel'!$B$45-'Control Panel'!$B$44)*'Control Panel'!$C$45+MAX(MAX(0,C$5-'Control Panel'!$C$38)-'Control Panel'!$B$45,0)*'Control Panel'!$C$46),$A10*'Control Panel'!$B$49))-('Control Panel'!$B$11+C$5*'Control Panel'!$B$10))/($A10+MIN((MIN(MAX(0,C$5-'Control Panel'!$C$38),'Control Panel'!$B$43)*'Control Panel'!$C$43+MIN(MAX(MAX(0,C$5-'Control Panel'!$C$38)-'Control Panel'!$B$43,0),'Control Panel'!$B$44-'Control Panel'!$B$43)*'Control Panel'!$C$44+MIN(MAX(MAX(0,C$5-'Control Panel'!$C$38)-'Control Panel'!$B$44,0),'Control Panel'!$B$45-'Control Panel'!$B$44)*'Control Panel'!$C$45+MAX(MAX(0,C$5-'Control Panel'!$C$38)-'Control Panel'!$B$45,0)*'Control Panel'!$C$46),$A10*'Control Panel'!$B$49)) | D10: =(($A10+MIN((MIN(MAX(0,D$5-'Control Panel'!$C$38),'Control Panel'!$B$43)*'Control Panel'!$C$43+MIN(MAX(MAX(0,D$5-'Control Panel'!$C$38)-'Control Panel'!$B$43,0),'Control Panel'!$B$44-'Control Panel'!$B$43)*'Control Panel'!$C$44+MIN(MAX(MAX(0,D$5-'Control Panel'!$C$38)-'Control Panel'!$B$44,0),'Control Panel'!$B$45-'Control Panel'!$B$44)*'Control Panel'!$C$45+MAX(MAX(0,D$5-'Control Panel'!$C$38)-'Control Panel'!$B$45,0)*'Control Panel'!$C$46),$A10*'Control Panel'!$B$49))-('Control Panel'!$B$11+D$5*'Control Panel'!$B$10))/($A10+MIN((MIN(MAX(0,D$5-'Control Panel'!$C$38),'Control Panel'!$B$43)*'Control Panel'!$C$43+MIN(MAX(MAX(0,D$5-'Control Panel'!$C$38)-'Control Panel'!$B$43,0),'Control Panel'!$B$44-'Control Panel'!$B$43)*'Control Panel'!$C$44+MIN(MAX(MAX(0,D$5-'Control Panel'!$C$38)-'Control Panel'!$B$44,0),'Control Panel'!$B$45-'Control Panel'!$B$44)*'Control Panel'!$C$45+MAX(MAX(0,D$5-'Control Panel'!$C$38)-'Control Panel'!$B$45,0)*'Control Panel'!$C$46),$A10*'Control Panel'!$B$49)) | E10: =(($A10+MIN((MIN(MAX(0,E$5-'Control Panel'!$C$38),'Control Panel'!$B$43)*'Control Panel'!$C$43+MIN(MAX(MAX(0,E$5-'Control Panel'!$C$38)-'Control Panel'!$B$43,0),'Control Panel'!$B$44-'Control Panel'!$B$43)*'Control Panel'!$C$44+MIN(MAX(MAX(0,E$5-'Control Panel'!$C$38)-'Control Panel'!$B$44,0),'Control Panel'!$B$45-'Control Panel'!$B$44)*'Control Panel'!$C$45+MAX(MAX(0,E$5-'Control Panel'!$C$38)-'Control Panel'!$B$45,0)*'Control Panel'!$C$46),$A10*'Control Panel'!$B$49))-('Control Panel'!$B$11+E$5*'Control Panel'!$B$10))/($A10+MIN((MIN(MAX(0,E$5-'Control Panel'!$C$38),'Control Panel'!$B$43)*'Control Panel'!$C$43+MIN(MAX(MAX(0,E$5-'Control Panel'!$C$38)-'Control Panel'!$B$43,0),'Control Panel'!$B$44-'Control Panel'!$B$43)*'Control Panel'!$C$44+MIN(MAX(MAX(0,E$5-'Control Panel'!$C$38)-'Control Panel'!$B$44,0),'Control Panel'!$B$45-'Control Panel'!$B$44)*'Control Panel'!$C$45+MAX(MAX(0,E$5-'Control Panel'!$C$38)-'Control Panel'!$B$45,0)*'Control Panel'!$C$46),$A10*'Control Panel'!$B$49)) | F10: =(($A10+MIN((MIN(MAX(0,F$5-'Control Panel'!$C$38),'Control Panel'!$B$43)*'Control Panel'!$C$43+MIN(MAX(MAX(0,F$5-'Control Panel'!$C$38)-'Control Panel'!$B$43,0),'Control Panel'!$B$44-'Control Panel'!$B$43)*'Control Panel'!$C$44+MIN(MAX(MAX(0,F$5-'Control Panel'!$C$38)-'Control Panel'!$B$44,0),'Control Panel'!$B$45-'Control Panel'!$B$44)*'Control Panel'!$C$45+MAX(MAX(0,F$5-'Control Panel'!$C$38)-'Control Panel'!$B$45,0)*'Control Panel'!$C$46),$A10*'Control Panel'!$B$49))-('Control Panel'!$B$11+F$5*'Control Panel'!$B$10))/($A10+MIN((MIN(MAX(0,F$5-'Control Panel'!$C$38),'Control Panel'!$B$43)*'Control Panel'!$C$43+MIN(MAX(MAX(0,F$5-'Control Panel'!$C$38)-'Control Panel'!$B$43,0),'Control Panel'!$B$44-'Control Panel'!$B$43)*'Control Panel'!$C$44+MIN(MAX(MAX(0,F$5-'Control Panel'!$C$38)-'Control Panel'!$B$44,0),'Control Panel'!$B$45-'Control Panel'!$B$44)*'Control Panel'!$C$45+MAX(MAX(0,F$5-'Control Panel'!$C$38)-'Control Panel'!$B$45,0)*'Control Panel'!$C$46),$A10*'Control Panel'!$B$49)) | G10: =(($A10+MIN((MIN(MAX(0,G$5-'Control Panel'!$C$38),'Control Panel'!$B$43)*'Control Panel'!$C$43+MIN(MAX(MAX(0,G$5-'Control Panel'!$C$38)-'Control Panel'!$B$43,0),'Control Panel'!$B$44-'Control Panel'!$B$43)*'Control Panel'!$C$44+MIN(MAX(MAX(0,G$5-'Control Panel'!$C$38)-'Control Panel'!$B$44,0),'Control Panel'!$B$45-'Control Panel'!$B$44)*'Control Panel'!$C$45+MAX(MAX(0,G$5-'Control Panel'!$C$38)-'Control Panel'!$B$45,0)*'Control Panel'!$C$46),$A10*'Control Panel'!$B$49))-('Control Panel'!$B$11+G$5*'Control Panel'!$B$10))/($A10+MIN((MIN(MAX(0,G$5-'Control Panel'!$C$38),'Control Panel'!$B$43)*'Control Panel'!$C$43+MIN(MAX(MAX(0,G$5-'Control Panel'!$C$38)-'Control Panel'!$B$43,0),'Control Panel'!$B$44-'Control Panel'!$B$43)*'Control Panel'!$C$44+MIN(MAX(MAX(0,G$5-'Control Panel'!$C$38)-'Control Panel'!$B$44,0),'Control Panel'!$B$45-'Control Panel'!$B$44)*'Control Panel'!$C$45+MAX(MAX(0,G$5-'Control Panel'!$C$38)-'Control Panel'!$B$45,0)*'Control Panel'!$C$46),$A10*'Control Panel'!$B$49)) | H10: =(($A10+MIN((MIN(MAX(0,H$5-'Control Panel'!$C$38),'Control Panel'!$B$43)*'Control Panel'!$C$43+MIN(MAX(MAX(0,H$5-'Control Panel'!$C$38)-'Control Panel'!$B$43,0),'Control Panel'!$B$44-'Control Panel'!$B$43)*'Control Panel'!$C$44+MIN(MAX(MAX(0,H$5-'Control Panel'!$C$38)-'Control Panel'!$B$44,0),'Control Panel'!$B$45-'Control Panel'!$B$44)*'Control Panel'!$C$45+MAX(MAX(0,H$5-'Control Panel'!$C$38)-'Control Panel'!$B$45,0)*'Control Panel'!$C$46),$A10*'Control Panel'!$B$49))-('Control Panel'!$B$11+H$5*'Control Panel'!$B$10))/($A10+MIN((MIN(MAX(0,H$5-'Control Panel'!$C$38),'Control Panel'!$B$43)*'Control Panel'!$C$43+MIN(MAX(MAX(0,H$5-'Control Panel'!$C$38)-'Control Panel'!$B$43,0),'Control Panel'!$B$44-'Control Panel'!$B$43)*'Control Panel'!$C$44+MIN(MAX(MAX(0,H$5-'Control Panel'!$C$38)-'Control Panel'!$B$44,0),'Control Panel'!$B$45-'Control Panel'!$B$44)*'Control Panel'!$C$45+MAX(MAX(0,H$5-'Control Panel'!$C$38)-'Control Panel'!$B$45,0)*'Control Panel'!$C$46),$A10*'Control Panel'!$B$49)) | I10: =(($A10+MIN((MIN(MAX(0,I$5-'Control Panel'!$C$38),'Control Panel'!$B$43)*'Control Panel'!$C$43+MIN(MAX(MAX(0,I$5-'Control Panel'!$C$38)-'Control Panel'!$B$43,0),'Control Panel'!$B$44-'Control Panel'!$B$43)*'Control Panel'!$C$44+MIN(MAX(MAX(0,I$5-'Control Panel'!$C$38)-'Control Panel'!$B$44,0),'Control Panel'!$B$45-'Control Panel'!$B$44)*'Control Panel'!$C$45+MAX(MAX(0,I$5-'Control Panel'!$C$38)-'Control Panel'!$B$45,0)*'Control Panel'!$C$46),$A10*'Control Panel'!$B$49))-('Control Panel'!$B$11+I$5*'Control Panel'!$B$10))/($A10+MIN((MIN(MAX(0,I$5-'Control Panel'!$C$38),'Control Panel'!$B$43)*'Control Panel'!$C$43+MIN(MAX(MAX(0,I$5-'Control Panel'!$C$38)-'Control Panel'!$B$43,0),'Control Panel'!$B$44-'Control Panel'!$B$43)*'Control Panel'!$C$44+MIN(MAX(MAX(0,I$5-'Control Panel'!$C$38)-'Control Panel'!$B$44,0),'Control Panel'!$B$45-'Control Panel'!$B$44)*'Control Panel'!$C$45+MAX(MAX(0,I$5-'Control Panel'!$C$38)-'Control Panel'!$B$45,0)*'Control Panel'!$C$46),$A10*'Control Panel'!$B$49)) | ... K10: =(($A10+MIN((MIN(MAX(0,K$5-'Control Panel'!$C$38),'Control Panel'!$B$43)*'Control Panel'!$C$43+MIN(MAX(MAX(0,K$5-'Control Panel'!$C$38)-'Control Panel'!$B$43,0),'Control Panel'!$B$44-'Control Panel'!$B$43)*'Control Panel'!$C$44+MIN(MAX(MAX(0,K$5-'Control Panel'!$C$38)-'Control Panel'!$B$44,0),'Control Panel'!$B$45-'Control Panel'!$B$44)*'Control Panel'!$C$45+MAX(MAX(0,K$5-'Control Panel'!$C$38)-'Control Panel'!$B$45,0)*'Control Panel'!$C$46),$A10*'Control Panel'!$B$49))-('Control Panel'!$B$11+K$5*'Control Panel'!$B$10))/($A10+MIN((MIN(MAX(0,K$5-'Control Panel'!$C$38),'Control Panel'!$B$43)*'Control Panel'!$C$43+MIN(MAX(MAX(0,K$5-'Control Panel'!$C$38)-'Control Panel'!$B$43,0),'Control Panel'!$B$44-'Control Panel'!$B$43)*'Control Panel'!$C$44+MIN(MAX(MAX(0,K$5-'Control Panel'!$C$38)-'Control Panel'!$B$44,0),'Control Panel'!$B$45-'Control Panel'!$B$44)*'Control Panel'!$C$45+MAX(MAX(0,K$5-'Control Panel'!$C$38)-'Control Panel'!$B$45,0)*'Control Panel'!$C$46),$A10*'Control Panel'!$B$49))
A11: 499 | B11: =(($A11+MIN((MIN(MAX(0,B$5-'Control Panel'!$C$38),'Control Panel'!$B$43)*'Control Panel'!$C$43+MIN(MAX(MAX(0,B$5-'Control Panel'!$C$38)-'Control Panel'!$B$43,0),'Control Panel'!$B$44-'Control Panel'!$B$43)*'Control Panel'!$C$44+MIN(MAX(MAX(0,B$5-'Control Panel'!$C$38)-'Control Panel'!$B$44,0),'Control Panel'!$B$45-'Control Panel'!$B$44)*'Control Panel'!$C$45+MAX(MAX(0,B$5-'Control Panel'!$C$38)-'Control Panel'!$B$45,0)*'Control Panel'!$C$46),$A11*'Control Panel'!$B$49))-('Control Panel'!$B$11+B$5*'Control Panel'!$B$10))/($A11+MIN((MIN(MAX(0,B$5-'Control Panel'!$C$38),'Control Panel'!$B$43)*'Control Panel'!$C$43+MIN(MAX(MAX(0,B$5-'Control Panel'!$C$38)-'Control Panel'!$B$43,0),'Control Panel'!$B$44-'Control Panel'!$B$43)*'Control Panel'!$C$44+MIN(MAX(MAX(0,B$5-'Control Panel'!$C$38)-'Control Panel'!$B$44,0),'Control Panel'!$B$45-'Control Panel'!$B$44)*'Control Panel'!$C$45+MAX(MAX(0,B$5-'Control Panel'!$C$38)-'Control Panel'!$B$45,0)*'Control Panel'!$C$46),$A11*'Control Panel'!$B$49)) | C11: =(($A11+MIN((MIN(MAX(0,C$5-'Control Panel'!$C$38),'Control Panel'!$B$43)*'Control Panel'!$C$43+MIN(MAX(MAX(0,C$5-'Control Panel'!$C$38)-'Control Panel'!$B$43,0),'Control Panel'!$B$44-'Control Panel'!$B$43)*'Control Panel'!$C$44+MIN(MAX(MAX(0,C$5-'Control Panel'!$C$38)-'Control Panel'!$B$44,0),'Control Panel'!$B$45-'Control Panel'!$B$44)*'Control Panel'!$C$45+MAX(MAX(0,C$5-'Control Panel'!$C$38)-'Control Panel'!$B$45,0)*'Control Panel'!$C$46),$A11*'Control Panel'!$B$49))-('Control Panel'!$B$11+C$5*'Control Panel'!$B$10))/($A11+MIN((MIN(MAX(0,C$5-'Control Panel'!$C$38),'Control Panel'!$B$43)*'Control Panel'!$C$43+MIN(MAX(MAX(0,C$5-'Control Panel'!$C$38)-'Control Panel'!$B$43,0),'Control Panel'!$B$44-'Control Panel'!$B$43)*'Control Panel'!$C$44+MIN(MAX(MAX(0,C$5-'Control Panel'!$C$38)-'Control Panel'!$B$44,0),'Control Panel'!$B$45-'Control Panel'!$B$44)*'Control Panel'!$C$45+MAX(MAX(0,C$5-'Control Panel'!$C$38)-'Control Panel'!$B$45,0)*'Control Panel'!$C$46),$A11*'Control Panel'!$B$49)) | D11: =(($A11+MIN((MIN(MAX(0,D$5-'Control Panel'!$C$38),'Control Panel'!$B$43)*'Control Panel'!$C$43+MIN(MAX(MAX(0,D$5-'Control Panel'!$C$38)-'Control Panel'!$B$43,0),'Control Panel'!$B$44-'Control Panel'!$B$43)*'Control Panel'!$C$44+MIN(MAX(MAX(0,D$5-'Control Panel'!$C$38)-'Control Panel'!$B$44,0),'Control Panel'!$B$45-'Control Panel'!$B$44)*'Control Panel'!$C$45+MAX(MAX(0,D$5-'Control Panel'!$C$38)-'Control Panel'!$B$45,0)*'Control Panel'!$C$46),$A11*'Control Panel'!$B$49))-('Control Panel'!$B$11+D$5*'Control Panel'!$B$10))/($A11+MIN((MIN(MAX(0,D$5-'Control Panel'!$C$38),'Control Panel'!$B$43)*'Control Panel'!$C$43+MIN(MAX(MAX(0,D$5-'Control Panel'!$C$38)-'Control Panel'!$B$43,0),'Control Panel'!$B$44-'Control Panel'!$B$43)*'Control Panel'!$C$44+MIN(MAX(MAX(0,D$5-'Control Panel'!$C$38)-'Control Panel'!$B$44,0),'Control Panel'!$B$45-'Control Panel'!$B$44)*'Control Panel'!$C$45+MAX(MAX(0,D$5-'Control Panel'!$C$38)-'Control Panel'!$B$45,0)*'Control Panel'!$C$46),$A11*'Control Panel'!$B$49)) | E11: =(($A11+MIN((MIN(MAX(0,E$5-'Control Panel'!$C$38),'Control Panel'!$B$43)*'Control Panel'!$C$43+MIN(MAX(MAX(0,E$5-'Control Panel'!$C$38)-'Control Panel'!$B$43,0),'Control Panel'!$B$44-'Control Panel'!$B$43)*'Control Panel'!$C$44+MIN(MAX(MAX(0,E$5-'Control Panel'!$C$38)-'Control Panel'!$B$44,0),'Control Panel'!$B$45-'Control Panel'!$B$44)*'Control Panel'!$C$45+MAX(MAX(0,E$5-'Control Panel'!$C$38)-'Control Panel'!$B$45,0)*'Control Panel'!$C$46),$A11*'Control Panel'!$B$49))-('Control Panel'!$B$11+E$5*'Control Panel'!$B$10))/($A11+MIN((MIN(MAX(0,E$5-'Control Panel'!$C$38),'Control Panel'!$B$43)*'Control Panel'!$C$43+MIN(MAX(MAX(0,E$5-'Control Panel'!$C$38)-'Control Panel'!$B$43,0),'Control Panel'!$B$44-'Control Panel'!$B$43)*'Control Panel'!$C$44+MIN(MAX(MAX(0,E$5-'Control Panel'!$C$38)-'Control Panel'!$B$44,0),'Control Panel'!$B$45-'Control Panel'!$B$44)*'Control Panel'!$C$45+MAX(MAX(0,E$5-'Control Panel'!$C$38)-'Control Panel'!$B$45,0)*'Control Panel'!$C$46),$A11*'Control Panel'!$B$49)) | F11: =(($A11+MIN((MIN(MAX(0,F$5-'Control Panel'!$C$38),'Control Panel'!$B$43)*'Control Panel'!$C$43+MIN(MAX(MAX(0,F$5-'Control Panel'!$C$38)-'Control Panel'!$B$43,0),'Control Panel'!$B$44-'Control Panel'!$B$43)*'Control Panel'!$C$44+MIN(MAX(MAX(0,F$5-'Control Panel'!$C$38)-'Control Panel'!$B$44,0),'Control Panel'!$B$45-'Control Panel'!$B$44)*'Control Panel'!$C$45+MAX(MAX(0,F$5-'Control Panel'!$C$38)-'Control Panel'!$B$45,0)*'Control Panel'!$C$46),$A11*'Control Panel'!$B$49))-('Control Panel'!$B$11+F$5*'Control Panel'!$B$10))/($A11+MIN((MIN(MAX(0,F$5-'Control Panel'!$C$38),'Control Panel'!$B$43)*'Control Panel'!$C$43+MIN(MAX(MAX(0,F$5-'Control Panel'!$C$38)-'Control Panel'!$B$43,0),'Control Panel'!$B$44-'Control Panel'!$B$43)*'Control Panel'!$C$44+MIN(MAX(MAX(0,F$5-'Control Panel'!$C$38)-'Control Panel'!$B$44,0),'Control Panel'!$B$45-'Control Panel'!$B$44)*'Control Panel'!$C$45+MAX(MAX(0,F$5-'Control Panel'!$C$38)-'Control Panel'!$B$45,0)*'Control Panel'!$C$46),$A11*'Control Panel'!$B$49)) | G11: =(($A11+MIN((MIN(MAX(0,G$5-'Control Panel'!$C$38),'Control Panel'!$B$43)*'Control Panel'!$C$43+MIN(MAX(MAX(0,G$5-'Control Panel'!$C$38)-'Control Panel'!$B$43,0),'Control Panel'!$B$44-'Control Panel'!$B$43)*'Control Panel'!$C$44+MIN(MAX(MAX(0,G$5-'Control Panel'!$C$38)-'Control Panel'!$B$44,0),'Control Panel'!$B$45-'Control Panel'!$B$44)*'Control Panel'!$C$45+MAX(MAX(0,G$5-'Control Panel'!$C$38)-'Control Panel'!$B$45,0)*'Control Panel'!$C$46),$A11*'Control Panel'!$B$49))-('Control Panel'!$B$11+G$5*'Control Panel'!$B$10))/($A11+MIN((MIN(MAX(0,G$5-'Control Panel'!$C$38),'Control Panel'!$B$43)*'Control Panel'!$C$43+MIN(MAX(MAX(0,G$5-'Control Panel'!$C$38)-'Control Panel'!$B$43,0),'Control Panel'!$B$44-'Control Panel'!$B$43)*'Control Panel'!$C$44+MIN(MAX(MAX(0,G$5-'Control Panel'!$C$38)-'Control Panel'!$B$44,0),'Control Panel'!$B$45-'Control Panel'!$B$44)*'Control Panel'!$C$45+MAX(MAX(0,G$5-'Control Panel'!$C$38)-'Control Panel'!$B$45,0)*'Control Panel'!$C$46),$A11*'Control Panel'!$B$49)) | H11: =(($A11+MIN((MIN(MAX(0,H$5-'Control Panel'!$C$38),'Control Panel'!$B$43)*'Control Panel'!$C$43+MIN(MAX(MAX(0,H$5-'Control Panel'!$C$38)-'Control Panel'!$B$43,0),'Control Panel'!$B$44-'Control Panel'!$B$43)*'Control Panel'!$C$44+MIN(MAX(MAX(0,H$5-'Control Panel'!$C$38)-'Control Panel'!$B$44,0),'Control Panel'!$B$45-'Control Panel'!$B$44)*'Control Panel'!$C$45+MAX(MAX(0,H$5-'Control Panel'!$C$38)-'Control Panel'!$B$45,0)*'Control Panel'!$C$46),$A11*'Control Panel'!$B$49))-('Control Panel'!$B$11+H$5*'Control Panel'!$B$10))/($A11+MIN((MIN(MAX(0,H$5-'Control Panel'!$C$38),'Control Panel'!$B$43)*'Control Panel'!$C$43+MIN(MAX(MAX(0,H$5-'Control Panel'!$C$38)-'Control Panel'!$B$43,0),'Control Panel'!$B$44-'Control Panel'!$B$43)*'Control Panel'!$C$44+MIN(MAX(MAX(0,H$5-'Control Panel'!$C$38)-'Control Panel'!$B$44,0),'Control Panel'!$B$45-'Control Panel'!$B$44)*'Control Panel'!$C$45+MAX(MAX(0,H$5-'Control Panel'!$C$38)-'Control Panel'!$B$45,0)*'Control Panel'!$C$46),$A11*'Control Panel'!$B$49)) | I11: =(($A11+MIN((MIN(MAX(0,I$5-'Control Panel'!$C$38),'Control Panel'!$B$43)*'Control Panel'!$C$43+MIN(MAX(MAX(0,I$5-'Control Panel'!$C$38)-'Control Panel'!$B$43,0),'Control Panel'!$B$44-'Control Panel'!$B$43)*'Control Panel'!$C$44+MIN(MAX(MAX(0,I$5-'Control Panel'!$C$38)-'Control Panel'!$B$44,0),'Control Panel'!$B$45-'Control Panel'!$B$44)*'Control Panel'!$C$45+MAX(MAX(0,I$5-'Control Panel'!$C$38)-'Control Panel'!$B$45,0)*'Control Panel'!$C$46),$A11*'Control Panel'!$B$49))-('Control Panel'!$B$11+I$5*'Control Panel'!$B$10))/($A11+MIN((MIN(MAX(0,I$5-'Control Panel'!$C$38),'Control Panel'!$B$43)*'Control Panel'!$C$43+MIN(MAX(MAX(0,I$5-'Control Panel'!$C$38)-'Control Panel'!$B$43,0),'Control Panel'!$B$44-'Control Panel'!$B$43)*'Control Panel'!$C$44+MIN(MAX(MAX(0,I$5-'Control Panel'!$C$38)-'Control Panel'!$B$44,0),'Control Panel'!$B$45-'Control Panel'!$B$44)*'Control Panel'!$C$45+MAX(MAX(0,I$5-'Control Panel'!$C$38)-'Control Panel'!$B$45,0)*'Control Panel'!$C$46),$A11*'Control Panel'!$B$49)) | ... K11: =(($A11+MIN((MIN(MAX(0,K$5-'Control Panel'!$C$38),'Control Panel'!$B$43)*'Control Panel'!$C$43+MIN(MAX(MAX(0,K$5-'Control Panel'!$C$38)-'Control Panel'!$B$43,0),'Control Panel'!$B$44-'Control Panel'!$B$43)*'Control Panel'!$C$44+MIN(MAX(MAX(0,K$5-'Control Panel'!$C$38)-'Control Panel'!$B$44,0),'Control Panel'!$B$45-'Control Panel'!$B$44)*'Control Panel'!$C$45+MAX(MAX(0,K$5-'Control Panel'!$C$38)-'Control Panel'!$B$45,0)*'Control Panel'!$C$46),$A11*'Control Panel'!$B$49))-('Control Panel'!$B$11+K$5*'Control Panel'!$B$10))/($A11+MIN((MIN(MAX(0,K$5-'Control Panel'!$C$38),'Control Panel'!$B$43)*'Control Panel'!$C$43+MIN(MAX(MAX(0,K$5-'Control Panel'!$C$38)-'Control Panel'!$B$43,0),'Control Panel'!$B$44-'Control Panel'!$B$43)*'Control Panel'!$C$44+MIN(MAX(MAX(0,K$5-'Control Panel'!$C$38)-'Control Panel'!$B$44,0),'Control Panel'!$B$45-'Control Panel'!$B$44)*'Control Panel'!$C$45+MAX(MAX(0,K$5-'Control Panel'!$C$38)-'Control Panel'!$B$45,0)*'Control Panel'!$C$46),$A11*'Control Panel'!$B$49))
A12: 549 | B12: =(($A12+MIN((MIN(MAX(0,B$5-'Control Panel'!$C$38),'Control Panel'!$B$43)*'Control Panel'!$C$43+MIN(MAX(MAX(0,B$5-'Control Panel'!$C$38)-'Control Panel'!$B$43,0),'Control Panel'!$B$44-'Control Panel'!$B$43)*'Control Panel'!$C$44+MIN(MAX(MAX(0,B$5-'Control Panel'!$C$38)-'Control Panel'!$B$44,0),'Control Panel'!$B$45-'Control Panel'!$B$44)*'Control Panel'!$C$45+MAX(MAX(0,B$5-'Control Panel'!$C$38)-'Control Panel'!$B$45,0)*'Control Panel'!$C$46),$A12*'Control Panel'!$B$49))-('Control Panel'!$B$11+B$5*'Control Panel'!$B$10))/($A12+MIN((MIN(MAX(0,B$5-'Control Panel'!$C$38),'Control Panel'!$B$43)*'Control Panel'!$C$43+MIN(MAX(MAX(0,B$5-'Control Panel'!$C$38)-'Control Panel'!$B$43,0),'Control Panel'!$B$44-'Control Panel'!$B$43)*'Control Panel'!$C$44+MIN(MAX(MAX(0,B$5-'Control Panel'!$C$38)-'Control Panel'!$B$44,0),'Control Panel'!$B$45-'Control Panel'!$B$44)*'Control Panel'!$C$45+MAX(MAX(0,B$5-'Control Panel'!$C$38)-'Control Panel'!$B$45,0)*'Control Panel'!$C$46),$A12*'Control Panel'!$B$49)) | C12: =(($A12+MIN((MIN(MAX(0,C$5-'Control Panel'!$C$38),'Control Panel'!$B$43)*'Control Panel'!$C$43+MIN(MAX(MAX(0,C$5-'Control Panel'!$C$38)-'Control Panel'!$B$43,0),'Control Panel'!$B$44-'Control Panel'!$B$43)*'Control Panel'!$C$44+MIN(MAX(MAX(0,C$5-'Control Panel'!$C$38)-'Control Panel'!$B$44,0),'Control Panel'!$B$45-'Control Panel'!$B$44)*'Control Panel'!$C$45+MAX(MAX(0,C$5-'Control Panel'!$C$38)-'Control Panel'!$B$45,0)*'Control Panel'!$C$46),$A12*'Control Panel'!$B$49))-('Control Panel'!$B$11+C$5*'Control Panel'!$B$10))/($A12+MIN((MIN(MAX(0,C$5-'Control Panel'!$C$38),'Control Panel'!$B$43)*'Control Panel'!$C$43+MIN(MAX(MAX(0,C$5-'Control Panel'!$C$38)-'Control Panel'!$B$43,0),'Control Panel'!$B$44-'Control Panel'!$B$43)*'Control Panel'!$C$44+MIN(MAX(MAX(0,C$5-'Control Panel'!$C$38)-'Control Panel'!$B$44,0),'Control Panel'!$B$45-'Control Panel'!$B$44)*'Control Panel'!$C$45+MAX(MAX(0,C$5-'Control Panel'!$C$38)-'Control Panel'!$B$45,0)*'Control Panel'!$C$46),$A12*'Control Panel'!$B$49)) | D12: =(($A12+MIN((MIN(MAX(0,D$5-'Control Panel'!$C$38),'Control Panel'!$B$43)*'Control Panel'!$C$43+MIN(MAX(MAX(0,D$5-'Control Panel'!$C$38)-'Control Panel'!$B$43,0),'Control Panel'!$B$44-'Control Panel'!$B$43)*'Control Panel'!$C$44+MIN(MAX(MAX(0,D$5-'Control Panel'!$C$38)-'Control Panel'!$B$44,0),'Control Panel'!$B$45-'Control Panel'!$B$44)*'Control Panel'!$C$45+MAX(MAX(0,D$5-'Control Panel'!$C$38)-'Control Panel'!$B$45,0)*'Control Panel'!$C$46),$A12*'Control Panel'!$B$49))-('Control Panel'!$B$11+D$5*'Control Panel'!$B$10))/($A12+MIN((MIN(MAX(0,D$5-'Control Panel'!$C$38),'Control Panel'!$B$43)*'Control Panel'!$C$43+MIN(MAX(MAX(0,D$5-'Control Panel'!$C$38)-'Control Panel'!$B$43,0),'Control Panel'!$B$44-'Control Panel'!$B$43)*'Control Panel'!$C$44+MIN(MAX(MAX(0,D$5-'Control Panel'!$C$38)-'Control Panel'!$B$44,0),'Control Panel'!$B$45-'Control Panel'!$B$44)*'Control Panel'!$C$45+MAX(MAX(0,D$5-'Control Panel'!$C$38)-'Control Panel'!$B$45,0)*'Control Panel'!$C$46),$A12*'Control Panel'!$B$49)) | E12: =(($A12+MIN((MIN(MAX(0,E$5-'Control Panel'!$C$38),'Control Panel'!$B$43)*'Control Panel'!$C$43+MIN(MAX(MAX(0,E$5-'Control Panel'!$C$38)-'Control Panel'!$B$43,0),'Control Panel'!$B$44-'Control Panel'!$B$43)*'Control Panel'!$C$44+MIN(MAX(MAX(0,E$5-'Control Panel'!$C$38)-'Control Panel'!$B$44,0),'Control Panel'!$B$45-'Control Panel'!$B$44)*'Control Panel'!$C$45+MAX(MAX(0,E$5-'Control Panel'!$C$38)-'Control Panel'!$B$45,0)*'Control Panel'!$C$46),$A12*'Control Panel'!$B$49))-('Control Panel'!$B$11+E$5*'Control Panel'!$B$10))/($A12+MIN((MIN(MAX(0,E$5-'Control Panel'!$C$38),'Control Panel'!$B$43)*'Control Panel'!$C$43+MIN(MAX(MAX(0,E$5-'Control Panel'!$C$38)-'Control Panel'!$B$43,0),'Control Panel'!$B$44-'Control Panel'!$B$43)*'Control Panel'!$C$44+MIN(MAX(MAX(0,E$5-'Control Panel'!$C$38)-'Control Panel'!$B$44,0),'Control Panel'!$B$45-'Control Panel'!$B$44)*'Control Panel'!$C$45+MAX(MAX(0,E$5-'Control Panel'!$C$38)-'Control Panel'!$B$45,0)*'Control Panel'!$C$46),$A12*'Control Panel'!$B$49)) | F12: =(($A12+MIN((MIN(MAX(0,F$5-'Control Panel'!$C$38),'Control Panel'!$B$43)*'Control Panel'!$C$43+MIN(MAX(MAX(0,F$5-'Control Panel'!$C$38)-'Control Panel'!$B$43,0),'Control Panel'!$B$44-'Control Panel'!$B$43)*'Control Panel'!$C$44+MIN(MAX(MAX(0,F$5-'Control Panel'!$C$38)-'Control Panel'!$B$44,0),'Control Panel'!$B$45-'Control Panel'!$B$44)*'Control Panel'!$C$45+MAX(MAX(0,F$5-'Control Panel'!$C$38)-'Control Panel'!$B$45,0)*'Control Panel'!$C$46),$A12*'Control Panel'!$B$49))-('Control Panel'!$B$11+F$5*'Control Panel'!$B$10))/($A12+MIN((MIN(MAX(0,F$5-'Control Panel'!$C$38),'Control Panel'!$B$43)*'Control Panel'!$C$43+MIN(MAX(MAX(0,F$5-'Control Panel'!$C$38)-'Control Panel'!$B$43,0),'Control Panel'!$B$44-'Control Panel'!$B$43)*'Control Panel'!$C$44+MIN(MAX(MAX(0,F$5-'Control Panel'!$C$38)-'Control Panel'!$B$44,0),'Control Panel'!$B$45-'Control Panel'!$B$44)*'Control Panel'!$C$45+MAX(MAX(0,F$5-'Control Panel'!$C$38)-'Control Panel'!$B$45,0)*'Control Panel'!$C$46),$A12*'Control Panel'!$B$49)) | G12: =(($A12+MIN((MIN(MAX(0,G$5-'Control Panel'!$C$38),'Control Panel'!$B$43)*'Control Panel'!$C$43+MIN(MAX(MAX(0,G$5-'Control Panel'!$C$38)-'Control Panel'!$B$43,0),'Control Panel'!$B$44-'Control Panel'!$B$43)*'Control Panel'!$C$44+MIN(MAX(MAX(0,G$5-'Control Panel'!$C$38)-'Control Panel'!$B$44,0),'Control Panel'!$B$45-'Control Panel'!$B$44)*'Control Panel'!$C$45+MAX(MAX(0,G$5-'Control Panel'!$C$38)-'Control Panel'!$B$45,0)*'Control Panel'!$C$46),$A12*'Control Panel'!$B$49))-('Control Panel'!$B$11+G$5*'Control Panel'!$B$10))/($A12+MIN((MIN(MAX(0,G$5-'Control Panel'!$C$38),'Control Panel'!$B$43)*'Control Panel'!$C$43+MIN(MAX(MAX(0,G$5-'Control Panel'!$C$38)-'Control Panel'!$B$43,0),'Control Panel'!$B$44-'Control Panel'!$B$43)*'Control Panel'!$C$44+MIN(MAX(MAX(0,G$5-'Control Panel'!$C$38)-'Control Panel'!$B$44,0),'Control Panel'!$B$45-'Control Panel'!$B$44)*'Control Panel'!$C$45+MAX(MAX(0,G$5-'Control Panel'!$C$38)-'Control Panel'!$B$45,0)*'Control Panel'!$C$46),$A12*'Control Panel'!$B$49)) | H12: =(($A12+MIN((MIN(MAX(0,H$5-'Control Panel'!$C$38),'Control Panel'!$B$43)*'Control Panel'!$C$43+MIN(MAX(MAX(0,H$5-'Control Panel'!$C$38)-'Control Panel'!$B$43,0),'Control Panel'!$B$44-'Control Panel'!$B$43)*'Control Panel'!$C$44+MIN(MAX(MAX(0,H$5-'Control Panel'!$C$38)-'Control Panel'!$B$44,0),'Control Panel'!$B$45-'Control Panel'!$B$44)*'Control Panel'!$C$45+MAX(MAX(0,H$5-'Control Panel'!$C$38)-'Control Panel'!$B$45,0)*'Control Panel'!$C$46),$A12*'Control Panel'!$B$49))-('Control Panel'!$B$11+H$5*'Control Panel'!$B$10))/($A12+MIN((MIN(MAX(0,H$5-'Control Panel'!$C$38),'Control Panel'!$B$43)*'Control Panel'!$C$43+MIN(MAX(MAX(0,H$5-'Control Panel'!$C$38)-'Control Panel'!$B$43,0),'Control Panel'!$B$44-'Control Panel'!$B$43)*'Control Panel'!$C$44+MIN(MAX(MAX(0,H$5-'Control Panel'!$C$38)-'Control Panel'!$B$44,0),'Control Panel'!$B$45-'Control Panel'!$B$44)*'Control Panel'!$C$45+MAX(MAX(0,H$5-'Control Panel'!$C$38)-'Control Panel'!$B$45,0)*'Control Panel'!$C$46),$A12*'Control Panel'!$B$49)) | I12: =(($A12+MIN((MIN(MAX(0,I$5-'Control Panel'!$C$38),'Control Panel'!$B$43)*'Control Panel'!$C$43+MIN(MAX(MAX(0,I$5-'Control Panel'!$C$38)-'Control Panel'!$B$43,0),'Control Panel'!$B$44-'Control Panel'!$B$43)*'Control Panel'!$C$44+MIN(MAX(MAX(0,I$5-'Control Panel'!$C$38)-'Control Panel'!$B$44,0),'Control Panel'!$B$45-'Control Panel'!$B$44)*'Control Panel'!$C$45+MAX(MAX(0,I$5-'Control Panel'!$C$38)-'Control Panel'!$B$45,0)*'Control Panel'!$C$46),$A12*'Control Panel'!$B$49))-('Control Panel'!$B$11+I$5*'Control Panel'!$B$10))/($A12+MIN((MIN(MAX(0,I$5-'Control Panel'!$C$38),'Control Panel'!$B$43)*'Control Panel'!$C$43+MIN(MAX(MAX(0,I$5-'Control Panel'!$C$38)-'Control Panel'!$B$43,0),'Control Panel'!$B$44-'Control Panel'!$B$43)*'Control Panel'!$C$44+MIN(MAX(MAX(0,I$5-'Control Panel'!$C$38)-'Control Panel'!$B$44,0),'Control Panel'!$B$45-'Control Panel'!$B$44)*'Control Panel'!$C$45+MAX(MAX(0,I$5-'Control Panel'!$C$38)-'Control Panel'!$B$45,0)*'Control Panel'!$C$46),$A12*'Control Panel'!$B$49)) | ... K12: =(($A12+MIN((MIN(MAX(0,K$5-'Control Panel'!$C$38),'Control Panel'!$B$43)*'Control Panel'!$C$43+MIN(MAX(MAX(0,K$5-'Control Panel'!$C$38)-'Control Panel'!$B$43,0),'Control Panel'!$B$44-'Control Panel'!$B$43)*'Control Panel'!$C$44+MIN(MAX(MAX(0,K$5-'Control Panel'!$C$38)-'Control Panel'!$B$44,0),'Control Panel'!$B$45-'Control Panel'!$B$44)*'Control Panel'!$C$45+MAX(MAX(0,K$5-'Control Panel'!$C$38)-'Control Panel'!$B$45,0)*'Control Panel'!$C$46),$A12*'Control Panel'!$B$49))-('Control Panel'!$B$11+K$5*'Control Panel'!$B$10))/($A12+MIN((MIN(MAX(0,K$5-'Control Panel'!$C$38),'Control Panel'!$B$43)*'Control Panel'!$C$43+MIN(MAX(MAX(0,K$5-'Control Panel'!$C$38)-'Control Panel'!$B$43,0),'Control Panel'!$B$44-'Control Panel'!$B$43)*'Control Panel'!$C$44+MIN(MAX(MAX(0,K$5-'Control Panel'!$C$38)-'Control Panel'!$B$44,0),'Control Panel'!$B$45-'Control Panel'!$B$44)*'Control Panel'!$C$45+MAX(MAX(0,K$5-'Control Panel'!$C$38)-'Control Panel'!$B$45,0)*'Control Panel'!$C$46),$A12*'Control Panel'!$B$49))
A13: 599 | B13: =(($A13+MIN((MIN(MAX(0,B$5-'Control Panel'!$C$38),'Control Panel'!$B$43)*'Control Panel'!$C$43+MIN(MAX(MAX(0,B$5-'Control Panel'!$C$38)-'Control Panel'!$B$43,0),'Control Panel'!$B$44-'Control Panel'!$B$43)*'Control Panel'!$C$44+MIN(MAX(MAX(0,B$5-'Control Panel'!$C$38)-'Control Panel'!$B$44,0),'Control Panel'!$B$45-'Control Panel'!$B$44)*'Control Panel'!$C$45+MAX(MAX(0,B$5-'Control Panel'!$C$38)-'Control Panel'!$B$45,0)*'Control Panel'!$C$46),$A13*'Control Panel'!$B$49))-('Control Panel'!$B$11+B$5*'Control Panel'!$B$10))/($A13+MIN((MIN(MAX(0,B$5-'Control Panel'!$C$38),'Control Panel'!$B$43)*'Control Panel'!$C$43+MIN(MAX(MAX(0,B$5-'Control Panel'!$C$38)-'Control Panel'!$B$43,0),'Control Panel'!$B$44-'Control Panel'!$B$43)*'Control Panel'!$C$44+MIN(MAX(MAX(0,B$5-'Control Panel'!$C$38)-'Control Panel'!$B$44,0),'Control Panel'!$B$45-'Control Panel'!$B$44)*'Control Panel'!$C$45+MAX(MAX(0,B$5-'Control Panel'!$C$38)-'Control Panel'!$B$45,0)*'Control Panel'!$C$46),$A13*'Control Panel'!$B$49)) | C13: =(($A13+MIN((MIN(MAX(0,C$5-'Control Panel'!$C$38),'Control Panel'!$B$43)*'Control Panel'!$C$43+MIN(MAX(MAX(0,C$5-'Control Panel'!$C$38)-'Control Panel'!$B$43,0),'Control Panel'!$B$44-'Control Panel'!$B$43)*'Control Panel'!$C$44+MIN(MAX(MAX(0,C$5-'Control Panel'!$C$38)-'Control Panel'!$B$44,0),'Control Panel'!$B$45-'Control Panel'!$B$44)*'Control Panel'!$C$45+MAX(MAX(0,C$5-'Control Panel'!$C$38)-'Control Panel'!$B$45,0)*'Control Panel'!$C$46),$A13*'Control Panel'!$B$49))-('Control Panel'!$B$11+C$5*'Control Panel'!$B$10))/($A13+MIN((MIN(MAX(0,C$5-'Control Panel'!$C$38),'Control Panel'!$B$43)*'Control Panel'!$C$43+MIN(MAX(MAX(0,C$5-'Control Panel'!$C$38)-'Control Panel'!$B$43,0),'Control Panel'!$B$44-'Control Panel'!$B$43)*'Control Panel'!$C$44+MIN(MAX(MAX(0,C$5-'Control Panel'!$C$38)-'Control Panel'!$B$44,0),'Control Panel'!$B$45-'Control Panel'!$B$44)*'Control Panel'!$C$45+MAX(MAX(0,C$5-'Control Panel'!$C$38)-'Control Panel'!$B$45,0)*'Control Panel'!$C$46),$A13*'Control Panel'!$B$49)) | D13: =(($A13+MIN((MIN(MAX(0,D$5-'Control Panel'!$C$38),'Control Panel'!$B$43)*'Control Panel'!$C$43+MIN(MAX(MAX(0,D$5-'Control Panel'!$C$38)-'Control Panel'!$B$43,0),'Control Panel'!$B$44-'Control Panel'!$B$43)*'Control Panel'!$C$44+MIN(MAX(MAX(0,D$5-'Control Panel'!$C$38)-'Control Panel'!$B$44,0),'Control Panel'!$B$45-'Control Panel'!$B$44)*'Control Panel'!$C$45+MAX(MAX(0,D$5-'Control Panel'!$C$38)-'Control Panel'!$B$45,0)*'Control Panel'!$C$46),$A13*'Control Panel'!$B$49))-('Control Panel'!$B$11+D$5*'Control Panel'!$B$10))/($A13+MIN((MIN(MAX(0,D$5-'Control Panel'!$C$38),'Control Panel'!$B$43)*'Control Panel'!$C$43+MIN(MAX(MAX(0,D$5-'Control Panel'!$C$38)-'Control Panel'!$B$43,0),'Control Panel'!$B$44-'Control Panel'!$B$43)*'Control Panel'!$C$44+MIN(MAX(MAX(0,D$5-'Control Panel'!$C$38)-'Control Panel'!$B$44,0),'Control Panel'!$B$45-'Control Panel'!$B$44)*'Control Panel'!$C$45+MAX(MAX(0,D$5-'Control Panel'!$C$38)-'Control Panel'!$B$45,0)*'Control Panel'!$C$46),$A13*'Control Panel'!$B$49)) | E13: =(($A13+MIN((MIN(MAX(0,E$5-'Control Panel'!$C$38),'Control Panel'!$B$43)*'Control Panel'!$C$43+MIN(MAX(MAX(0,E$5-'Control Panel'!$C$38)-'Control Panel'!$B$43,0),'Control Panel'!$B$44-'Control Panel'!$B$43)*'Control Panel'!$C$44+MIN(MAX(MAX(0,E$5-'Control Panel'!$C$38)-'Control Panel'!$B$44,0),'Control Panel'!$B$45-'Control Panel'!$B$44)*'Control Panel'!$C$45+MAX(MAX(0,E$5-'Control Panel'!$C$38)-'Control Panel'!$B$45,0)*'Control Panel'!$C$46),$A13*'Control Panel'!$B$49))-('Control Panel'!$B$11+E$5*'Control Panel'!$B$10))/($A13+MIN((MIN(MAX(0,E$5-'Control Panel'!$C$38),'Control Panel'!$B$43)*'Control Panel'!$C$43+MIN(MAX(MAX(0,E$5-'Control Panel'!$C$38)-'Control Panel'!$B$43,0),'Control Panel'!$B$44-'Control Panel'!$B$43)*'Control Panel'!$C$44+MIN(MAX(MAX(0,E$5-'Control Panel'!$C$38)-'Control Panel'!$B$44,0),'Control Panel'!$B$45-'Control Panel'!$B$44)*'Control Panel'!$C$45+MAX(MAX(0,E$5-'Control Panel'!$C$38)-'Control Panel'!$B$45,0)*'Control Panel'!$C$46),$A13*'Control Panel'!$B$49)) | F13: =(($A13+MIN((MIN(MAX(0,F$5-'Control Panel'!$C$38),'Control Panel'!$B$43)*'Control Panel'!$C$43+MIN(MAX(MAX(0,F$5-'Control Panel'!$C$38)-'Control Panel'!$B$43,0),'Control Panel'!$B$44-'Control Panel'!$B$43)*'Control Panel'!$C$44+MIN(MAX(MAX(0,F$5-'Control Panel'!$C$38)-'Control Panel'!$B$44,0),'Control Panel'!$B$45-'Control Panel'!$B$44)*'Control Panel'!$C$45+MAX(MAX(0,F$5-'Control Panel'!$C$38)-'Control Panel'!$B$45,0)*'Control Panel'!$C$46),$A13*'Control Panel'!$B$49))-('Control Panel'!$B$11+F$5*'Control Panel'!$B$10))/($A13+MIN((MIN(MAX(0,F$5-'Control Panel'!$C$38),'Control Panel'!$B$43)*'Control Panel'!$C$43+MIN(MAX(MAX(0,F$5-'Control Panel'!$C$38)-'Control Panel'!$B$43,0),'Control Panel'!$B$44-'Control Panel'!$B$43)*'Control Panel'!$C$44+MIN(MAX(MAX(0,F$5-'Control Panel'!$C$38)-'Control Panel'!$B$44,0),'Control Panel'!$B$45-'Control Panel'!$B$44)*'Control Panel'!$C$45+MAX(MAX(0,F$5-'Control Panel'!$C$38)-'Control Panel'!$B$45,0)*'Control Panel'!$C$46),$A13*'Control Panel'!$B$49)) | G13: =(($A13+MIN((MIN(MAX(0,G$5-'Control Panel'!$C$38),'Control Panel'!$B$43)*'Control Panel'!$C$43+MIN(MAX(MAX(0,G$5-'Control Panel'!$C$38)-'Control Panel'!$B$43,0),'Control Panel'!$B$44-'Control Panel'!$B$43)*'Control Panel'!$C$44+MIN(MAX(MAX(0,G$5-'Control Panel'!$C$38)-'Control Panel'!$B$44,0),'Control Panel'!$B$45-'Control Panel'!$B$44)*'Control Panel'!$C$45+MAX(MAX(0,G$5-'Control Panel'!$C$38)-'Control Panel'!$B$45,0)*'Control Panel'!$C$46),$A13*'Control Panel'!$B$49))-('Control Panel'!$B$11+G$5*'Control Panel'!$B$10))/($A13+MIN((MIN(MAX(0,G$5-'Control Panel'!$C$38),'Control Panel'!$B$43)*'Control Panel'!$C$43+MIN(MAX(MAX(0,G$5-'Control Panel'!$C$38)-'Control Panel'!$B$43,0),'Control Panel'!$B$44-'Control Panel'!$B$43)*'Control Panel'!$C$44+MIN(MAX(MAX(0,G$5-'Control Panel'!$C$38)-'Control Panel'!$B$44,0),'Control Panel'!$B$45-'Control Panel'!$B$44)*'Control Panel'!$C$45+MAX(MAX(0,G$5-'Control Panel'!$C$38)-'Control Panel'!$B$45,0)*'Control Panel'!$C$46),$A13*'Control Panel'!$B$49)) | H13: =(($A13+MIN((MIN(MAX(0,H$5-'Control Panel'!$C$38),'Control Panel'!$B$43)*'Control Panel'!$C$43+MIN(MAX(MAX(0,H$5-'Control Panel'!$C$38)-'Control Panel'!$B$43,0),'Control Panel'!$B$44-'Control Panel'!$B$43)*'Control Panel'!$C$44+MIN(MAX(MAX(0,H$5-'Control Panel'!$C$38)-'Control Panel'!$B$44,0),'Control Panel'!$B$45-'Control Panel'!$B$44)*'Control Panel'!$C$45+MAX(MAX(0,H$5-'Control Panel'!$C$38)-'Control Panel'!$B$45,0)*'Control Panel'!$C$46),$A13*'Control Panel'!$B$49))-('Control Panel'!$B$11+H$5*'Control Panel'!$B$10))/($A13+MIN((MIN(MAX(0,H$5-'Control Panel'!$C$38),'Control Panel'!$B$43)*'Control Panel'!$C$43+MIN(MAX(MAX(0,H$5-'Control Panel'!$C$38)-'Control Panel'!$B$43,0),'Control Panel'!$B$44-'Control Panel'!$B$43)*'Control Panel'!$C$44+MIN(MAX(MAX(0,H$5-'Control Panel'!$C$38)-'Control Panel'!$B$44,0),'Control Panel'!$B$45-'Control Panel'!$B$44)*'Control Panel'!$C$45+MAX(MAX(0,H$5-'Control Panel'!$C$38)-'Control Panel'!$B$45,0)*'Control Panel'!$C$46),$A13*'Control Panel'!$B$49)) | I13: =(($A13+MIN((MIN(MAX(0,I$5-'Control Panel'!$C$38),'Control Panel'!$B$43)*'Control Panel'!$C$43+MIN(MAX(MAX(0,I$5-'Control Panel'!$C$38)-'Control Panel'!$B$43,0),'Control Panel'!$B$44-'Control Panel'!$B$43)*'Control Panel'!$C$44+MIN(MAX(MAX(0,I$5-'Control Panel'!$C$38)-'Control Panel'!$B$44,0),'Control Panel'!$B$45-'Control Panel'!$B$44)*'Control Panel'!$C$45+MAX(MAX(0,I$5-'Control Panel'!$C$38)-'Control Panel'!$B$45,0)*'Control Panel'!$C$46),$A13*'Control Panel'!$B$49))-('Control Panel'!$B$11+I$5*'Control Panel'!$B$10))/($A13+MIN((MIN(MAX(0,I$5-'Control Panel'!$C$38),'Control Panel'!$B$43)*'Control Panel'!$C$43+MIN(MAX(MAX(0,I$5-'Control Panel'!$C$38)-'Control Panel'!$B$43,0),'Control Panel'!$B$44-'Control Panel'!$B$43)*'Control Panel'!$C$44+MIN(MAX(MAX(0,I$5-'Control Panel'!$C$38)-'Control Panel'!$B$44,0),'Control Panel'!$B$45-'Control Panel'!$B$44)*'Control Panel'!$C$45+MAX(MAX(0,I$5-'Control Panel'!$C$38)-'Control Panel'!$B$45,0)*'Control Panel'!$C$46),$A13*'Control Panel'!$B$49)) | ... K13: =(($A13+MIN((MIN(MAX(0,K$5-'Control Panel'!$C$38),'Control Panel'!$B$43)*'Control Panel'!$C$43+MIN(MAX(MAX(0,K$5-'Control Panel'!$C$38)-'Control Panel'!$B$43,0),'Control Panel'!$B$44-'Control Panel'!$B$43)*'Control Panel'!$C$44+MIN(MAX(MAX(0,K$5-'Control Panel'!$C$38)-'Control Panel'!$B$44,0),'Control Panel'!$B$45-'Control Panel'!$B$44)*'Control Panel'!$C$45+MAX(MAX(0,K$5-'Control Panel'!$C$38)-'Control Panel'!$B$45,0)*'Control Panel'!$C$46),$A13*'Control Panel'!$B$49))-('Control Panel'!$B$11+K$5*'Control Panel'!$B$10))/($A13+MIN((MIN(MAX(0,K$5-'Control Panel'!$C$38),'Control Panel'!$B$43)*'Control Panel'!$C$43+MIN(MAX(MAX(0,K$5-'Control Panel'!$C$38)-'Control Panel'!$B$43,0),'Control Panel'!$B$44-'Control Panel'!$B$43)*'Control Panel'!$C$44+MIN(MAX(MAX(0,K$5-'Control Panel'!$C$38)-'Control Panel'!$B$44,0),'Control Panel'!$B$45-'Control Panel'!$B$44)*'Control Panel'!$C$45+MAX(MAX(0,K$5-'Control Panel'!$C$38)-'Control Panel'!$B$45,0)*'Control Panel'!$C$46),$A13*'Control Panel'!$B$49))
A14: 649 | B14: =(($A14+MIN((MIN(MAX(0,B$5-'Control Panel'!$C$38),'Control Panel'!$B$43)*'Control Panel'!$C$43+MIN(MAX(MAX(0,B$5-'Control Panel'!$C$38)-'Control Panel'!$B$43,0),'Control Panel'!$B$44-'Control Panel'!$B$43)*'Control Panel'!$C$44+MIN(MAX(MAX(0,B$5-'Control Panel'!$C$38)-'Control Panel'!$B$44,0),'Control Panel'!$B$45-'Control Panel'!$B$44)*'Control Panel'!$C$45+MAX(MAX(0,B$5-'Control Panel'!$C$38)-'Control Panel'!$B$45,0)*'Control Panel'!$C$46),$A14*'Control Panel'!$B$49))-('Control Panel'!$B$11+B$5*'Control Panel'!$B$10))/($A14+MIN((MIN(MAX(0,B$5-'Control Panel'!$C$38),'Control Panel'!$B$43)*'Control Panel'!$C$43+MIN(MAX(MAX(0,B$5-'Control Panel'!$C$38)-'Control Panel'!$B$43,0),'Control Panel'!$B$44-'Control Panel'!$B$43)*'Control Panel'!$C$44+MIN(MAX(MAX(0,B$5-'Control Panel'!$C$38)-'Control Panel'!$B$44,0),'Control Panel'!$B$45-'Control Panel'!$B$44)*'Control Panel'!$C$45+MAX(MAX(0,B$5-'Control Panel'!$C$38)-'Control Panel'!$B$45,0)*'Control Panel'!$C$46),$A14*'Control Panel'!$B$49)) | C14: =(($A14+MIN((MIN(MAX(0,C$5-'Control Panel'!$C$38),'Control Panel'!$B$43)*'Control Panel'!$C$43+MIN(MAX(MAX(0,C$5-'Control Panel'!$C$38)-'Control Panel'!$B$43,0),'Control Panel'!$B$44-'Control Panel'!$B$43)*'Control Panel'!$C$44+MIN(MAX(MAX(0,C$5-'Control Panel'!$C$38)-'Control Panel'!$B$44,0),'Control Panel'!$B$45-'Control Panel'!$B$44)*'Control Panel'!$C$45+MAX(MAX(0,C$5-'Control Panel'!$C$38)-'Control Panel'!$B$45,0)*'Control Panel'!$C$46),$A14*'Control Panel'!$B$49))-('Control Panel'!$B$11+C$5*'Control Panel'!$B$10))/($A14+MIN((MIN(MAX(0,C$5-'Control Panel'!$C$38),'Control Panel'!$B$43)*'Control Panel'!$C$43+MIN(MAX(MAX(0,C$5-'Control Panel'!$C$38)-'Control Panel'!$B$43,0),'Control Panel'!$B$44-'Control Panel'!$B$43)*'Control Panel'!$C$44+MIN(MAX(MAX(0,C$5-'Control Panel'!$C$38)-'Control Panel'!$B$44,0),'Control Panel'!$B$45-'Control Panel'!$B$44)*'Control Panel'!$C$45+MAX(MAX(0,C$5-'Control Panel'!$C$38)-'Control Panel'!$B$45,0)*'Control Panel'!$C$46),$A14*'Control Panel'!$B$49)) | D14: =(($A14+MIN((MIN(MAX(0,D$5-'Control Panel'!$C$38),'Control Panel'!$B$43)*'Control Panel'!$C$43+MIN(MAX(MAX(0,D$5-'Control Panel'!$C$38)-'Control Panel'!$B$43,0),'Control Panel'!$B$44-'Control Panel'!$B$43)*'Control Panel'!$C$44+MIN(MAX(MAX(0,D$5-'Control Panel'!$C$38)-'Control Panel'!$B$44,0),'Control Panel'!$B$45-'Control Panel'!$B$44)*'Control Panel'!$C$45+MAX(MAX(0,D$5-'Control Panel'!$C$38)-'Control Panel'!$B$45,0)*'Control Panel'!$C$46),$A14*'Control Panel'!$B$49))-('Control Panel'!$B$11+D$5*'Control Panel'!$B$10))/($A14+MIN((MIN(MAX(0,D$5-'Control Panel'!$C$38),'Control Panel'!$B$43)*'Control Panel'!$C$43+MIN(MAX(MAX(0,D$5-'Control Panel'!$C$38)-'Control Panel'!$B$43,0),'Control Panel'!$B$44-'Control Panel'!$B$43)*'Control Panel'!$C$44+MIN(MAX(MAX(0,D$5-'Control Panel'!$C$38)-'Control Panel'!$B$44,0),'Control Panel'!$B$45-'Control Panel'!$B$44)*'Control Panel'!$C$45+MAX(MAX(0,D$5-'Control Panel'!$C$38)-'Control Panel'!$B$45,0)*'Control Panel'!$C$46),$A14*'Control Panel'!$B$49)) | E14: =(($A14+MIN((MIN(MAX(0,E$5-'Control Panel'!$C$38),'Control Panel'!$B$43)*'Control Panel'!$C$43+MIN(MAX(MAX(0,E$5-'Control Panel'!$C$38)-'Control Panel'!$B$43,0),'Control Panel'!$B$44-'Control Panel'!$B$43)*'Control Panel'!$C$44+MIN(MAX(MAX(0,E$5-'Control Panel'!$C$38)-'Control Panel'!$B$44,0),'Control Panel'!$B$45-'Control Panel'!$B$44)*'Control Panel'!$C$45+MAX(MAX(0,E$5-'Control Panel'!$C$38)-'Control Panel'!$B$45,0)*'Control Panel'!$C$46),$A14*'Control Panel'!$B$49))-('Control Panel'!$B$11+E$5*'Control Panel'!$B$10))/($A14+MIN((MIN(MAX(0,E$5-'Control Panel'!$C$38),'Control Panel'!$B$43)*'Control Panel'!$C$43+MIN(MAX(MAX(0,E$5-'Control Panel'!$C$38)-'Control Panel'!$B$43,0),'Control Panel'!$B$44-'Control Panel'!$B$43)*'Control Panel'!$C$44+MIN(MAX(MAX(0,E$5-'Control Panel'!$C$38)-'Control Panel'!$B$44,0),'Control Panel'!$B$45-'Control Panel'!$B$44)*'Control Panel'!$C$45+MAX(MAX(0,E$5-'Control Panel'!$C$38)-'Control Panel'!$B$45,0)*'Control Panel'!$C$46),$A14*'Control Panel'!$B$49)) | F14: =(($A14+MIN((MIN(MAX(0,F$5-'Control Panel'!$C$38),'Control Panel'!$B$43)*'Control Panel'!$C$43+MIN(MAX(MAX(0,F$5-'Control Panel'!$C$38)-'Control Panel'!$B$43,0),'Control Panel'!$B$44-'Control Panel'!$B$43)*'Control Panel'!$C$44+MIN(MAX(MAX(0,F$5-'Control Panel'!$C$38)-'Control Panel'!$B$44,0),'Control Panel'!$B$45-'Control Panel'!$B$44)*'Control Panel'!$C$45+MAX(MAX(0,F$5-'Control Panel'!$C$38)-'Control Panel'!$B$45,0)*'Control Panel'!$C$46),$A14*'Control Panel'!$B$49))-('Control Panel'!$B$11+F$5*'Control Panel'!$B$10))/($A14+MIN((MIN(MAX(0,F$5-'Control Panel'!$C$38),'Control Panel'!$B$43)*'Control Panel'!$C$43+MIN(MAX(MAX(0,F$5-'Control Panel'!$C$38)-'Control Panel'!$B$43,0),'Control Panel'!$B$44-'Control Panel'!$B$43)*'Control Panel'!$C$44+MIN(MAX(MAX(0,F$5-'Control Panel'!$C$38)-'Control Panel'!$B$44,0),'Control Panel'!$B$45-'Control Panel'!$B$44)*'Control Panel'!$C$45+MAX(MAX(0,F$5-'Control Panel'!$C$38)-'Control Panel'!$B$45,0)*'Control Panel'!$C$46),$A14*'Control Panel'!$B$49)) | G14: =(($A14+MIN((MIN(MAX(0,G$5-'Control Panel'!$C$38),'Control Panel'!$B$43)*'Control Panel'!$C$43+MIN(MAX(MAX(0,G$5-'Control Panel'!$C$38)-'Control Panel'!$B$43,0),'Control Panel'!$B$44-'Control Panel'!$B$43)*'Control Panel'!$C$44+MIN(MAX(MAX(0,G$5-'Control Panel'!$C$38)-'Control Panel'!$B$44,0),'Control Panel'!$B$45-'Control Panel'!$B$44)*'Control Panel'!$C$45+MAX(MAX(0,G$5-'Control Panel'!$C$38)-'Control Panel'!$B$45,0)*'Control Panel'!$C$46),$A14*'Control Panel'!$B$49))-('Control Panel'!$B$11+G$5*'Control Panel'!$B$10))/($A14+MIN((MIN(MAX(0,G$5-'Control Panel'!$C$38),'Control Panel'!$B$43)*'Control Panel'!$C$43+MIN(MAX(MAX(0,G$5-'Control Panel'!$C$38)-'Control Panel'!$B$43,0),'Control Panel'!$B$44-'Control Panel'!$B$43)*'Control Panel'!$C$44+MIN(MAX(MAX(0,G$5-'Control Panel'!$C$38)-'Control Panel'!$B$44,0),'Control Panel'!$B$45-'Control Panel'!$B$44)*'Control Panel'!$C$45+MAX(MAX(0,G$5-'Control Panel'!$C$38)-'Control Panel'!$B$45,0)*'Control Panel'!$C$46),$A14*'Control Panel'!$B$49)) | H14: =(($A14+MIN((MIN(MAX(0,H$5-'Control Panel'!$C$38),'Control Panel'!$B$43)*'Control Panel'!$C$43+MIN(MAX(MAX(0,H$5-'Control Panel'!$C$38)-'Control Panel'!$B$43,0),'Control Panel'!$B$44-'Control Panel'!$B$43)*'Control Panel'!$C$44+MIN(MAX(MAX(0,H$5-'Control Panel'!$C$38)-'Control Panel'!$B$44,0),'Control Panel'!$B$45-'Control Panel'!$B$44)*'Control Panel'!$C$45+MAX(MAX(0,H$5-'Control Panel'!$C$38)-'Control Panel'!$B$45,0)*'Control Panel'!$C$46),$A14*'Control Panel'!$B$49))-('Control Panel'!$B$11+H$5*'Control Panel'!$B$10))/($A14+MIN((MIN(MAX(0,H$5-'Control Panel'!$C$38),'Control Panel'!$B$43)*'Control Panel'!$C$43+MIN(MAX(MAX(0,H$5-'Control Panel'!$C$38)-'Control Panel'!$B$43,0),'Control Panel'!$B$44-'Control Panel'!$B$43)*'Control Panel'!$C$44+MIN(MAX(MAX(0,H$5-'Control Panel'!$C$38)-'Control Panel'!$B$44,0),'Control Panel'!$B$45-'Control Panel'!$B$44)*'Control Panel'!$C$45+MAX(MAX(0,H$5-'Control Panel'!$C$38)-'Control Panel'!$B$45,0)*'Control Panel'!$C$46),$A14*'Control Panel'!$B$49)) | I14: =(($A14+MIN((MIN(MAX(0,I$5-'Control Panel'!$C$38),'Control Panel'!$B$43)*'Control Panel'!$C$43+MIN(MAX(MAX(0,I$5-'Control Panel'!$C$38)-'Control Panel'!$B$43,0),'Control Panel'!$B$44-'Control Panel'!$B$43)*'Control Panel'!$C$44+MIN(MAX(MAX(0,I$5-'Control Panel'!$C$38)-'Control Panel'!$B$44,0),'Control Panel'!$B$45-'Control Panel'!$B$44)*'Control Panel'!$C$45+MAX(MAX(0,I$5-'Control Panel'!$C$38)-'Control Panel'!$B$45,0)*'Control Panel'!$C$46),$A14*'Control Panel'!$B$49))-('Control Panel'!$B$11+I$5*'Control Panel'!$B$10))/($A14+MIN((MIN(MAX(0,I$5-'Control Panel'!$C$38),'Control Panel'!$B$43)*'Control Panel'!$C$43+MIN(MAX(MAX(0,I$5-'Control Panel'!$C$38)-'Control Panel'!$B$43,0),'Control Panel'!$B$44-'Control Panel'!$B$43)*'Control Panel'!$C$44+MIN(MAX(MAX(0,I$5-'Control Panel'!$C$38)-'Control Panel'!$B$44,0),'Control Panel'!$B$45-'Control Panel'!$B$44)*'Control Panel'!$C$45+MAX(MAX(0,I$5-'Control Panel'!$C$38)-'Control Panel'!$B$45,0)*'Control Panel'!$C$46),$A14*'Control Panel'!$B$49)) | ... K14: =(($A14+MIN((MIN(MAX(0,K$5-'Control Panel'!$C$38),'Control Panel'!$B$43)*'Control Panel'!$C$43+MIN(MAX(MAX(0,K$5-'Control Panel'!$C$38)-'Control Panel'!$B$43,0),'Control Panel'!$B$44-'Control Panel'!$B$43)*'Control Panel'!$C$44+MIN(MAX(MAX(0,K$5-'Control Panel'!$C$38)-'Control Panel'!$B$44,0),'Control Panel'!$B$45-'Control Panel'!$B$44)*'Control Panel'!$C$45+MAX(MAX(0,K$5-'Control Panel'!$C$38)-'Control Panel'!$B$45,0)*'Control Panel'!$C$46),$A14*'Control Panel'!$B$49))-('Control Panel'!$B$11+K$5*'Control Panel'!$B$10))/($A14+MIN((MIN(MAX(0,K$5-'Control Panel'!$C$38),'Control Panel'!$B$43)*'Control Panel'!$C$43+MIN(MAX(MAX(0,K$5-'Control Panel'!$C$38)-'Control Panel'!$B$43,0),'Control Panel'!$B$44-'Control Panel'!$B$43)*'Control Panel'!$C$44+MIN(MAX(MAX(0,K$5-'Control Panel'!$C$38)-'Control Panel'!$B$44,0),'Control Panel'!$B$45-'Control Panel'!$B$44)*'Control Panel'!$C$45+MAX(MAX(0,K$5-'Control Panel'!$C$38)-'Control Panel'!$B$45,0)*'Control Panel'!$C$46),$A14*'Control Panel'!$B$49))
A15: 699 | B15: =(($A15+MIN((MIN(MAX(0,B$5-'Control Panel'!$C$38),'Control Panel'!$B$43)*'Control Panel'!$C$43+MIN(MAX(MAX(0,B$5-'Control Panel'!$C$38)-'Control Panel'!$B$43,0),'Control Panel'!$B$44-'Control Panel'!$B$43)*'Control Panel'!$C$44+MIN(MAX(MAX(0,B$5-'Control Panel'!$C$38)-'Control Panel'!$B$44,0),'Control Panel'!$B$45-'Control Panel'!$B$44)*'Control Panel'!$C$45+MAX(MAX(0,B$5-'Control Panel'!$C$38)-'Control Panel'!$B$45,0)*'Control Panel'!$C$46),$A15*'Control Panel'!$B$49))-('Control Panel'!$B$11+B$5*'Control Panel'!$B$10))/($A15+MIN((MIN(MAX(0,B$5-'Control Panel'!$C$38),'Control Panel'!$B$43)*'Control Panel'!$C$43+MIN(MAX(MAX(0,B$5-'Control Panel'!$C$38)-'Control Panel'!$B$43,0),'Control Panel'!$B$44-'Control Panel'!$B$43)*'Control Panel'!$C$44+MIN(MAX(MAX(0,B$5-'Control Panel'!$C$38)-'Control Panel'!$B$44,0),'Control Panel'!$B$45-'Control Panel'!$B$44)*'Control Panel'!$C$45+MAX(MAX(0,B$5-'Control Panel'!$C$38)-'Control Panel'!$B$45,0)*'Control Panel'!$C$46),$A15*'Control Panel'!$B$49)) | C15: =(($A15+MIN((MIN(MAX(0,C$5-'Control Panel'!$C$38),'Control Panel'!$B$43)*'Control Panel'!$C$43+MIN(MAX(MAX(0,C$5-'Control Panel'!$C$38)-'Control Panel'!$B$43,0),'Control Panel'!$B$44-'Control Panel'!$B$43)*'Control Panel'!$C$44+MIN(MAX(MAX(0,C$5-'Control Panel'!$C$38)-'Control Panel'!$B$44,0),'Control Panel'!$B$45-'Control Panel'!$B$44)*'Control Panel'!$C$45+MAX(MAX(0,C$5-'Control Panel'!$C$38)-'Control Panel'!$B$45,0)*'Control Panel'!$C$46),$A15*'Control Panel'!$B$49))-('Control Panel'!$B$11+C$5*'Control Panel'!$B$10))/($A15+MIN((MIN(MAX(0,C$5-'Control Panel'!$C$38),'Control Panel'!$B$43)*'Control Panel'!$C$43+MIN(MAX(MAX(0,C$5-'Control Panel'!$C$38)-'Control Panel'!$B$43,0),'Control Panel'!$B$44-'Control Panel'!$B$43)*'Control Panel'!$C$44+MIN(MAX(MAX(0,C$5-'Control Panel'!$C$38)-'Control Panel'!$B$44,0),'Control Panel'!$B$45-'Control Panel'!$B$44)*'Control Panel'!$C$45+MAX(MAX(0,C$5-'Control Panel'!$C$38)-'Control Panel'!$B$45,0)*'Control Panel'!$C$46),$A15*'Control Panel'!$B$49)) | D15: =(($A15+MIN((MIN(MAX(0,D$5-'Control Panel'!$C$38),'Control Panel'!$B$43)*'Control Panel'!$C$43+MIN(MAX(MAX(0,D$5-'Control Panel'!$C$38)-'Control Panel'!$B$43,0),'Control Panel'!$B$44-'Control Panel'!$B$43)*'Control Panel'!$C$44+MIN(MAX(MAX(0,D$5-'Control Panel'!$C$38)-'Control Panel'!$B$44,0),'Control Panel'!$B$45-'Control Panel'!$B$44)*'Control Panel'!$C$45+MAX(MAX(0,D$5-'Control Panel'!$C$38)-'Control Panel'!$B$45,0)*'Control Panel'!$C$46),$A15*'Control Panel'!$B$49))-('Control Panel'!$B$11+D$5*'Control Panel'!$B$10))/($A15+MIN((MIN(MAX(0,D$5-'Control Panel'!$C$38),'Control Panel'!$B$43)*'Control Panel'!$C$43+MIN(MAX(MAX(0,D$5-'Control Panel'!$C$38)-'Control Panel'!$B$43,0),'Control Panel'!$B$44-'Control Panel'!$B$43)*'Control Panel'!$C$44+MIN(MAX(MAX(0,D$5-'Control Panel'!$C$38)-'Control Panel'!$B$44,0),'Control Panel'!$B$45-'Control Panel'!$B$44)*'Control Panel'!$C$45+MAX(MAX(0,D$5-'Control Panel'!$C$38)-'Control Panel'!$B$45,0)*'Control Panel'!$C$46),$A15*'Control Panel'!$B$49)) | E15: =(($A15+MIN((MIN(MAX(0,E$5-'Control Panel'!$C$38),'Control Panel'!$B$43)*'Control Panel'!$C$43+MIN(MAX(MAX(0,E$5-'Control Panel'!$C$38)-'Control Panel'!$B$43,0),'Control Panel'!$B$44-'Control Panel'!$B$43)*'Control Panel'!$C$44+MIN(MAX(MAX(0,E$5-'Control Panel'!$C$38)-'Control Panel'!$B$44,0),'Control Panel'!$B$45-'Control Panel'!$B$44)*'Control Panel'!$C$45+MAX(MAX(0,E$5-'Control Panel'!$C$38)-'Control Panel'!$B$45,0)*'Control Panel'!$C$46),$A15*'Control Panel'!$B$49))-('Control Panel'!$B$11+E$5*'Control Panel'!$B$10))/($A15+MIN((MIN(MAX(0,E$5-'Control Panel'!$C$38),'Control Panel'!$B$43)*'Control Panel'!$C$43+MIN(MAX(MAX(0,E$5-'Control Panel'!$C$38)-'Control Panel'!$B$43,0),'Control Panel'!$B$44-'Control Panel'!$B$43)*'Control Panel'!$C$44+MIN(MAX(MAX(0,E$5-'Control Panel'!$C$38)-'Control Panel'!$B$44,0),'Control Panel'!$B$45-'Control Panel'!$B$44)*'Control Panel'!$C$45+MAX(MAX(0,E$5-'Control Panel'!$C$38)-'Control Panel'!$B$45,0)*'Control Panel'!$C$46),$A15*'Control Panel'!$B$49)) | F15: =(($A15+MIN((MIN(MAX(0,F$5-'Control Panel'!$C$38),'Control Panel'!$B$43)*'Control Panel'!$C$43+MIN(MAX(MAX(0,F$5-'Control Panel'!$C$38)-'Control Panel'!$B$43,0),'Control Panel'!$B$44-'Control Panel'!$B$43)*'Control Panel'!$C$44+MIN(MAX(MAX(0,F$5-'Control Panel'!$C$38)-'Control Panel'!$B$44,0),'Control Panel'!$B$45-'Control Panel'!$B$44)*'Control Panel'!$C$45+MAX(MAX(0,F$5-'Control Panel'!$C$38)-'Control Panel'!$B$45,0)*'Control Panel'!$C$46),$A15*'Control Panel'!$B$49))-('Control Panel'!$B$11+F$5*'Control Panel'!$B$10))/($A15+MIN((MIN(MAX(0,F$5-'Control Panel'!$C$38),'Control Panel'!$B$43)*'Control Panel'!$C$43+MIN(MAX(MAX(0,F$5-'Control Panel'!$C$38)-'Control Panel'!$B$43,0),'Control Panel'!$B$44-'Control Panel'!$B$43)*'Control Panel'!$C$44+MIN(MAX(MAX(0,F$5-'Control Panel'!$C$38)-'Control Panel'!$B$44,0),'Control Panel'!$B$45-'Control Panel'!$B$44)*'Control Panel'!$C$45+MAX(MAX(0,F$5-'Control Panel'!$C$38)-'Control Panel'!$B$45,0)*'Control Panel'!$C$46),$A15*'Control Panel'!$B$49)) | G15: =(($A15+MIN((MIN(MAX(0,G$5-'Control Panel'!$C$38),'Control Panel'!$B$43)*'Control Panel'!$C$43+MIN(MAX(MAX(0,G$5-'Control Panel'!$C$38)-'Control Panel'!$B$43,0),'Control Panel'!$B$44-'Control Panel'!$B$43)*'Control Panel'!$C$44+MIN(MAX(MAX(0,G$5-'Control Panel'!$C$38)-'Control Panel'!$B$44,0),'Control Panel'!$B$45-'Control Panel'!$B$44)*'Control Panel'!$C$45+MAX(MAX(0,G$5-'Control Panel'!$C$38)-'Control Panel'!$B$45,0)*'Control Panel'!$C$46),$A15*'Control Panel'!$B$49))-('Control Panel'!$B$11+G$5*'Control Panel'!$B$10))/($A15+MIN((MIN(MAX(0,G$5-'Control Panel'!$C$38),'Control Panel'!$B$43)*'Control Panel'!$C$43+MIN(MAX(MAX(0,G$5-'Control Panel'!$C$38)-'Control Panel'!$B$43,0),'Control Panel'!$B$44-'Control Panel'!$B$43)*'Control Panel'!$C$44+MIN(MAX(MAX(0,G$5-'Control Panel'!$C$38)-'Control Panel'!$B$44,0),'Control Panel'!$B$45-'Control Panel'!$B$44)*'Control Panel'!$C$45+MAX(MAX(0,G$5-'Control Panel'!$C$38)-'Control Panel'!$B$45,0)*'Control Panel'!$C$46),$A15*'Control Panel'!$B$49)) | H15: =(($A15+MIN((MIN(MAX(0,H$5-'Control Panel'!$C$38),'Control Panel'!$B$43)*'Control Panel'!$C$43+MIN(MAX(MAX(0,H$5-'Control Panel'!$C$38)-'Control Panel'!$B$43,0),'Control Panel'!$B$44-'Control Panel'!$B$43)*'Control Panel'!$C$44+MIN(MAX(MAX(0,H$5-'Control Panel'!$C$38)-'Control Panel'!$B$44,0),'Control Panel'!$B$45-'Control Panel'!$B$44)*'Control Panel'!$C$45+MAX(MAX(0,H$5-'Control Panel'!$C$38)-'Control Panel'!$B$45,0)*'Control Panel'!$C$46),$A15*'Control Panel'!$B$49))-('Control Panel'!$B$11+H$5*'Control Panel'!$B$10))/($A15+MIN((MIN(MAX(0,H$5-'Control Panel'!$C$38),'Control Panel'!$B$43)*'Control Panel'!$C$43+MIN(MAX(MAX(0,H$5-'Control Panel'!$C$38)-'Control Panel'!$B$43,0),'Control Panel'!$B$44-'Control Panel'!$B$43)*'Control Panel'!$C$44+MIN(MAX(MAX(0,H$5-'Control Panel'!$C$38)-'Control Panel'!$B$44,0),'Control Panel'!$B$45-'Control Panel'!$B$44)*'Control Panel'!$C$45+MAX(MAX(0,H$5-'Control Panel'!$C$38)-'Control Panel'!$B$45,0)*'Control Panel'!$C$46),$A15*'Control Panel'!$B$49)) | I15: =(($A15+MIN((MIN(MAX(0,I$5-'Control Panel'!$C$38),'Control Panel'!$B$43)*'Control Panel'!$C$43+MIN(MAX(MAX(0,I$5-'Control Panel'!$C$38)-'Control Panel'!$B$43,0),'Control Panel'!$B$44-'Control Panel'!$B$43)*'Control Panel'!$C$44+MIN(MAX(MAX(0,I$5-'Control Panel'!$C$38)-'Control Panel'!$B$44,0),'Control Panel'!$B$45-'Control Panel'!$B$44)*'Control Panel'!$C$45+MAX(MAX(0,I$5-'Control Panel'!$C$38)-'Control Panel'!$B$45,0)*'Control Panel'!$C$46),$A15*'Control Panel'!$B$49))-('Control Panel'!$B$11+I$5*'Control Panel'!$B$10))/($A15+MIN((MIN(MAX(0,I$5-'Control Panel'!$C$38),'Control Panel'!$B$43)*'Control Panel'!$C$43+MIN(MAX(MAX(0,I$5-'Control Panel'!$C$38)-'Control Panel'!$B$43,0),'Control Panel'!$B$44-'Control Panel'!$B$43)*'Control Panel'!$C$44+MIN(MAX(MAX(0,I$5-'Control Panel'!$C$38)-'Control Panel'!$B$44,0),'Control Panel'!$B$45-'Control Panel'!$B$44)*'Control Panel'!$C$45+MAX(MAX(0,I$5-'Control Panel'!$C$38)-'Control Panel'!$B$45,0)*'Control Panel'!$C$46),$A15*'Control Panel'!$B$49)) | ... K15: =(($A15+MIN((MIN(MAX(0,K$5-'Control Panel'!$C$38),'Control Panel'!$B$43)*'Control Panel'!$C$43+MIN(MAX(MAX(0,K$5-'Control Panel'!$C$38)-'Control Panel'!$B$43,0),'Control Panel'!$B$44-'Control Panel'!$B$43)*'Control Panel'!$C$44+MIN(MAX(MAX(0,K$5-'Control Panel'!$C$38)-'Control Panel'!$B$44,0),'Control Panel'!$B$45-'Control Panel'!$B$44)*'Control Panel'!$C$45+MAX(MAX(0,K$5-'Control Panel'!$C$38)-'Control Panel'!$B$45,0)*'Control Panel'!$C$46),$A15*'Control Panel'!$B$49))-('Control Panel'!$B$11+K$5*'Control Panel'!$B$10))/($A15+MIN((MIN(MAX(0,K$5-'Control Panel'!$C$38),'Control Panel'!$B$43)*'Control Panel'!$C$43+MIN(MAX(MAX(0,K$5-'Control Panel'!$C$38)-'Control Panel'!$B$43,0),'Control Panel'!$B$44-'Control Panel'!$B$43)*'Control Panel'!$C$44+MIN(MAX(MAX(0,K$5-'Control Panel'!$C$38)-'Control Panel'!$B$44,0),'Control Panel'!$B$45-'Control Panel'!$B$44)*'Control Panel'!$C$45+MAX(MAX(0,K$5-'Control Panel'!$C$38)-'Control Panel'!$B$45,0)*'Control Panel'!$C$46),$A15*'Control Panel'!$B$49))
A16: 749 | B16: =(($A16+MIN((MIN(MAX(0,B$5-'Control Panel'!$C$38),'Control Panel'!$B$43)*'Control Panel'!$C$43+MIN(MAX(MAX(0,B$5-'Control Panel'!$C$38)-'Control Panel'!$B$43,0),'Control Panel'!$B$44-'Control Panel'!$B$43)*'Control Panel'!$C$44+MIN(MAX(MAX(0,B$5-'Control Panel'!$C$38)-'Control Panel'!$B$44,0),'Control Panel'!$B$45-'Control Panel'!$B$44)*'Control Panel'!$C$45+MAX(MAX(0,B$5-'Control Panel'!$C$38)-'Control Panel'!$B$45,0)*'Control Panel'!$C$46),$A16*'Control Panel'!$B$49))-('Control Panel'!$B$11+B$5*'Control Panel'!$B$10))/($A16+MIN((MIN(MAX(0,B$5-'Control Panel'!$C$38),'Control Panel'!$B$43)*'Control Panel'!$C$43+MIN(MAX(MAX(0,B$5-'Control Panel'!$C$38)-'Control Panel'!$B$43,0),'Control Panel'!$B$44-'Control Panel'!$B$43)*'Control Panel'!$C$44+MIN(MAX(MAX(0,B$5-'Control Panel'!$C$38)-'Control Panel'!$B$44,0),'Control Panel'!$B$45-'Control Panel'!$B$44)*'Control Panel'!$C$45+MAX(MAX(0,B$5-'Control Panel'!$C$38)-'Control Panel'!$B$45,0)*'Control Panel'!$C$46),$A16*'Control Panel'!$B$49)) | C16: =(($A16+MIN((MIN(MAX(0,C$5-'Control Panel'!$C$38),'Control Panel'!$B$43)*'Control Panel'!$C$43+MIN(MAX(MAX(0,C$5-'Control Panel'!$C$38)-'Control Panel'!$B$43,0),'Control Panel'!$B$44-'Control Panel'!$B$43)*'Control Panel'!$C$44+MIN(MAX(MAX(0,C$5-'Control Panel'!$C$38)-'Control Panel'!$B$44,0),'Control Panel'!$B$45-'Control Panel'!$B$44)*'Control Panel'!$C$45+MAX(MAX(0,C$5-'Control Panel'!$C$38)-'Control Panel'!$B$45,0)*'Control Panel'!$C$46),$A16*'Control Panel'!$B$49))-('Control Panel'!$B$11+C$5*'Control Panel'!$B$10))/($A16+MIN((MIN(MAX(0,C$5-'Control Panel'!$C$38),'Control Panel'!$B$43)*'Control Panel'!$C$43+MIN(MAX(MAX(0,C$5-'Control Panel'!$C$38)-'Control Panel'!$B$43,0),'Control Panel'!$B$44-'Control Panel'!$B$43)*'Control Panel'!$C$44+MIN(MAX(MAX(0,C$5-'Control Panel'!$C$38)-'Control Panel'!$B$44,0),'Control Panel'!$B$45-'Control Panel'!$B$44)*'Control Panel'!$C$45+MAX(MAX(0,C$5-'Control Panel'!$C$38)-'Control Panel'!$B$45,0)*'Control Panel'!$C$46),$A16*'Control Panel'!$B$49)) | D16: =(($A16+MIN((MIN(MAX(0,D$5-'Control Panel'!$C$38),'Control Panel'!$B$43)*'Control Panel'!$C$43+MIN(MAX(MAX(0,D$5-'Control Panel'!$C$38)-'Control Panel'!$B$43,0),'Control Panel'!$B$44-'Control Panel'!$B$43)*'Control Panel'!$C$44+MIN(MAX(MAX(0,D$5-'Control Panel'!$C$38)-'Control Panel'!$B$44,0),'Control Panel'!$B$45-'Control Panel'!$B$44)*'Control Panel'!$C$45+MAX(MAX(0,D$5-'Control Panel'!$C$38)-'Control Panel'!$B$45,0)*'Control Panel'!$C$46),$A16*'Control Panel'!$B$49))-('Control Panel'!$B$11+D$5*'Control Panel'!$B$10))/($A16+MIN((MIN(MAX(0,D$5-'Control Panel'!$C$38),'Control Panel'!$B$43)*'Control Panel'!$C$43+MIN(MAX(MAX(0,D$5-'Control Panel'!$C$38)-'Control Panel'!$B$43,0),'Control Panel'!$B$44-'Control Panel'!$B$43)*'Control Panel'!$C$44+MIN(MAX(MAX(0,D$5-'Control Panel'!$C$38)-'Control Panel'!$B$44,0),'Control Panel'!$B$45-'Control Panel'!$B$44)*'Control Panel'!$C$45+MAX(MAX(0,D$5-'Control Panel'!$C$38)-'Control Panel'!$B$45,0)*'Control Panel'!$C$46),$A16*'Control Panel'!$B$49)) | E16: =(($A16+MIN((MIN(MAX(0,E$5-'Control Panel'!$C$38),'Control Panel'!$B$43)*'Control Panel'!$C$43+MIN(MAX(MAX(0,E$5-'Control Panel'!$C$38)-'Control Panel'!$B$43,0),'Control Panel'!$B$44-'Control Panel'!$B$43)*'Control Panel'!$C$44+MIN(MAX(MAX(0,E$5-'Control Panel'!$C$38)-'Control Panel'!$B$44,0),'Control Panel'!$B$45-'Control Panel'!$B$44)*'Control Panel'!$C$45+MAX(MAX(0,E$5-'Control Panel'!$C$38)-'Control Panel'!$B$45,0)*'Control Panel'!$C$46),$A16*'Control Panel'!$B$49))-('Control Panel'!$B$11+E$5*'Control Panel'!$B$10))/($A16+MIN((MIN(MAX(0,E$5-'Control Panel'!$C$38),'Control Panel'!$B$43)*'Control Panel'!$C$43+MIN(MAX(MAX(0,E$5-'Control Panel'!$C$38)-'Control Panel'!$B$43,0),'Control Panel'!$B$44-'Control Panel'!$B$43)*'Control Panel'!$C$44+MIN(MAX(MAX(0,E$5-'Control Panel'!$C$38)-'Control Panel'!$B$44,0),'Control Panel'!$B$45-'Control Panel'!$B$44)*'Control Panel'!$C$45+MAX(MAX(0,E$5-'Control Panel'!$C$38)-'Control Panel'!$B$45,0)*'Control Panel'!$C$46),$A16*'Control Panel'!$B$49)) | F16: =(($A16+MIN((MIN(MAX(0,F$5-'Control Panel'!$C$38),'Control Panel'!$B$43)*'Control Panel'!$C$43+MIN(MAX(MAX(0,F$5-'Control Panel'!$C$38)-'Control Panel'!$B$43,0),'Control Panel'!$B$44-'Control Panel'!$B$43)*'Control Panel'!$C$44+MIN(MAX(MAX(0,F$5-'Control Panel'!$C$38)-'Control Panel'!$B$44,0),'Control Panel'!$B$45-'Control Panel'!$B$44)*'Control Panel'!$C$45+MAX(MAX(0,F$5-'Control Panel'!$C$38)-'Control Panel'!$B$45,0)*'Control Panel'!$C$46),$A16*'Control Panel'!$B$49))-('Control Panel'!$B$11+F$5*'Control Panel'!$B$10))/($A16+MIN((MIN(MAX(0,F$5-'Control Panel'!$C$38),'Control Panel'!$B$43)*'Control Panel'!$C$43+MIN(MAX(MAX(0,F$5-'Control Panel'!$C$38)-'Control Panel'!$B$43,0),'Control Panel'!$B$44-'Control Panel'!$B$43)*'Control Panel'!$C$44+MIN(MAX(MAX(0,F$5-'Control Panel'!$C$38)-'Control Panel'!$B$44,0),'Control Panel'!$B$45-'Control Panel'!$B$44)*'Control Panel'!$C$45+MAX(MAX(0,F$5-'Control Panel'!$C$38)-'Control Panel'!$B$45,0)*'Control Panel'!$C$46),$A16*'Control Panel'!$B$49)) | G16: =(($A16+MIN((MIN(MAX(0,G$5-'Control Panel'!$C$38),'Control Panel'!$B$43)*'Control Panel'!$C$43+MIN(MAX(MAX(0,G$5-'Control Panel'!$C$38)-'Control Panel'!$B$43,0),'Control Panel'!$B$44-'Control Panel'!$B$43)*'Control Panel'!$C$44+MIN(MAX(MAX(0,G$5-'Control Panel'!$C$38)-'Control Panel'!$B$44,0),'Control Panel'!$B$45-'Control Panel'!$B$44)*'Control Panel'!$C$45+MAX(MAX(0,G$5-'Control Panel'!$C$38)-'Control Panel'!$B$45,0)*'Control Panel'!$C$46),$A16*'Control Panel'!$B$49))-('Control Panel'!$B$11+G$5*'Control Panel'!$B$10))/($A16+MIN((MIN(MAX(0,G$5-'Control Panel'!$C$38),'Control Panel'!$B$43)*'Control Panel'!$C$43+MIN(MAX(MAX(0,G$5-'Control Panel'!$C$38)-'Control Panel'!$B$43,0),'Control Panel'!$B$44-'Control Panel'!$B$43)*'Control Panel'!$C$44+MIN(MAX(MAX(0,G$5-'Control Panel'!$C$38)-'Control Panel'!$B$44,0),'Control Panel'!$B$45-'Control Panel'!$B$44)*'Control Panel'!$C$45+MAX(MAX(0,G$5-'Control Panel'!$C$38)-'Control Panel'!$B$45,0)*'Control Panel'!$C$46),$A16*'Control Panel'!$B$49)) | H16: =(($A16+MIN((MIN(MAX(0,H$5-'Control Panel'!$C$38),'Control Panel'!$B$43)*'Control Panel'!$C$43+MIN(MAX(MAX(0,H$5-'Control Panel'!$C$38)-'Control Panel'!$B$43,0),'Control Panel'!$B$44-'Control Panel'!$B$43)*'Control Panel'!$C$44+MIN(MAX(MAX(0,H$5-'Control Panel'!$C$38)-'Control Panel'!$B$44,0),'Control Panel'!$B$45-'Control Panel'!$B$44)*'Control Panel'!$C$45+MAX(MAX(0,H$5-'Control Panel'!$C$38)-'Control Panel'!$B$45,0)*'Control Panel'!$C$46),$A16*'Control Panel'!$B$49))-('Control Panel'!$B$11+H$5*'Control Panel'!$B$10))/($A16+MIN((MIN(MAX(0,H$5-'Control Panel'!$C$38),'Control Panel'!$B$43)*'Control Panel'!$C$43+MIN(MAX(MAX(0,H$5-'Control Panel'!$C$38)-'Control Panel'!$B$43,0),'Control Panel'!$B$44-'Control Panel'!$B$43)*'Control Panel'!$C$44+MIN(MAX(MAX(0,H$5-'Control Panel'!$C$38)-'Control Panel'!$B$44,0),'Control Panel'!$B$45-'Control Panel'!$B$44)*'Control Panel'!$C$45+MAX(MAX(0,H$5-'Control Panel'!$C$38)-'Control Panel'!$B$45,0)*'Control Panel'!$C$46),$A16*'Control Panel'!$B$49)) | I16: =(($A16+MIN((MIN(MAX(0,I$5-'Control Panel'!$C$38),'Control Panel'!$B$43)*'Control Panel'!$C$43+MIN(MAX(MAX(0,I$5-'Control Panel'!$C$38)-'Control Panel'!$B$43,0),'Control Panel'!$B$44-'Control Panel'!$B$43)*'Control Panel'!$C$44+MIN(MAX(MAX(0,I$5-'Control Panel'!$C$38)-'Control Panel'!$B$44,0),'Control Panel'!$B$45-'Control Panel'!$B$44)*'Control Panel'!$C$45+MAX(MAX(0,I$5-'Control Panel'!$C$38)-'Control Panel'!$B$45,0)*'Control Panel'!$C$46),$A16*'Control Panel'!$B$49))-('Control Panel'!$B$11+I$5*'Control Panel'!$B$10))/($A16+MIN((MIN(MAX(0,I$5-'Control Panel'!$C$38),'Control Panel'!$B$43)*'Control Panel'!$C$43+MIN(MAX(MAX(0,I$5-'Control Panel'!$C$38)-'Control Panel'!$B$43,0),'Control Panel'!$B$44-'Control Panel'!$B$43)*'Control Panel'!$C$44+MIN(MAX(MAX(0,I$5-'Control Panel'!$C$38)-'Control Panel'!$B$44,0),'Control Panel'!$B$45-'Control Panel'!$B$44)*'Control Panel'!$C$45+MAX(MAX(0,I$5-'Control Panel'!$C$38)-'Control Panel'!$B$45,0)*'Control Panel'!$C$46),$A16*'Control Panel'!$B$49)) | ... K16: =(($A16+MIN((MIN(MAX(0,K$5-'Control Panel'!$C$38),'Control Panel'!$B$43)*'Control Panel'!$C$43+MIN(MAX(MAX(0,K$5-'Control Panel'!$C$38)-'Control Panel'!$B$43,0),'Control Panel'!$B$44-'Control Panel'!$B$43)*'Control Panel'!$C$44+MIN(MAX(MAX(0,K$5-'Control Panel'!$C$38)-'Control Panel'!$B$44,0),'Control Panel'!$B$45-'Control Panel'!$B$44)*'Control Panel'!$C$45+MAX(MAX(0,K$5-'Control Panel'!$C$38)-'Control Panel'!$B$45,0)*'Control Panel'!$C$46),$A16*'Control Panel'!$B$49))-('Control Panel'!$B$11+K$5*'Control Panel'!$B$10))/($A16+MIN((MIN(MAX(0,K$5-'Control Panel'!$C$38),'Control Panel'!$B$43)*'Control Panel'!$C$43+MIN(MAX(MAX(0,K$5-'Control Panel'!$C$38)-'Control Panel'!$B$43,0),'Control Panel'!$B$44-'Control Panel'!$B$43)*'Control Panel'!$C$44+MIN(MAX(MAX(0,K$5-'Control Panel'!$C$38)-'Control Panel'!$B$44,0),'Control Panel'!$B$45-'Control Panel'!$B$44)*'Control Panel'!$C$45+MAX(MAX(0,K$5-'Control Panel'!$C$38)-'Control Panel'!$B$45,0)*'Control Panel'!$C$46),$A16*'Control Panel'!$B$49))
A17: 799 | B17: =(($A17+MIN((MIN(MAX(0,B$5-'Control Panel'!$C$38),'Control Panel'!$B$43)*'Control Panel'!$C$43+MIN(MAX(MAX(0,B$5-'Control Panel'!$C$38)-'Control Panel'!$B$43,0),'Control Panel'!$B$44-'Control Panel'!$B$43)*'Control Panel'!$C$44+MIN(MAX(MAX(0,B$5-'Control Panel'!$C$38)-'Control Panel'!$B$44,0),'Control Panel'!$B$45-'Control Panel'!$B$44)*'Control Panel'!$C$45+MAX(MAX(0,B$5-'Control Panel'!$C$38)-'Control Panel'!$B$45,0)*'Control Panel'!$C$46),$A17*'Control Panel'!$B$49))-('Control Panel'!$B$11+B$5*'Control Panel'!$B$10))/($A17+MIN((MIN(MAX(0,B$5-'Control Panel'!$C$38),'Control Panel'!$B$43)*'Control Panel'!$C$43+MIN(MAX(MAX(0,B$5-'Control Panel'!$C$38)-'Control Panel'!$B$43,0),'Control Panel'!$B$44-'Control Panel'!$B$43)*'Control Panel'!$C$44+MIN(MAX(MAX(0,B$5-'Control Panel'!$C$38)-'Control Panel'!$B$44,0),'Control Panel'!$B$45-'Control Panel'!$B$44)*'Control Panel'!$C$45+MAX(MAX(0,B$5-'Control Panel'!$C$38)-'Control Panel'!$B$45,0)*'Control Panel'!$C$46),$A17*'Control Panel'!$B$49)) | C17: =(($A17+MIN((MIN(MAX(0,C$5-'Control Panel'!$C$38),'Control Panel'!$B$43)*'Control Panel'!$C$43+MIN(MAX(MAX(0,C$5-'Control Panel'!$C$38)-'Control Panel'!$B$43,0),'Control Panel'!$B$44-'Control Panel'!$B$43)*'Control Panel'!$C$44+MIN(MAX(MAX(0,C$5-'Control Panel'!$C$38)-'Control Panel'!$B$44,0),'Control Panel'!$B$45-'Control Panel'!$B$44)*'Control Panel'!$C$45+MAX(MAX(0,C$5-'Control Panel'!$C$38)-'Control Panel'!$B$45,0)*'Control Panel'!$C$46),$A17*'Control Panel'!$B$49))-('Control Panel'!$B$11+C$5*'Control Panel'!$B$10))/($A17+MIN((MIN(MAX(0,C$5-'Control Panel'!$C$38),'Control Panel'!$B$43)*'Control Panel'!$C$43+MIN(MAX(MAX(0,C$5-'Control Panel'!$C$38)-'Control Panel'!$B$43,0),'Control Panel'!$B$44-'Control Panel'!$B$43)*'Control Panel'!$C$44+MIN(MAX(MAX(0,C$5-'Control Panel'!$C$38)-'Control Panel'!$B$44,0),'Control Panel'!$B$45-'Control Panel'!$B$44)*'Control Panel'!$C$45+MAX(MAX(0,C$5-'Control Panel'!$C$38)-'Control Panel'!$B$45,0)*'Control Panel'!$C$46),$A17*'Control Panel'!$B$49)) | D17: =(($A17+MIN((MIN(MAX(0,D$5-'Control Panel'!$C$38),'Control Panel'!$B$43)*'Control Panel'!$C$43+MIN(MAX(MAX(0,D$5-'Control Panel'!$C$38)-'Control Panel'!$B$43,0),'Control Panel'!$B$44-'Control Panel'!$B$43)*'Control Panel'!$C$44+MIN(MAX(MAX(0,D$5-'Control Panel'!$C$38)-'Control Panel'!$B$44,0),'Control Panel'!$B$45-'Control Panel'!$B$44)*'Control Panel'!$C$45+MAX(MAX(0,D$5-'Control Panel'!$C$38)-'Control Panel'!$B$45,0)*'Control Panel'!$C$46),$A17*'Control Panel'!$B$49))-('Control Panel'!$B$11+D$5*'Control Panel'!$B$10))/($A17+MIN((MIN(MAX(0,D$5-'Control Panel'!$C$38),'Control Panel'!$B$43)*'Control Panel'!$C$43+MIN(MAX(MAX(0,D$5-'Control Panel'!$C$38)-'Control Panel'!$B$43,0),'Control Panel'!$B$44-'Control Panel'!$B$43)*'Control Panel'!$C$44+MIN(MAX(MAX(0,D$5-'Control Panel'!$C$38)-'Control Panel'!$B$44,0),'Control Panel'!$B$45-'Control Panel'!$B$44)*'Control Panel'!$C$45+MAX(MAX(0,D$5-'Control Panel'!$C$38)-'Control Panel'!$B$45,0)*'Control Panel'!$C$46),$A17*'Control Panel'!$B$49)) | E17: =(($A17+MIN((MIN(MAX(0,E$5-'Control Panel'!$C$38),'Control Panel'!$B$43)*'Control Panel'!$C$43+MIN(MAX(MAX(0,E$5-'Control Panel'!$C$38)-'Control Panel'!$B$43,0),'Control Panel'!$B$44-'Control Panel'!$B$43)*'Control Panel'!$C$44+MIN(MAX(MAX(0,E$5-'Control Panel'!$C$38)-'Control Panel'!$B$44,0),'Control Panel'!$B$45-'Control Panel'!$B$44)*'Control Panel'!$C$45+MAX(MAX(0,E$5-'Control Panel'!$C$38)-'Control Panel'!$B$45,0)*'Control Panel'!$C$46),$A17*'Control Panel'!$B$49))-('Control Panel'!$B$11+E$5*'Control Panel'!$B$10))/($A17+MIN((MIN(MAX(0,E$5-'Control Panel'!$C$38),'Control Panel'!$B$43)*'Control Panel'!$C$43+MIN(MAX(MAX(0,E$5-'Control Panel'!$C$38)-'Control Panel'!$B$43,0),'Control Panel'!$B$44-'Control Panel'!$B$43)*'Control Panel'!$C$44+MIN(MAX(MAX(0,E$5-'Control Panel'!$C$38)-'Control Panel'!$B$44,0),'Control Panel'!$B$45-'Control Panel'!$B$44)*'Control Panel'!$C$45+MAX(MAX(0,E$5-'Control Panel'!$C$38)-'Control Panel'!$B$45,0)*'Control Panel'!$C$46),$A17*'Control Panel'!$B$49)) | F17: =(($A17+MIN((MIN(MAX(0,F$5-'Control Panel'!$C$38),'Control Panel'!$B$43)*'Control Panel'!$C$43+MIN(MAX(MAX(0,F$5-'Control Panel'!$C$38)-'Control Panel'!$B$43,0),'Control Panel'!$B$44-'Control Panel'!$B$43)*'Control Panel'!$C$44+MIN(MAX(MAX(0,F$5-'Control Panel'!$C$38)-'Control Panel'!$B$44,0),'Control Panel'!$B$45-'Control Panel'!$B$44)*'Control Panel'!$C$45+MAX(MAX(0,F$5-'Control Panel'!$C$38)-'Control Panel'!$B$45,0)*'Control Panel'!$C$46),$A17*'Control Panel'!$B$49))-('Control Panel'!$B$11+F$5*'Control Panel'!$B$10))/($A17+MIN((MIN(MAX(0,F$5-'Control Panel'!$C$38),'Control Panel'!$B$43)*'Control Panel'!$C$43+MIN(MAX(MAX(0,F$5-'Control Panel'!$C$38)-'Control Panel'!$B$43,0),'Control Panel'!$B$44-'Control Panel'!$B$43)*'Control Panel'!$C$44+MIN(MAX(MAX(0,F$5-'Control Panel'!$C$38)-'Control Panel'!$B$44,0),'Control Panel'!$B$45-'Control Panel'!$B$44)*'Control Panel'!$C$45+MAX(MAX(0,F$5-'Control Panel'!$C$38)-'Control Panel'!$B$45,0)*'Control Panel'!$C$46),$A17*'Control Panel'!$B$49)) | G17: =(($A17+MIN((MIN(MAX(0,G$5-'Control Panel'!$C$38),'Control Panel'!$B$43)*'Control Panel'!$C$43+MIN(MAX(MAX(0,G$5-'Control Panel'!$C$38)-'Control Panel'!$B$43,0),'Control Panel'!$B$44-'Control Panel'!$B$43)*'Control Panel'!$C$44+MIN(MAX(MAX(0,G$5-'Control Panel'!$C$38)-'Control Panel'!$B$44,0),'Control Panel'!$B$45-'Control Panel'!$B$44)*'Control Panel'!$C$45+MAX(MAX(0,G$5-'Control Panel'!$C$38)-'Control Panel'!$B$45,0)*'Control Panel'!$C$46),$A17*'Control Panel'!$B$49))-('Control Panel'!$B$11+G$5*'Control Panel'!$B$10))/($A17+MIN((MIN(MAX(0,G$5-'Control Panel'!$C$38),'Control Panel'!$B$43)*'Control Panel'!$C$43+MIN(MAX(MAX(0,G$5-'Control Panel'!$C$38)-'Control Panel'!$B$43,0),'Control Panel'!$B$44-'Control Panel'!$B$43)*'Control Panel'!$C$44+MIN(MAX(MAX(0,G$5-'Control Panel'!$C$38)-'Control Panel'!$B$44,0),'Control Panel'!$B$45-'Control Panel'!$B$44)*'Control Panel'!$C$45+MAX(MAX(0,G$5-'Control Panel'!$C$38)-'Control Panel'!$B$45,0)*'Control Panel'!$C$46),$A17*'Control Panel'!$B$49)) | H17: =(($A17+MIN((MIN(MAX(0,H$5-'Control Panel'!$C$38),'Control Panel'!$B$43)*'Control Panel'!$C$43+MIN(MAX(MAX(0,H$5-'Control Panel'!$C$38)-'Control Panel'!$B$43,0),'Control Panel'!$B$44-'Control Panel'!$B$43)*'Control Panel'!$C$44+MIN(MAX(MAX(0,H$5-'Control Panel'!$C$38)-'Control Panel'!$B$44,0),'Control Panel'!$B$45-'Control Panel'!$B$44)*'Control Panel'!$C$45+MAX(MAX(0,H$5-'Control Panel'!$C$38)-'Control Panel'!$B$45,0)*'Control Panel'!$C$46),$A17*'Control Panel'!$B$49))-('Control Panel'!$B$11+H$5*'Control Panel'!$B$10))/($A17+MIN((MIN(MAX(0,H$5-'Control Panel'!$C$38),'Control Panel'!$B$43)*'Control Panel'!$C$43+MIN(MAX(MAX(0,H$5-'Control Panel'!$C$38)-'Control Panel'!$B$43,0),'Control Panel'!$B$44-'Control Panel'!$B$43)*'Control Panel'!$C$44+MIN(MAX(MAX(0,H$5-'Control Panel'!$C$38)-'Control Panel'!$B$44,0),'Control Panel'!$B$45-'Control Panel'!$B$44)*'Control Panel'!$C$45+MAX(MAX(0,H$5-'Control Panel'!$C$38)-'Control Panel'!$B$45,0)*'Control Panel'!$C$46),$A17*'Control Panel'!$B$49)) | I17: =(($A17+MIN((MIN(MAX(0,I$5-'Control Panel'!$C$38),'Control Panel'!$B$43)*'Control Panel'!$C$43+MIN(MAX(MAX(0,I$5-'Control Panel'!$C$38)-'Control Panel'!$B$43,0),'Control Panel'!$B$44-'Control Panel'!$B$43)*'Control Panel'!$C$44+MIN(MAX(MAX(0,I$5-'Control Panel'!$C$38)-'Control Panel'!$B$44,0),'Control Panel'!$B$45-'Control Panel'!$B$44)*'Control Panel'!$C$45+MAX(MAX(0,I$5-'Control Panel'!$C$38)-'Control Panel'!$B$45,0)*'Control Panel'!$C$46),$A17*'Control Panel'!$B$49))-('Control Panel'!$B$11+I$5*'Control Panel'!$B$10))/($A17+MIN((MIN(MAX(0,I$5-'Control Panel'!$C$38),'Control Panel'!$B$43)*'Control Panel'!$C$43+MIN(MAX(MAX(0,I$5-'Control Panel'!$C$38)-'Control Panel'!$B$43,0),'Control Panel'!$B$44-'Control Panel'!$B$43)*'Control Panel'!$C$44+MIN(MAX(MAX(0,I$5-'Control Panel'!$C$38)-'Control Panel'!$B$44,0),'Control Panel'!$B$45-'Control Panel'!$B$44)*'Control Panel'!$C$45+MAX(MAX(0,I$5-'Control Panel'!$C$38)-'Control Panel'!$B$45,0)*'Control Panel'!$C$46),$A17*'Control Panel'!$B$49)) | ... K17: =(($A17+MIN((MIN(MAX(0,K$5-'Control Panel'!$C$38),'Control Panel'!$B$43)*'Control Panel'!$C$43+MIN(MAX(MAX(0,K$5-'Control Panel'!$C$38)-'Control Panel'!$B$43,0),'Control Panel'!$B$44-'Control Panel'!$B$43)*'Control Panel'!$C$44+MIN(MAX(MAX(0,K$5-'Control Panel'!$C$38)-'Control Panel'!$B$44,0),'Control Panel'!$B$45-'Control Panel'!$B$44)*'Control Panel'!$C$45+MAX(MAX(0,K$5-'Control Panel'!$C$38)-'Control Panel'!$B$45,0)*'Control Panel'!$C$46),$A17*'Control Panel'!$B$49))-('Control Panel'!$B$11+K$5*'Control Panel'!$B$10))/($A17+MIN((MIN(MAX(0,K$5-'Control Panel'!$C$38),'Control Panel'!$B$43)*'Control Panel'!$C$43+MIN(MAX(MAX(0,K$5-'Control Panel'!$C$38)-'Control Panel'!$B$43,0),'Control Panel'!$B$44-'Control Panel'!$B$43)*'Control Panel'!$C$44+MIN(MAX(MAX(0,K$5-'Control Panel'!$C$38)-'Control Panel'!$B$44,0),'Control Panel'!$B$45-'Control Panel'!$B$44)*'Control Panel'!$C$45+MAX(MAX(0,K$5-'Control Panel'!$C$38)-'Control Panel'!$B$45,0)*'Control Panel'!$C$46),$A17*'Control Panel'!$B$49))
